Workbook

Sheet Data
A1: Company | B1: PRF_No | C1: PRF_Date | D1: PRF_Location | E1: PRF_Qty | F1: Pack_Size | G1: Conversion_Unit | H1: PRF_Qty_Converted | I1: PO_No | J1: PO_Date | K1: PO_Qty | L1: PO_Rate | M1: PO_Net_Amount | N1: PO_Other_Charge_Percent | O1: PO_Other_Charge_Amount | P1: PO_Total_Amount | Q1: PI_No | R1: PI_Date | S1: Supplier_Name | T1: Item_Code | U1: Product_Name_(DRC) | V1: PI_Qty | W1: PI_FOC_Qty | X1: PI_Rate | Y1: PI_Net_Amount | Z1: PI_Other_Charge_Amount | AA1: PI_Total_Amount | AB1: Advance_Percent | AC1: Advance_Amount | AD1: Advance_Amount_Paid | AE1: Advance_Paid_Date | AF1: Advance_SWIFT_No | AG1: Dispatched_Qty | AH1: Invoice_Qty | AI1: FOC_QTY | AJ1: Short_Excess_Qty | AK1: Invoice_No | AL1: Invoice_Date | AM1: Invoice_Company | AN1: Invoice_Rate | AO1: Invoice_Amount | AP1: Freight | AQ1: Insurance | AR1: Other_Charges | AS1: Invoice_Total_Amount | AT1: BL_No | AU1: BL_Date | AV1: Shipment_Status | AW1: GRN_Qty | AX1: GRN_No | AY1: GRN_Date | AZ1: Prev_Advance_Adjusted | BA1: Available_Advance | BB1: Running_PO_Advance_Used | BC1: Extra_Short_Amount_Used | BD1: Total_Advance_Deducted | BE1: Remaining_Advance | BF1: Advance_Adjusted | BG1: Final_Advance_Remaining | BH1: Final_Payable_Balance | BI1: Balance_Paid_Part1 | BJ1: Balance_Paid_Date_Part1 | BK1: Part1_SWIFT_No | BL1: Balance_Paid_Part2 | BM1: Part2_SWIFT_No | BN1: Balance_Paid_Date_Part2 | BO1: Final_Paid_Total | BP1: Final_Outstanding | BQ1: Payment_Status | BR1: Remarks | BS1: PO_Status | BT1: PO_Age_Days
A2: Aizah Pharma FZCO | B2: 1932.26 | C2: 46188 | D2: Kinshasa | E2: 15000 | F2: 10 ml x 20 Amps | G2: =IF(AG2="","GRN Not Received",AW2/AG2) -> GRN Not Received | H2: =IF(E2="PRF_Details_Not Availbale","PRF Qty Not Available",IF(G2="GRN Not Received","GRN Not Received",--E2*--G2)) -> GRN Not Received | I2: 0131/2026 | J2: 46197 | K2: 300000 | L2: 0.13 | M2: =K2*L2 -> 39000 | N2: 0 | O2: 0 | P2: =M2+O2 -> 39000 | Q2: AFPL/PI/313 | R2: 46197 | S2: Aarmed Formulations Pvt Ltd | T2: NEW 001 | U2: =IFERROR(VLOOKUP(T2,'item master'!B:C,2,0),"") -> DYNAMIQ20 AMP | V2: 300000 | W2: 0 | X2: 0.13 | Y2: =V2*X2 -> 39000 | Z2: 0 | AA2: =Y2+Z2 -> 39000 | AB2: 0.3 | AC2: =Y2*AB2 -> 11700 | AD2: 11700 | AE2: 46203 | AF2: 033DBFC261801579 | AH2: =AG2 -> 0 | AJ2: =V2-AG2 -> 300000 | AS2: =AO2+AP2+AQ2+AR2 -> 0 | AV2: PO Issued – Awaiting BL | BA2: =AD2+AZ2 -> 11700 | BB2: 0 | BC2: 0 | BD2: =IF(AK2>0,BA2+BB2+BC2,"0") -> 0 | BE2: =BA2-BD2 -> 11700 | BF2: 0 | BG2: =BE2-BF2 -> 11700 | BH2: =AS2-BD2 -> 0 | BO2: =BI2+BL2 -> 0 | BP2: =BH2-BO2 -> 0 | BQ2: =IF(ROUND(BG2,2)>0,"Advance With Supplier",IF(ROUND(BP2,2)>0,"Payable Balance Supplier","Fully Paid")) -> Advance With Supplier | BS2: =IF(AX2<>"","Closed","Open") -> Open | BT2: =IF(BS2="Open",TODAY()-J2,"Closed") -> 66
A3: Aizah Pharma FZCO | B3: 1904.26 | C3: 46174 | D3: Kinshasa | E3: 24000 | F3: 125 gm | G3: =IF(AG3="","GRN Not Received",AW3/AG3) -> GRN Not Received | H3: =IF(E3="PRF_Details_Not Availbale","PRF Qty Not Available",IF(G3="GRN Not Received","GRN Not Received",--E3*--G3)) -> GRN Not Received | I3: 0121/2026 | J3: 46211 | K3: =E3 -> 24000 | L3: 0.28 | M3: =K3*L3 -> 6720 | N3: 0 | O3: 0 | P3: =M3+O3 -> 6720 | Q3: 2062026 | R3: 46175 | S3: Kavit Soap Industries | T3: FG08036 | U3: =IFERROR(VLOOKUP(T3,'item master'!B:C,2,0),"") -> DELABACT SAVON ***125GM*** | V3: 24000 | W3: 0 | X3: 0.28 | Y3: =V3*X3 -> 6720 | Z3: 0 | AA3: =Y3+Z3 -> 6720 | AB3: 0.5 | AC3: =Y3*AB3 -> 3360 | AD3: =AC3 -> 3360 | AE3: 46216 | AF3: 033DBFC261920624 | AH3: =AG3 -> 0 | AJ3: =V3-AG3 -> 24000 | AS3: =AO3+AP3+AQ3+AR3 -> 0 | AV3: PO Issued – Awaiting BL | BA3: =AD3+AZ3 -> 3360 | BB3: 0 | BC3: 0 | BD3: =IF(AK3>0,BA3+BB3+BC3,"0") -> 0 | BE3: =BA3-BD3 -> 3360 | BF3: 0 | BG3: =BE3-BF3 -> 3360 | BH3: =AS3-BD3 -> 0 | BO3: =BI3+BL3 -> 0 | BP3: =BH3-BO3 -> 0 | BQ3: =IF(ROUND(BG3,2)>0,"Advance With Supplier",IF(ROUND(BP3,2)>0,"Payable Balance Supplier","Fully Paid")) -> Advance With Supplier | BS3: =IF(AX3<>"","Closed","Open") -> Open | BT3: =IF(BS3="Open",TODAY()-J3,"Closed") -> 52
A4: Aizah Pharma FZCO | B4: 1904.26 | C4: 46174 | D4: Kinshasa | E4: 200000 | F4: 75 gm | G4: =IF(AG4="","GRN Not Received",AW4/AG4) -> GRN Not Received | H4: =IF(E4="PRF_Details_Not Availbale","PRF Qty Not Available",IF(G4="GRN Not Received","GRN Not Received",--E4*--G4)) -> GRN Not Received | I4: 0121/2026 | J4: 46211 | K4: =E4 -> 200000 | L4: 0.2 | M4: =K4*L4 -> 40000 | N4: 0 | O4: 0 | P4: =M4+O4 -> 40000 | Q4: 2062026 | R4: 46175 | S4: Kavit Soap Industries | T4: FG00973 | U4: =IFERROR(VLOOKUP(T4,'item master'!B:C,2,0),"") -> DELABACT SAVON 75GM | V4: 200000 | W4: 0 | X4: 0.2 | Y4: =V4*X4 -> 40000 | Z4: 0 | AA4: =Y4+Z4 -> 40000 | AB4: 0.5 | AC4: =Y4*AB4 -> 20000 | AD4: =AC4 -> 20000 | AE4: 46216 | AF4: 033DBFC261920624 | AH4: =AG4 -> 0 | AJ4: =V4-AG4 -> 200000 | AS4: =AO4+AP4+AQ4+AR4 -> 0 | AV4: PO Issued – Awaiting BL | BA4: =AD4+AZ4 -> 20000 | BB4: 0 | BC4: 0 | BD4: =IF(AK4>0,BA4+BB4+BC4,"0") -> 0 | BE4: =BA4-BD4 -> 20000 | BF4: 0 | BG4: =BE4-BF4 -> 20000 | BH4: =AS4-BD4 -> 0 | BO4: =BI4+BL4 -> 0 | BP4: =BH4-BO4 -> 0 | BQ4: =IF(ROUND(BG4,2)>0,"Advance With Supplier",IF(ROUND(BP4,2)>0,"Payable Balance Supplier","Fully Paid")) -> Advance With Supplier | BS4: =IF(AX4<>"","Closed","Open") -> Open | BT4: =IF(BS4="Open",TODAY()-J4,"Closed") -> 52
A5: Aizah Pharma FZCO | B5: 1904.26 | C5: 46174 | D5: Kinshasa | E5: 12000 | F5: 75 gm | G5: =IF(AG5="","GRN Not Received",AW5/AG5) -> GRN Not Received | H5: =IF(E5="PRF_Details_Not Availbale","PRF Qty Not Available",IF(G5="GRN Not Received","GRN Not Received",--E5*--G5)) -> GRN Not Received | I5: 0121/2026 | J5: 46211 | K5: =E5 -> 12000 | L5: 0.196 | M5: =K5*L5 -> 2352 | N5: 0 | O5: 0 | P5: =M5+O5 -> 2352 | Q5: 2062026 | R5: 46175 | S5: Kavit Soap Industries | T5: FG08549 | U5: =IFERROR(VLOOKUP(T5,'item master'!B:C,2,0),"") -> 20 DEGRE SAVON DE BEAUTE PAPAYE 75G | V5: 12000 | W5: 0 | X5: 0.196 | Y5: =V5*X5 -> 2352 | Z5: 0 | AA5: =Y5+Z5 -> 2352 | AB5: 0.5 | AC5: =Y5*AB5 -> 1176 | AD5: =AC5 -> 1176 | AE5: 46216 | AF5: 033DBFC261920624 | AH5: =AG5 -> 0 | AJ5: =V5-AG5 -> 12000 | AS5: =AO5+AP5+AQ5+AR5 -> 0 | AV5: PO Issued – Awaiting BL | BA5: =AD5+AZ5 -> 1176 | BB5: 0 | BC5: 0 | BD5: =IF(AK5>0,BA5+BB5+BC5,"0") -> 0 | BE5: =BA5-BD5 -> 1176 | BF5: 0 | BG5: =BE5-BF5 -> 1176 | BH5: =AS5-BD5 -> 0 | BO5: =BI5+BL5 -> 0 | BP5: =BH5-BO5 -> 0 | BQ5: =IF(ROUND(BG5,2)>0,"Advance With Supplier",IF(ROUND(BP5,2)>0,"Payable Balance Supplier","Fully Paid")) -> Advance With Supplier | BS5: =IF(AX5<>"","Closed","Open") -> Open | BT5: =IF(BS5="Open",TODAY()-J5,"Closed") -> 52
A6: Aizah Pharma FZCO | B6: 1904.26 | C6: 46174 | D6: Kinshasa | E6: 12000 | F6: 75 gm | G6: =IF(AG6="","GRN Not Received",AW6/AG6) -> GRN Not Received | H6: =IF(E6="PRF_Details_Not Availbale","PRF Qty Not Available",IF(G6="GRN Not Received","GRN Not Received",--E6*--G6)) -> GRN Not Received | I6: 0121/2026 | J6: 46211 | K6: =E6 -> 12000 | L6: 0.28 | M6: =K6*L6 -> 3360 | N6: 0 | O6: 0 | P6: =M6+O6 -> 3360 | Q6: 2062026 | R6: 46175 | S6: Kavit Soap Industries | T6: FG08037 | U6: =IFERROR(VLOOKUP(T6,'item master'!B:C,2,0),"") -> KETOMIZ SAVON 75GM | V6: 12000 | W6: 0 | X6: 0.28 | Y6: =V6*X6 -> 3360 | Z6: 0 | AA6: =Y6+Z6 -> 3360 | AB6: 0.5 | AC6: =Y6*AB6 -> 1680 | AD6: =AC6 -> 1680 | AE6: 46216 | AF6: 033DBFC261920624 | AH6: =AG6 -> 0 | AJ6: =V6-AG6 -> 12000 | AS6: =AO6+AP6+AQ6+AR6 -> 0 | AV6: PO Issued – Awaiting BL | BA6: =AD6+AZ6 -> 1680 | BB6: 0 | BC6: 0 | BD6: =IF(AK6>0,BA6+BB6+BC6,"0") -> 0 | BE6: =BA6-BD6 -> 1680 | BF6: 0 | BG6: =BE6-BF6 -> 1680 | BH6: =AS6-BD6 -> 0 | BO6: =BI6+BL6 -> 0 | BP6: =BH6-BO6 -> 0 | BQ6: =IF(ROUND(BG6,2)>0,"Advance With Supplier",IF(ROUND(BP6,2)>0,"Payable Balance Supplier","Fully Paid")) -> Advance With Supplier | BS6: =IF(AX6<>"","Closed","Open") -> Open | BT6: =IF(BS6="Open",TODAY()-J6,"Closed") -> 52
A7: Aizah Pharma FZCO | B7: 1904.26 | C7: 46174 | D7: Kinshasa | E7: 12000 | F7: 100 gm | G7: =IF(AG7="","GRN Not Received",AW7/AG7) -> GRN Not Received | H7: =IF(E7="PRF_Details_Not Availbale","PRF Qty Not Available",IF(G7="GRN Not Received","GRN Not Received",--E7*--G7)) -> GRN Not Received | I7: 0121/2026 | J7: 46211 | K7: =E7 -> 12000 | L7: 0.276 | M7: =K7*L7 -> 3312 | N7: 0 | O7: 0 | P7: =M7+O7 -> 3312 | Q7: 2062026 | R7: 46175 | S7: Kavit Soap Industries | T7: FG08548 | U7: =IFERROR(VLOOKUP(T7,'item master'!B:C,2,0),"") -> GERMITTOL SAVON 100 GM | V7: 12000 | W7: 0 | X7: 0.276 | Y7: =V7*X7 -> 3312 | Z7: 0 | AA7: =Y7+Z7 -> 3312 | AB7: 0.5 | AC7: =Y7*AB7 -> 1656 | AD7: =AC7 -> 1656 | AE7: 46216 | AF7: 033DBFC261920624 | AH7: =AG7 -> 0 | AJ7: =V7-AG7 -> 12000 | AS7: =AO7+AP7+AQ7+AR7 -> 0 | AV7: PO Issued – Awaiting BL | BA7: =AD7+AZ7 -> 1656 | BB7: 0 | BC7: 0 | BD7: =IF(AK7>0,BA7+BB7+BC7,"0") -> 0 | BE7: =BA7-BD7 -> 1656 | BF7: 0 | BG7: =BE7-BF7 -> 1656 | BH7: =AS7-BD7 -> 0 | BO7: =BI7+BL7 -> 0 | BP7: =BH7-BO7 -> 0 | BQ7: =IF(ROUND(BG7,2)>0,"Advance With Supplier",IF(ROUND(BP7,2)>0,"Payable Balance Supplier","Fully Paid")) -> Advance With Supplier | BS7: =IF(AX7<>"","Closed","Open") -> Open | BT7: =IF(BS7="Open",TODAY()-J7,"Closed") -> 52
A8: Aizah Pharma FZCO | B8: 1904.26 | C8: 46174 | D8: Kinshasa | E8: 30000 | F8: 100 gm | G8: =IF(AG8="","GRN Not Received",AW8/AG8) -> GRN Not Received | H8: =IF(E8="PRF_Details_Not Availbale","PRF Qty Not Available",IF(G8="GRN Not Received","GRN Not Received",--E8*--G8)) -> GRN Not Received | I8: 0121/2026 | J8: 46211 | K8: =E8 -> 30000 | L8: 0.24 | M8: =K8*L8 -> 7200 | N8: 0 | O8: 0 | P8: =M8+O8 -> 7200 | Q8: 2062026 | R8: 46175 | S8: Kavit Soap Industries | T8: FG08555 | U8: =IFERROR(VLOOKUP(T8,'item master'!B:C,2,0),"") -> 20 DEGRE TALC (NEEM+MENTHE) 100G | V8: 30000 | W8: 0 | X8: 0.24 | Y8: =V8*X8 -> 7200 | Z8: 0 | AA8: =Y8+Z8 -> 7200 | AB8: 0.5 | AC8: =Y8*AB8 -> 3600 | AD8: =AC8 -> 3600 | AE8: 46216 | AF8: 033DBFC261920624 | AH8: =AG8 -> 0 | AJ8: =V8-AG8 -> 30000 | AS8: =AO8+AP8+AQ8+AR8 -> 0 | AV8: PO Issued – Awaiting BL | BA8: =AD8+AZ8 -> 3600 | BB8: 0 | BC8: 0 | BD8: =IF(AK8>0,BA8+BB8+BC8,"0") -> 0 | BE8: =BA8-BD8 -> 3600 | BF8: 0 | BG8: =BE8-BF8 -> 3600 | BH8: =AS8-BD8 -> 0 | BO8: =BI8+BL8 -> 0 | BP8: =BH8-BO8 -> 0 | BQ8: =IF(ROUND(BG8,2)>0,"Advance With Supplier",IF(ROUND(BP8,2)>0,"Payable Balance Supplier","Fully Paid")) -> Advance With Supplier | BS8: =IF(AX8<>"","Closed","Open") -> Open | BT8: =IF(BS8="Open",TODAY()-J8,"Closed") -> 52
A9: Unique Ventures | B9: PRF_Details_Not Availbale | C9: PRF_Details_Not Availbale | D9: Kinshasa | E9: PRF_Details_Not Availbale | F9: Per Pack 100 Amp | G9: =IF(AG9="","GRN Not Received",AW9/AG9) -> 10 | H9: =IF(E9="PRF_Details_Not Availbale","PRF Qty Not Available",IF(G9="GRN Not Received","GRN Not Received",--E9*--G9)) -> PRF Qty Not Available | I9: 043/2024 | J9: 45388 | K9: 4000 | L9: 4.4 | M9: =K9*L9 -> 17600 | N9: 0 | O9: 0 | P9: =M9+O9 -> 17600 | Q9: 23-24/108 | R9: 45381 | S9: Pharmax India Pvt Ltd | T9: FG03867 | U9: =IFERROR(VLOOKUP(T9,'item master'!B:C,2,0),"") -> DIAZEPAM 10MG/2ML INJ B/10AMP | V9: =K9 -> 4000 | W9: 0 | X9: =L9 -> 4.4 | Y9: =V9*X9 -> 17600 | Z9: 0 | AA9: =Y9+Z9 -> 17600 | AB9: 0.3 | AC9: =Y9*AB9 -> 5280 | AD9: =AC9 -> 5280 | AE9: 45463 | AF9: EPHCOP17203Y9ZGA | AG9: 4000 | AH9: =AG9 -> 4000 | AJ9: =V9-AG9 -> 0 | AK9: 24-25/105 | AL9: 45479 | AM9: UNIQUE VENTURES | AN9: 4.4 | AO9: =AG9*AN9 -> 17600 | AS9: =AO9+AP9+AQ9+AR9 -> 17600 | AT9: 242156078 | AU9: 45525 | AV9: Goods Received at Warehouse | AW9: 40000 | AX9: 24KIN/IGRN000261 | AY9: 45573 | AZ9: 0 | BA9: =AD9+AZ9 -> 5280 | BB9: 0 | BC9: 0 | BD9: =IF(AK9>0,BA9+BB9+BC9,"0") -> 5280 | BE9: =BA9-BD9 -> 0 | BF9: 0 | BG9: =BE9-BF9 -> 0 | BH9: =AS9-BD9 -> 12320 | BI9: =BH9 -> 12320 | BJ9: 45500 | BK9: EPHCOP209047ZI1N | BO9: =BI9+BL9 -> 12320 | BP9: =BH9-BO9 -> 0 | BQ9: =IF(ROUND(BG9,2)>0,"Advance With Supplier",IF(ROUND(BP9,2)>0,"Payable Balance Supplier","Fully Paid")) -> Fully Paid | BS9: =IF(AX9<>"","Closed","Open") -> Closed | BT9: =IF(BS9="Open",TODAY()-J9,"Closed") -> Closed
A10: Unique Ventures | B10: PRF_Details_Not Availbale | C10: PRF_Details_Not Availbale | D10: Kinshasa | E10: PRF_Details_Not Availbale | F10: 0 | G10: =IF(AG10="","GRN Not Received",AW10/AG10) -> 1 | H10: =IF(E10="PRF_Details_Not Availbale","PRF Qty Not Available",IF(G10="GRN Not Received","GRN Not Received",--E10*--G10)) -> PRF Qty Not Available | I10: 043/2024 | J10: 45388 | K10: 1000000 | L10: 0.09 | M10: =K10*L10 -> 90000 | N10: 0 | O10: 0 | P10: =M10+O10 -> 90000 | Q10: 23-24/108 | R10: 45381 | S10: Pharmax India Pvt Ltd | T10: FG04047 | U10: =IFERROR(VLOOKUP(T10,'item master'!B:C,2,0),"") -> LINCOMYCINE 600MG INJ.B/1 VIAL | V10: =K10 -> 1000000 | W10: 0 | X10: =L10 -> 0.09 | Y10: =V10*X10 -> 90000 | Z10: 0 | AA10: =Y10+Z10 -> 90000 | AB10: 0.3 | AC10: =Y10*AB10 -> 27000 | AD10: =AC10 -> 27000 | AE10: 45463 | AF10: EPHCOP17203Y9ZGA | AG10: 1011000 | AH10: =AG10 -> 1011000 | AJ10: =V10-AG10 -> -11000 | AK10: 24-25/105 | AL10: 45479 | AM10: UNIQUE VENTURES | AN10: 0.09 | AO10: =AG10*AN10 -> 90990 | AS10: =AO10+AP10+AQ10+AR10 -> 90990 | AT10: 242156078 | AU10: 45525 | AV10: Goods Received at Warehouse | AW10: =926000+85000 -> 1011000 | AX10: 24KIN/IGRN000261 & 24KIN/IGRN000302 | AY10: 08-10-2024 & 12-11-2024 | AZ10: 0 | BA10: =AD10+AZ10 -> 27000 | BB10: 0 | BC10: 297 | BD10: =IF(AK10>0,BA10+BB10+BC10,"0") -> 27297 | BE10: =BA10-BD10 -> -297 | BF10: -297 | BG10: =BE10-BF10 -> 0 | BH10: =AS10-BD10 -> 63693 | BI10: =BH10 -> 63693 | BJ10: 45500 | BK10: EPHCOP209047ZI1N | BO10: =BI10+BL10 -> 63693 | BP10: =BH10-BO10 -> 0 | BQ10: =IF(ROUND(BG10,2)>0,"Advance With Supplier",IF(ROUND(BP10,2)>0,"Payable Balance Supplier","Fully Paid")) -> Fully Paid | BR10: TWO GRN | BS10: =IF(AX10<>"","Closed","Open") -> Closed | BT10: =IF(BS10="Open",TODAY()-J10,"Closed") -> Closed
A11: Unique Ventures | B11: PRF_Details_Not Availbale | C11: PRF_Details_Not Availbale | D11: Kinshasa | E11: PRF_Details_Not Availbale | F11: Per Pack 100 Amp | G11: =IF(AG11="","GRN Not Received",AW11/AG11) -> 10 | H11: =IF(E11="PRF_Details_Not Availbale","PRF Qty Not Available",IF(G11="GRN Not Received","GRN Not Received",--E11*--G11)) -> PRF Qty Not Available | I11: 043/2024 | J11: 45388 | K11: 2000 | L11: 5.3 | M11: =K11*L11 -> 10600 | N11: 0 | O11: 0 | P11: =M11+O11 -> 10600 | Q11: 23-24/108 | R11: 45381 | S11: Pharmax India Pvt Ltd | T11: FG01261 | U11: =IFERROR(VLOOKUP(T11,'item master'!B:C,2,0),"") -> ERGOMETRINE B/10AMP | V11: =K11 -> 2000 | W11: 0 | X11: =L11 -> 5.3 | Y11: =V11*X11 -> 10600 | Z11: 0 | AA11: =Y11+Z11 -> 10600 | AB11: 0.3 | AC11: =Y11*AB11 -> 3180 | AD11: =AC11 -> 3180 | AE11: 45463 | AF11: EPHCOP17203Y9ZGA | AG11: 2000 | AH11: =AG11 -> 2000 | AJ11: =V11-AG11 -> 0 | AK11: 24-25/078 | AL11: 45457 | AM11: UNIQUE VENTURES | AN11: 5.3 | AO11: =AG11*AN11 -> 10600 | AS11: =AO11+AP11+AQ11+AR11 -> 10600 | AT11: AMC2229366 | AU11: 45500 | AV11: Goods Received at Warehouse | AW11: 20000 | AX11: 24KIN/IGRN000234 | AY11: 45544 | AZ11: 0 | BA11: =AD11+AZ11 -> 3180 | BB11: 0 | BC11: 0 | BD11: =IF(AK11>0,BA11+BB11+BC11,"0") -> 3180 | BE11: =BA11-BD11 -> 0 | BF11: 0 | BG11: =BE11-BF11 -> 0 | BH11: =AS11-BD11 -> 7420 | BI11: =BH11 -> 7420 | BJ11: 45500 | BK11: EPHCOP209047ZI1N | BO11: =BI11+BL11 -> 7420 | BP11: =BH11-BO11 -> 0 | BQ11: =IF(ROUND(BG11,2)>0,"Advance With Supplier",IF(ROUND(BP11,2)>0,"Payable Balance Supplier","Fully Paid")) -> Fully Paid | BS11: =IF(AX11<>"","Closed","Open") -> Closed | BT11: =IF(BS11="Open",TODAY()-J11,"Closed") -> Closed
A12: Unique Ventures | B12: PRF_Details_Not Availbale | C12: PRF_Details_Not Availbale | D12: Kinshasa | E12: PRF_Details_Not Availbale | F12: Vial of 20 mL | G12: =IF(AG12="","GRN Not Received",AW12/AG12) -> 1 | H12: =IF(E12="PRF_Details_Not Availbale","PRF Qty Not Available",IF(G12="GRN Not Received","GRN Not Received",--E12*--G12)) -> PRF Qty Not Available | I12: 043/2024 | J12: 45388 | K12: 100000 | L12: 0.11 | M12: =K12*L12 -> 11000 | N12: 0 | O12: 0 | P12: =M12+O12 -> 11000 | Q12: 23-24/108 | R12: 45381 | S12: Pharmax India Pvt Ltd | T12: FG04097 | U12: =IFERROR(VLOOKUP(T12,'item master'!B:C,2,0),"") -> UNICAINE 2% (LIDOCAIN) INJ. FL/20ML | V12: =K12 -> 100000 | W12: 0 | X12: =L12 -> 0.11 | Y12: =V12*X12 -> 11000 | Z12: 0 | AA12: =Y12+Z12 -> 11000 | AB12: 0.3 | AC12: =Y12*AB12 -> 3300 | AD12: =AC12 -> 3300 | AE12: 45463 | AF12: EPHCOP17203Y9ZGA | AG12: 100000 | AH12: =AG12 -> 100000 | AJ12: =V12-AG12 -> 0 | AK12: 24-25/078 | AL12: 45457 | AM12: UNIQUE VENTURES | AN12: 0.11 | AO12: =AG12*AN12 -> 11000 | AS12: =AO12+AP12+AQ12+AR12 -> 11000 | AT12: AMC2229366 | AU12: 45500 | AV12: Goods Received at Warehouse | AW12: 100000 | AX12: 24KIN/IGRN000234 | AY12: 45544 | AZ12: 0 | BA12: =AD12+AZ12 -> 3300 | BB12: 0 | BC12: 0 | BD12: =IF(AK12>0,BA12+BB12+BC12,"0") -> 3300 | BE12: =BA12-BD12 -> 0 | BF12: 0 | BG12: =BE12-BF12 -> 0 | BH12: =AS12-BD12 -> 7700 | BI12: =BH12 -> 7700 | BJ12: 45500 | BK12: EPHCOP209047ZI1N | BO12: =BI12+BL12 -> 7700 | BP12: =BH12-BO12 -> 0 | BQ12: =IF(ROUND(BG12,2)>0,"Advance With Supplier",IF(ROUND(BP12,2)>0,"Payable Balance Supplier","Fully Paid")) -> Fully Paid | BS12: =IF(AX12<>"","Closed","Open") -> Closed | BT12: =IF(BS12="Open",TODAY()-J12,"Closed") -> Closed
A13: Unique Ventures | B13: PRF_Details_Not Availbale | C13: PRF_Details_Not Availbale | D13: Kinshasa | E13: PRF_Details_Not Availbale | F13: Vial of 20 mL | G13: =IF(AG13="","GRN Not Received",AW13/AG13) -> 1 | H13: =IF(E13="PRF_Details_Not Availbale","PRF Qty Not Available",IF(G13="GRN Not Received","GRN Not Received",--E13*--G13)) -> PRF Qty Not Available | I13: 043/2024 | J13: 45388 | K13: 0 | L13: 0 | M13: =K13*L13 -> 0 | N13: 0 | O13: 0 | P13: =M13+O13 -> 0 | Q13: 23-24/108 | R13: 45381 | S13: Pharmax India Pvt Ltd | T13: FG04097 | U13: =IFERROR(VLOOKUP(T13,'item master'!B:C,2,0),"") -> UNICAINE 2% (LIDOCAIN) INJ. FL/20ML | V13: =K13 -> 0 | W13: 0 | X13: =L13 -> 0 | Y13: =V13*X13 -> 0 | Z13: 0 | AA13: =Y13+Z13 -> 0 | AD13: 0 | AG13: 1600 | AH13: =AG13 -> 1600 | AJ13: =V13-AG13 -> -1600 | AK13: 24-25/387 | AL13: 45668 | AM13: UNIQUE VENTURES | AN13: 0.11 | AO13: =AG13*AN13 -> 176 | AS13: =AO13+AP13+AQ13+AR13 -> 176 | AT13: AMC2353209 | AU13: 45700 | AV13: Goods Received at Warehouse | AW13: 1600 | AX13: 25KIN1/IGRN000048 | AY13: 45747 | AZ13: 0 | BA13: =AD13+AZ13 -> 0 | BB13: 0 | BC13: 0 | BD13: =IF(AK13>0,BA13+BB13+BC13,"0") -> 0 | BE13: =BA13-BD13 -> 0 | BF13: 0 | BG13: =BE13-BF13 -> 0 | BH13: =AS13-BD13 -> 176 | BI13: =BH13 -> 176 | BJ13: 45765 | BK13: SWIFT COPY NOT AVAILABLE | BO13: =BI13+BL13 -> 176 | BP13: =BH13-BO13 -> 0 | BQ13: =IF(ROUND(BG13,2)>0,"Advance With Supplier",IF(ROUND(BP13,2)>0,"Payable Balance Supplier","Fully Paid")) -> Fully Paid | BS13: =IF(AX13<>"","Closed","Open") -> Closed | BT13: =IF(BS13="Open",TODAY()-J13,"Closed") -> Closed
A14: Unique Ventures | B14: PRF_Details_Not Availbale | C14: PRF_Details_Not Availbale | D14: Kinshasa | E14: PRF_Details_Not Availbale | F14: Per Vial | G14: =IF(AG14="","GRN Not Received",AW14/AG14) -> 1 | H14: =IF(E14="PRF_Details_Not Availbale","PRF Qty Not Available",IF(G14="GRN Not Received","GRN Not Received",--E14*--G14)) -> PRF Qty Not Available | I14: 043/2024 | J14: 45388 | K14: 20000 | L14: 0.5 | M14: =K14*L14 -> 10000 | N14: 0 | O14: 0 | P14: =M14+O14 -> 10000 | Q14: 23-24/108 | R14: 45381 | S14: Pharmax India Pvt Ltd | T14: FG06812 | U14: =IFERROR(VLOOKUP(T14,'item master'!B:C,2,0),"") -> UNIKORT-80 (TRIAMCINOLONE) B/1 VIAL +SER | V14: =K14 -> 20000 | W14: 0 | X14: =L14 -> 0.5 | Y14: =V14*X14 -> 10000 | Z14: 0 | AA14: =Y14+Z14 -> 10000 | AB14: 0.3 | AC14: =Y14*AB14 -> 3000 | AD14: =AC14 -> 3000 | AE14: 45463 | AF14: EPHCOP17203Y9ZGA | AG14: 19800 | AH14: =AG14 -> 19800 | AJ14: =V14-AG14 -> 200 | AK14: 24-25/105 | AL14: 45457 | AM14: UNIQUE VENTURES | AN14: 0.5 | AO14: =AG14*AN14 -> 9900 | AS14: =AO14+AP14+AQ14+AR14 -> 9900 | AT14: 242156078 | AU14: 45525 | AV14: Goods Received at Warehouse | AW14: 19800 | AX14: 24KIN/IGRN000261 | AY14: 45573 | AZ14: 0 | BA14: =AD14+AZ14 -> 3000 | BB14: 0 | BC14: -30 | BD14: =IF(AK14>0,BA14+BB14+BC14,"0") -> 2970 | BE14: =BA14-BD14 -> 30 | BF14: 30 | BG14: =BE14-BF14 -> 0 | BH14: =AS14-BD14 -> 6930 | BI14: =BH14 -> 6930 | BJ14: 45500 | BK14: EPHCOP209047ZI1N | BO14: =BI14+BL14 -> 6930 | BP14: =BH14-BO14 -> 0 | BQ14: =IF(ROUND(BG14,2)>0,"Advance With Supplier",IF(ROUND(BP14,2)>0,"Payable Balance Supplier","Fully Paid")) -> Fully Paid | BS14: =IF(AX14<>"","Closed","Open") -> Closed | BT14: =IF(BS14="Open",TODAY()-J14,"Closed") -> Closed
A15: Unique Ventures | B15: PRF_Details_Not Availbale | C15: PRF_Details_Not Availbale | D15: Kinshasa | E15: PRF_Details_Not Availbale | F15: 0 | G15: =IF(AG15="","GRN Not Received",AW15/AG15) -> 1 | H15: =IF(E15="PRF_Details_Not Availbale","PRF Qty Not Available",IF(G15="GRN Not Received","GRN Not Received",--E15*--G15)) -> PRF Qty Not Available | I15: 043/2024 | J15: 45388 | K15: 10000 | L15: 1.1 | M15: =K15*L15 -> 11000 | N15: 0 | O15: 0 | P15: =M15+O15 -> 11000 | Q15: 23-24/108 | R15: 45381 | S15: Pharmax India Pvt Ltd | T15: FG06678 | U15: =IFERROR(VLOOKUP(T15,'item master'!B:C,2,0),"") -> HEPAQUE (HEPARIN) 25000UI/5ML INJ. B/1 VIAL | V15: =K15 -> 10000 | W15: 0 | X15: =L15 -> 1.1 | Y15: =V15*X15 -> 11000 | Z15: 0 | AA15: =Y15+Z15 -> 11000 | AB15: 0.3 | AC15: =Y15*AB15 -> 3300 | AD15: =AC15 -> 3300 | AE15: 45463 | AF15: EPHCOP17203Y9ZGA | AG15: 9600 | AH15: =AG15 -> 9600 | AJ15: =V15-AG15 -> 400 | AK15: 24-25/322 | AL15: 45625 | AM15: UNIQUE VENTURES | AN15: =X15 -> 1.1 | AO15: =AG15*AN15 -> 10560 | AS15: =AO15+AP15+AQ15+AR15 -> 10560 | AT15: AMC2336146 | AU15: 45667 | AV15: Goods Received at Warehouse | AW15: 9600 | AX15: 25KIN/IGRN000021 | AY15: 45721 | AZ15: -297 | BA15: =AD15+AZ15 -> 3003 | BB15: 450 | BC15: 80 | BD15: =IF(AK15>0,BA15+BB15+BC15,"0") -> 3533 | BE15: =BA15-BD15 -> -530 | BF15: -530 | BG15: =BE15-BF15 -> 0 | BH15: =AS15-BD15 -> 7027 | BI15: =BH15 -> 7027 | BJ15: 45765 | BK15: SWIFT COPY NOT AVAILABLE | BO15: =BI15+BL15 -> 7027 | BP15: =BH15-BO15 -> 0 | BQ15: =IF(ROUND(BG15,2)>0,"Advance With Supplier",IF(ROUND(BP15,2)>0,"Payable Balance Supplier","Fully Paid")) -> Fully Paid | BS15: =IF(AX15<>"","Closed","Open") -> Closed | BT15: =IF(BS15="Open",TODAY()-J15,"Closed") -> Closed
A16: Unique Ventures | B16: PRF_Details_Not Availbale | C16: PRF_Details_Not Availbale | D16: Kinshasa | E16: PRF_Details_Not Availbale | F16: Per Vial | G16: =IF(AG16="","GRN Not Received",AW16/AG16) -> 1 | H16: =IF(E16="PRF_Details_Not Availbale","PRF Qty Not Available",IF(G16="GRN Not Received","GRN Not Received",--E16*--G16)) -> PRF Qty Not Available | I16: 043/2024 | J16: 45388 | K16: 30000 | L16: 0.95 | M16: =K16*L16 -> 28500 | N16: 0 | O16: 0 | P16: =M16+O16 -> 28500 | Q16: 23-24/108 | R16: 45381 | S16: Pharmax India Pvt Ltd | T16: FG06804 | U16: =IFERROR(VLOOKUP(T16,'item master'!B:C,2,0),"") -> TROBINIQUE-2G(SPECTINOMYCIN) B/1VIAL+3.2MLE.D | V16: =K16 -> 30000 | W16: 0 | X16: =L16 -> 0.95 | Y16: =V16*X16 -> 28500 | Z16: 0 | AA16: =Y16+Z16 -> 28500 | AB16: 0.3 | AC16: =Y16*AB16 -> 8550 | AD16: =AC16 -> 8550 | AE16: 45463 | AF16: EPHCOP17203Y9ZGA | AG16: 30000 | AH16: =AG16 -> 30000 | AJ16: =V16-AG16 -> 0 | AK16: 24-25/105 | AL16: 45479 | AM16: UNIQUE VENTURES | AN16: 0.95 | AO16: =AG16*AN16 -> 28500 | AS16: =AO16+AP16+AQ16+AR16 -> 28500 | AT16: 242156078 | AU16: 45525 | AV16: Goods Received at Warehouse | AW16: 30000 | AX16: 24KIN/IGRN000261 | AY16: 45573 | AZ16: 0 | BA16: =AD16+AZ16 -> 8550 | BB16: 0 | BC16: 0 | BD16: =IF(AK16>0,BA16+BB16+BC16,"0") -> 8550 | BE16: =BA16-BD16 -> 0 | BF16: 0 | BG16: =BE16-BF16 -> 0 | BH16: =AS16-BD16 -> 19950 | BI16: =BH16 -> 19950 | BJ16: 45500 | BK16: EPHCOP209047ZI1N | BO16: =BI16+BL16 -> 19950 | BP16: =BH16-BO16 -> 0 | BQ16: =IF(ROUND(BG16,2)>0,"Advance With Supplier",IF(ROUND(BP16,2)>0,"Payable Balance Supplier","Fully Paid")) -> Fully Paid | BS16: =IF(AX16<>"","Closed","Open") -> Closed | BT16: =IF(BS16="Open",TODAY()-J16,"Closed") -> Closed
A17: Unique Ventures | B17: PRF_Details_Not Availbale | C17: PRF_Details_Not Availbale | D17: Kinshasa | E17: PRF_Details_Not Availbale | F17: 0 | G17: =IF(AG17="","GRN Not Received",AW17/AG17) -> 1 | H17: =IF(E17="PRF_Details_Not Availbale","PRF Qty Not Available",IF(G17="GRN Not Received","GRN Not Received",--E17*--G17)) -> PRF Qty Not Available | I17: 043/2024 | J17: 45388 | K17: 2000 | L17: 2.2 | M17: =K17*L17 -> 4400 | N17: 0 | O17: 0 | P17: =M17+O17 -> 4400 | Q17: 23-24/108 | R17: 45381 | S17: Pharmax India Pvt Ltd | T17: FG07424 | U17: =IFERROR(VLOOKUP(T17,'item master'!B:C,2,0),"") -> PANCUR 4MG/2ML (PANCURONIUM) INJ. B/10 AMP | V17: =K17 -> 2000 | W17: 0 | X17: =L17 -> 2.2 | Y17: =V17*X17 -> 4400 | Z17: 0 | AA17: =Y17+Z17 -> 4400 | AB17: 0.3 | AC17: =Y17*AB17 -> 1320 | AD17: =AC17 -> 1320 | AE17: 45463 | AF17: EPHCOP17203Y9ZGA | AG17: 1970 | AH17: =AG17 -> 1970 | AJ17: =V17-AG17 -> 30 | AK17: 24-25/192 | AL17: 45537 | AM17: UNIQUE VENTURES | AN17: 2.2 | AO17: =AG17*AN17 -> 4334 | AS17: =AO17+AP17+AQ17+AR17 -> 4334 | AT17: 244450371 | AV17: Goods Received at Warehouse | AW17: 1970 | AX17: 24KIN/IGRN000302 | AY17: 45608 | AZ17: 0 | BA17: =AD17+AZ17 -> 1320 | BB17: 0 | BC17: -19.8 | BD17: =IF(AK17>0,BA17+BB17+BC17,"0") -> 1300.2 | BE17: =BA17-BD17 -> 19.8 | BF17: 19.8 | BG17: =BE17-BF17 -> -4.6185278e-14 | BH17: =AS17-BD17 -> 3033.8 | BI17: =BH17 -> 3033.8 | BJ17: 45586 | BK17: EPHCOP29504UC6MI | BO17: =BI17+BL17 -> 3033.8 | BP17: =BH17-BO17 -> 0 | BQ17: =IF(ROUND(BG17,2)>0,"Advance With Supplier",IF(ROUND(BP17,2)>0,"Payable Balance Supplier","Fully Paid")) -> Fully Paid | BS17: =IF(AX17<>"","Closed","Open") -> Closed | BT17: =IF(BS17="Open",TODAY()-J17,"Closed") -> Closed
A18: Unique Ventures | B18: PRF_Details_Not Availbale | C18: PRF_Details_Not Availbale | D18: Kinshasa | E18: PRF_Details_Not Availbale | F18: 0 | G18: =IF(AG18="","GRN Not Received",AW18/AG18) -> 1 | H18: =IF(E18="PRF_Details_Not Availbale","PRF Qty Not Available",IF(G18="GRN Not Received","GRN Not Received",--E18*--G18)) -> PRF Qty Not Available | I18: 043/2024 | J18: 45388 | K18: 100000 | L18: 0.0675 | M18: =K18*L18 -> 6750 | N18: 0 | O18: 0 | P18: =M18+O18 -> 6750 | Q18: 23-24/108 | R18: 45381 | S18: Pharmax India Pvt Ltd | T18: FG04611 | U18: =IFERROR(VLOOKUP(T18,'item master'!B:C,2,0),"") -> CHLORAMPHENICOL 0.5% COLLYRE 10ML | V18: =K18 -> 100000 | W18: 0 | X18: =L18 -> 0.0675 | Y18: =V18*X18 -> 6750 | Z18: 0 | AA18: =Y18+Z18 -> 6750 | AB18: 0.3 | AC18: =Y18*AB18 -> 2025 | AD18: =AC18 -> 2025 | AE18: 45463 | AF18: EPHCOP17203Y9ZGA | AG18: 99320 | AH18: =AG18 -> 99320 | AJ18: =V18-AG18 -> 680 | AK18: 24-25/105 | AL18: 45479 | AM18: UNIQUE VENTURES | AN18: 0.0675 | AO18: =AG18*AN18 -> 6704.1 | AS18: =AO18+AP18+AQ18+AR18 -> 6704.1 | AT18: 242156078 | AU18: 45525 | AV18: Goods Received at Warehouse | AW18: 99320 | AX18: 24KIN/IGRN000261 | AY18: 45573 | AZ18: 0 | BA18: =AD18+AZ18 -> 2025 | BB18: 0 | BC18: -13.77 | BD18: =IF(AK18>0,BA18+BB18+BC18,"0") -> 2011.23 | BE18: =BA18-BD18 -> 13.77 | BF18: 13.77 | BG18: =BE18-BF18 -> -1.7763568e-14 | BH18: =AS18-BD18 -> 4692.87 | BI18: =BH18 -> 4692.87 | BJ18: 45500 | BK18: EPHCOP209047ZI1N | BO18: =BI18+BL18 -> 4692.87 | BP18: =BH18-BO18 -> 0 | BQ18: =IF(ROUND(BG18,2)>0,"Advance With Supplier",IF(ROUND(BP18,2)>0,"Payable Balance Supplier","Fully Paid")) -> Fully Paid | BS18: =IF(AX18<>"","Closed","Open") -> Closed | BT18: =IF(BS18="Open",TODAY()-J18,"Closed") -> Closed
A19: Unique Ventures | B19: PRF_Details_Not Availbale | C19: PRF_Details_Not Availbale | D19: Kinshasa | E19: PRF_Details_Not Availbale | F19: 0 | G19: =IF(AG19="","GRN Not Received",AW19/AG19) -> 1 | H19: =IF(E19="PRF_Details_Not Availbale","PRF Qty Not Available",IF(G19="GRN Not Received","GRN Not Received",--E19*--G19)) -> PRF Qty Not Available | I19: 043/2024 | J19: 45388 | K19: 5000 | L19: 0.52 | M19: =K19*L19 -> 2600 | N19: 0 | O19: 0 | P19: =M19+O19 -> 2600 | Q19: 23-24/108 | R19: 45381 | S19: Pharmax India Pvt Ltd | T19: FG07409 | U19: =IFERROR(VLOOKUP(T19,'item master'!B:C,2,0),"") -> HEMOSTAT 250MG/2ML (ETAMSYLATE) INJ.B/4 AMP. | V19: =K19 -> 5000 | W19: 0 | X19: =L19 -> 0.52 | Y19: =V19*X19 -> 2600 | Z19: 0 | AA19: =Y19+Z19 -> 2600 | AB19: 0.3 | AC19: =Y19*AB19 -> 780 | AD19: =AC19 -> 780 | AE19: 45463 | AF19: EPHCOP17203Y9ZGA | AG19: 5000 | AH19: =AG19 -> 5000 | AJ19: =V19-AG19 -> 0 | AK19: 24-25/436 | AL19: 45695 | AM19: UNIQUE VENTURES | AN19: 0.52 | AO19: =AG19*AN19 -> 2600 | AS19: =AO19+AP19+AQ19+AR19 -> 2600 | AT19: 2515134444 | AV19: Goods Received at Warehouse | AW19: 5000 | AX19: 25KIN1/IGRN000088 | AZ19: 19.8 | BA19: =AD19+AZ19 -> 799.8 | BB19: 0 | BC19: 0 | BD19: =IF(AK19>0,BA19+BB19+BC19,"0") -> 799.8 | BE19: =BA19-BD19 -> 0 | BF19: 0 | BG19: =BE19-BF19 -> 0 | BH19: =AS19-BD19 -> 1800.2 | BI19: =BH19 -> 1800.2 | BJ19: 45765 | BK19: SWIFT COPY NOT AVAILABLE | BO19: =BI19+BL19 -> 1800.2 | BP19: =BH19-BO19 -> 0 | BQ19: =IF(ROUND(BG19,2)>0,"Advance With Supplier",IF(ROUND(BP19,2)>0,"Payable Balance Supplier","Fully Paid")) -> Fully Paid | BS19: =IF(AX19<>"","Closed","Open") -> Closed | BT19: =IF(BS19="Open",TODAY()-J19,"Closed") -> Closed
A20: Unique Ventures | B20: PRF_Details_Not Availbale | C20: PRF_Details_Not Availbale | D20: Kinshasa | E20: PRF_Details_Not Availbale | F20: 0 | G20: =IF(AG20="","GRN Not Received",AW20/AG20) -> 1 | H20: =IF(E20="PRF_Details_Not Availbale","PRF Qty Not Available",IF(G20="GRN Not Received","GRN Not Received",--E20*--G20)) -> PRF Qty Not Available | I20: 043/2024 | J20: 45388 | K20: 20000 | L20: 0.22 | M20: =K20*L20 -> 4400 | N20: 0 | O20: 0 | P20: =M20+O20 -> 4400 | Q20: 23-24/108 | R20: 45381 | S20: Pharmax India Pvt Ltd | T20: FG07415 | U20: =IFERROR(VLOOKUP(T20,'item master'!B:C,2,0),"") -> VOMITRON 0.075 MG/1.5ML (PALONOSÉTRON) INJ. B/1 VIAL | V20: =K20 -> 20000 | W20: 0 | X20: =L20 -> 0.22 | Y20: =V20*X20 -> 4400 | Z20: 0 | AA20: =Y20+Z20 -> 4400 | AB20: 0.3 | AC20: =Y20*AB20 -> 1320 | AD20: =AC20 -> 1320 | AE20: 45463 | AF20: EPHCOP17203Y9ZGA | AG20: 19750 | AH20: =AG20 -> 19750 | AJ20: =V20-AG20 -> 250 | AK20: 24-25/192 | AL20: 45537 | AM20: UNIQUE VENTURES | AN20: 0.22 | AO20: =AG20*AN20 -> 4345 | AS20: =AO20+AP20+AQ20+AR20 -> 4345 | AT20: 244450371 | AV20: Goods Received at Warehouse | AW20: 19750 | AX20: 24KIN/IGRN000302 | AY20: 45608 | AZ20: 0 | BA20: =AD20+AZ20 -> 1320 | BB20: 0 | BC20: -16.5 | BD20: =IF(AK20>0,BA20+BB20+BC20,"0") -> 1303.5 | BE20: =BA20-BD20 -> 16.5 | BF20: 16.5 | BG20: =BE20-BF20 -> 0 | BH20: =AS20-BD20 -> 3041.5 | BI20: =BH20 -> 3041.5 | BJ20: 45586 | BK20: EPHCOP29504UC6MI | BO20: =BI20+BL20 -> 3041.5 | BP20: =BH20-BO20 -> 0 | BQ20: =IF(ROUND(BG20,2)>0,"Advance With Supplier",IF(ROUND(BP20,2)>0,"Payable Balance Supplier","Fully Paid")) -> Fully Paid | BS20: =IF(AX20<>"","Closed","Open") -> Closed | BT20: =IF(BS20="Open",TODAY()-J20,"Closed") -> Closed
A21: Unique Ventures | B21: PRF_Details_Not Availbale | C21: PRF_Details_Not Availbale | D21: Kinshasa | E21: PRF_Details_Not Availbale | F21: 0 | G21: =IF(AG21="","GRN Not Received",AW21/AG21) -> 1 | H21: =IF(E21="PRF_Details_Not Availbale","PRF Qty Not Available",IF(G21="GRN Not Received","GRN Not Received",--E21*--G21)) -> PRF Qty Not Available | I21: 043/2024 | J21: 45388 | K21: 15000 | L21: 0.16 | M21: =K21*L21 -> 2400 | N21: 0 | O21: 0 | P21: =M21+O21 -> 2400 | Q21: 23-24/108 | R21: 45381 | S21: Pharmax India Pvt Ltd | T21: FG07413 | U21: =IFERROR(VLOOKUP(T21,'item master'!B:C,2,0),"") -> H-CID 20MG/2ML (FAMOTIDINE ) INJ. B/1 VIAL | V21: =K21 -> 15000 | W21: 0 | X21: =L21 -> 0.16 | Y21: =V21*X21 -> 2400 | Z21: 0 | AA21: =Y21+Z21 -> 2400 | AB21: 0.3 | AC21: =Y21*AB21 -> 720 | AD21: =AC21 -> 720 | AE21: 45463 | AF21: EPHCOP17203Y9ZGA | AG21: 15160 | AH21: =AG21 -> 15160 | AJ21: =V21-AG21 -> -160 | AK21: 24-25/322 | AL21: 45625 | AM21: UNIQUE VENTURES | AN21: =X21 -> 0.16 | AO21: =AG21*AN21 -> 2425.6 | AS21: =AO21+AP21+AQ21+AR21 -> 2425.6 | AT21: AMC2336146 | AU21: 45667 | AV21: Goods Received at Warehouse | AW21: 15160 | AX21: 25KIN/IGRN000021 | AY21: 45721 | AZ21: 16.5 | BA21: =AD21+AZ21 -> 736.5 | BB21: 828 | BC21: 0 | BD21: =IF(AK21>0,BA21+BB21+BC21,"0") -> 1564.5 | BE21: =BA21-BD21 -> -828 | BF21: -828 | BG21: =BE21-BF21 -> 0 | BH21: =AS21-BD21 -> 861.1 | BI21: =BH21 -> 861.1 | BJ21: 45765 | BK21: SWIFT COPY NOT AVAILABLE | BO21: =BI21+BL21 -> 861.1 | BP21: =BH21-BO21 -> 0 | BQ21: =IF(ROUND(BG21,2)>0,"Advance With Supplier",IF(ROUND(BP21,2)>0,"Payable Balance Supplier","Fully Paid")) -> Fully Paid | BS21: =IF(AX21<>"","Closed","Open") -> Closed | BT21: =IF(BS21="Open",TODAY()-J21,"Closed") -> Closed
A22: Unique Ventures | B22: PRF_Details_Not Availbale | C22: PRF_Details_Not Availbale | D22: Kinshasa | E22: PRF_Details_Not Availbale | F22: 0 | G22: =IF(AG22="","GRN Not Received",AW22/AG22) -> 1 | H22: =IF(E22="PRF_Details_Not Availbale","PRF Qty Not Available",IF(G22="GRN Not Received","GRN Not Received",--E22*--G22)) -> PRF Qty Not Available | I22: 043/2024 | J22: 45388 | K22: 10000 | L22: 0.25 | M22: =K22*L22 -> 2500 | N22: 0 | O22: 0 | P22: =M22+O22 -> 2500 | Q22: 23-24/108 | R22: 45381 | S22: Pharmax India Pvt Ltd | T22: FG07418 | U22: =IFERROR(VLOOKUP(T22,'item master'!B:C,2,0),"") -> KETOFEN 100MG/2ML ( KÉTOPROFÈNE) INJ. B/5AMP | V22: =K22 -> 10000 | W22: 0 | X22: =L22 -> 0.25 | Y22: =V22*X22 -> 2500 | Z22: 0 | AA22: =Y22+Z22 -> 2500 | AB22: 0.3 | AC22: =Y22*AB22 -> 750 | AD22: =AC22 -> 750 | AE22: 45463 | AF22: EPHCOP17203Y9ZGA | AG22: 9000 | AH22: =AG22 -> 9000 | AJ22: =V22-AG22 -> 1000 | AK22: 24-25/192 | AL22: 45537 | AM22: UNIQUE VENTURES | AN22: 0.25 | AO22: =AG22*AN22 -> 2250 | AS22: =AO22+AP22+AQ22+AR22 -> 2250 | AT22: 244450371 | AV22: Goods Received at Warehouse | AW22: 9000 | AX22: 24KIN/IGRN000302 | AY22: 45608 | AZ22: 0 | BA22: =AD22+AZ22 -> 750 | BB22: 0 | BC22: -75 | BD22: =IF(AK22>0,BA22+BB22+BC22,"0") -> 675 | BE22: =BA22-BD22 -> 75 | BF22: 75 | BG22: =BE22-BF22 -> 0 | BH22: =AS22-BD22 -> 1575 | BI22: =BH22 -> 1575 | BJ22: 45586 | BK22: EPHCOP29504UC6MI | BO22: =BI22+BL22 -> 1575 | BP22: =BH22-BO22 -> 0 | BQ22: =IF(ROUND(BG22,2)>0,"Advance With Supplier",IF(ROUND(BP22,2)>0,"Payable Balance Supplier","Fully Paid")) -> Fully Paid | BS22: =IF(AX22<>"","Closed","Open") -> Closed | BT22: =IF(BS22="Open",TODAY()-J22,"Closed") -> Closed
A23: Unique Ventures | B23: PRF_Details_Not Availbale | C23: PRF_Details_Not Availbale | D23: Kinshasa | E23: PRF_Details_Not Availbale | F23: 0 | G23: =IF(AG23="","GRN Not Received",AW23/AG23) -> 1 | H23: =IF(E23="PRF_Details_Not Availbale","PRF Qty Not Available",IF(G23="GRN Not Received","GRN Not Received",--E23*--G23)) -> PRF Qty Not Available | I23: 043/2024 | J23: 45388 | K23: 3000 | L23: 0.9 | M23: =K23*L23 -> 2700 | N23: 0 | O23: 0 | P23: =M23+O23 -> 2700 | Q23: 23-24/108 | R23: 45381 | S23: Pharmax India Pvt Ltd | T23: FG07423 | U23: =IFERROR(VLOOKUP(T23,'item master'!B:C,2,0),"") -> NIMOTRIX 10MG (NIMODIPINE) IV B/50ML VIAL | V23: =K23 -> 3000 | W23: 0 | X23: =L23 -> 0.9 | Y23: =V23*X23 -> 2700 | Z23: 0 | AA23: =Y23+Z23 -> 2700 | AB23: 0.3 | AC23: =Y23*AB23 -> 810 | AD23: =AC23 -> 810 | AE23: 45463 | AF23: EPHCOP17203Y9ZGA | AG23: 3050 | AH23: =AG23 -> 3050 | AJ23: =V23-AG23 -> -50 | AK23: 24-25/192 | AL23: 45537 | AM23: UNIQUE VENTURES | AN23: 0.9 | AO23: =AG23*AN23 -> 2745 | AS23: =AO23+AP23+AQ23+AR23 -> 2745 | AT23: 244450371 | AV23: Goods Received at Warehouse | AW23: 3050 | AX23: 24KIN/IGRN000302 | AY23: 45608 | AZ23: 0 | BA23: =AD23+AZ23 -> 810 | BB23: 0 | BC23: 13.5 | BD23: =IF(AK23>0,BA23+BB23+BC23,"0") -> 823.5 | BE23: =BA23-BD23 -> -13.5 | BF23: -13.5 | BG23: =BE23-BF23 -> 0 | BH23: =AS23-BD23 -> 1921.5 | BI23: =BH23 -> 1921.5 | BJ23: 45586 | BK23: EPHCOP29504UC6MI | BO23: =BI23+BL23 -> 1921.5 | BP23: =BH23-BO23 -> 0 | BQ23: =IF(ROUND(BG23,2)>0,"Advance With Supplier",IF(ROUND(BP23,2)>0,"Payable Balance Supplier","Fully Paid")) -> Fully Paid | BS23: =IF(AX23<>"","Closed","Open") -> Closed | BT23: =IF(BS23="Open",TODAY()-J23,"Closed") -> Closed
A24: Unique Ventures | B24: PRF_Details_Not Availbale | C24: PRF_Details_Not Availbale | D24: Kinshasa | E24: PRF_Details_Not Availbale | F24: 0 | G24: =IF(AG24="","GRN Not Received",AW24/AG24) -> 1 | H24: =IF(E24="PRF_Details_Not Availbale","PRF Qty Not Available",IF(G24="GRN Not Received","GRN Not Received",--E24*--G24)) -> PRF Qty Not Available | I24: 043/2024 | J24: 45388 | K24: 3000 | L24: 0.5 | M24: =K24*L24 -> 1500 | N24: 0 | O24: 0 | P24: =M24+O24 -> 1500 | Q24: 23-24/108 | R24: 45381 | S24: Pharmax India Pvt Ltd | T24: FG07425 | U24: =IFERROR(VLOOKUP(T24,'item master'!B:C,2,0),"") -> PHAMINE 22,75MG/ML (MALÉATE DE PHÉNIRAMINE) 2ML INJ. B/10 AMP | V24: =K24 -> 3000 | W24: 0 | X24: =L24 -> 0.5 | Y24: =V24*X24 -> 1500 | Z24: 0 | AA24: =Y24+Z24 -> 1500 | AB24: 0.3 | AC24: =Y24*AB24 -> 450 | AD24: =AC24 -> 450 | AE24: 45463 | AF24: EPHCOP17203Y9ZGA | AG24: 3100 | AH24: =AG24 -> 3100 | AJ24: =V24-AG24 -> -100 | AK24: 25-26/079 | AL24: 45804 | AM24: UNIQUE VENTURES | AN24: 0.5 | AO24: =AG24*AN24 -> 1550 | AS24: =AO24+AP24+AQ24+AR24 -> 1550 | AT24: 255404858 | AV24: Goods Received at Warehouse | AW24: 3100 | AX24: 25KIN1/IGRN000203 | AY24: 45891 | AZ24: 0 | BA24: =AD24+AZ24 -> 450 | BB24: 0 | BC24: 0 | BD24: =IF(AK24>0,BA24+BB24+BC24,"0") -> 450 | BE24: =BA24-BD24 -> 0 | BF24: 0 | BG24: =BE24-BF24 -> 0 | BH24: =AS24-BD24 -> 1100 | BI24: =BH24 -> 1100 | BJ24: 45895 | BK24: EPHCOP23807H9WMK | BO24: =BI24+BL24 -> 1100 | BP24: =BH24-BO24 -> 0 | BQ24: =IF(ROUND(BG24,2)>0,"Advance With Supplier",IF(ROUND(BP24,2)>0,"Payable Balance Supplier","Fully Paid")) -> Fully Paid | BS24: =IF(AX24<>"","Closed","Open") -> Closed | BT24: =IF(BS24="Open",TODAY()-J24,"Closed") -> Closed
A25: Unique Ventures | B25: PRF_Details_Not Availbale | C25: PRF_Details_Not Availbale | D25: Kinshasa | E25: PRF_Details_Not Availbale | F25: 0 | G25: =IF(AG25="","GRN Not Received",AW25/AG25) -> 1 | H25: =IF(E25="PRF_Details_Not Availbale","PRF Qty Not Available",IF(G25="GRN Not Received","GRN Not Received",--E25*--G25)) -> PRF Qty Not Available | I25: 043/2024 | J25: 45388 | K25: 3000 | L25: 0.92 | M25: =K25*L25 -> 2760 | N25: 0 | O25: 0 | P25: =M25+O25 -> 2760 | Q25: 23-24/108 | R25: 45381 | S25: Pharmax India Pvt Ltd | T25: FG07411 | U25: =IFERROR(VLOOKUP(T25,'item master'!B:C,2,0),"") -> UNITRIM 480MG/5ML (CO-TRIMOXAZOLE) INJ. B/5 AMP. | V25: =K25 -> 3000 | W25: 0 | X25: =L25 -> 0.92 | Y25: =V25*X25 -> 2760 | Z25: 0 | AA25: =Y25+Z25 -> 2760 | AB25: 0.3 | AC25: =Y25*AB25 -> 828 | AD25: =AC25 -> 828 | AE25: 45463 | AF25: EPHCOP17203Y9ZGA | AG25: 2960 | AH25: =AG25 -> 2960 | AJ25: =V25-AG25 -> 40 | AK25: 25-26/437 | AL25: 46024 | AM25: UNIQUE VENTURES | AN25: 0.92 | AO25: =AG25*AN25 -> 2723.2 | AS25: =AO25+AP25+AQ25+AR25 -> 2723.2 | AT25: 266199219 | AU25: 46091 | AV25: Goods Received at Warehouse | AW25: 2960 | AX25: 26KIN1/IGRN000130 | AZ25: -828 | BA25: =AD25+AZ25 -> 0 | BB25: 0 | BC25: 0 | BD25: =IF(AK25>0,BA25+BB25+BC25,"0") -> 0 | BE25: =BA25-BD25 -> 0 | BF25: 0 | BG25: =BE25-BF25 -> 0 | BH25: =AS25-BD25 -> 2723.2 | BI25: 2723.2 | BJ25: 46234 | BO25: =BI25+BL25 -> 2723.2 | BP25: =BH25-BO25 -> 0 | BQ25: =IF(ROUND(BG25,2)>0,"Advance With Supplier",IF(ROUND(BP25,2)>0,"Payable Balance Supplier","Fully Paid")) -> Fully Paid | BS25: =IF(AX25<>"","Closed","Open") -> Closed | BT25: =IF(BS25="Open",TODAY()-J25,"Closed") -> Closed
A26: Unique Ventures | B26: PRF_Details_Not Availbale | C26: PRF_Details_Not Availbale | D26: Kinshasa | E26: PRF_Details_Not Availbale | F26: 0 | G26: =IF(AG26="","GRN Not Received",AW26/AG26) -> 1 | H26: =IF(E26="PRF_Details_Not Availbale","PRF Qty Not Available",IF(G26="GRN Not Received","GRN Not Received",--E26*--G26)) -> PRF Qty Not Available | I26: 043/2024 | J26: 45388 | K26: 3000 | L26: 0.56 | M26: =K26*L26 -> 1680 | N26: 0 | O26: 0 | P26: =M26+O26 -> 1680 | Q26: 23-24/108 | R26: 45381 | S26: Pharmax India Pvt Ltd | T26: FG07410 | U26: =IFERROR(VLOOKUP(T26,'item master'!B:C,2,0),"") -> ATARIUM 50MG/5ML (ATACURIUM ) INJ. B/5 AMP. | V26: =K26 -> 3000 | W26: 0 | X26: =L26 -> 0.56 | Y26: =V26*X26 -> 1680 | Z26: 0 | AA26: =Y26+Z26 -> 1680 | AB26: 0.3 | AC26: =Y26*AB26 -> 504 | AD26: =AC26 -> 504 | AE26: 45463 | AF26: EPHCOP17203Y9ZGA | AG26: 2880 | AH26: =AG26 -> 2880 | AJ26: =V26-AG26 -> 120 | AK26: 24-25/311 | AL26: 45621 | AM26: UNIQUE VENTURES | AN26: 0.56 | AO26: =AG26*AN26 -> 1612.8 | AS26: =AO26+AP26+AQ26+AR26 -> 1612.8 | AT26: 071-5484 5781 | AU26: 45624 | AV26: Goods Received at Warehouse | AW26: 2880 | AX26: 24KIN/IGRN000343 | AY26: 45654 | AZ26: 75 | BA26: =AD26+AZ26 -> 579 | BB26: 0 | BC26: 0 | BD26: =IF(AK26>0,BA26+BB26+BC26,"0") -> 579 | BE26: =BA26-BD26 -> 0 | BF26: 0 | BG26: =BE26-BF26 -> 0 | BH26: =AS26-BD26 -> 1033.8 | BI26: =BH26 -> 1033.8 | BJ26: 45765 | BK26: SWIFT COPY NOT AVAILABLE | BO26: =BI26+BL26 -> 1033.8 | BP26: =BH26-BO26 -> 0 | BQ26: =IF(ROUND(BG26,2)>0,"Advance With Supplier",IF(ROUND(BP26,2)>0,"Payable Balance Supplier","Fully Paid")) -> Fully Paid | BS26: =IF(AX26<>"","Closed","Open") -> Closed | BT26: =IF(BS26="Open",TODAY()-J26,"Closed") -> Closed
A27: Unique Ventures | B27: PRF_Details_Not Availbale | C27: PRF_Details_Not Availbale | D27: Kinshasa | E27: PRF_Details_Not Availbale | F27: 0 | G27: =IF(AG27="","GRN Not Received",AW27/AG27) -> 1 | H27: =IF(E27="PRF_Details_Not Availbale","PRF Qty Not Available",IF(G27="GRN Not Received","GRN Not Received",--E27*--G27)) -> PRF Qty Not Available | I27: 043/2024 | J27: 45388 | K27: 10000 | L27: 0.2 | M27: =K27*L27 -> 2000 | N27: 0 | O27: 0 | P27: =M27+O27 -> 2000 | Q27: 23-24/108 | R27: 45381 | S27: Pharmax India Pvt Ltd | T27: FG07412 | U27: =IFERROR(VLOOKUP(T27,'item master'!B:C,2,0),"") -> DICQUE AQUA 75MG/ML (DICLOFÉNAC ) INJ. B/5 AMP | V27: =K27 -> 10000 | W27: 0 | X27: =L27 -> 0.2 | Y27: =V27*X27 -> 2000 | Z27: 0 | AA27: =Y27+Z27 -> 2000 | AB27: 0.3 | AC27: =Y27*AB27 -> 600 | AD27: =AC27 -> 600 | AE27: 45463 | AF27: EPHCOP17203Y9ZGA | AG27: 8570 | AH27: =AG27 -> 8570 | AJ27: =V27-AG27 -> 1430 | AK27: 24-25/322 | AL27: 45625 | AM27: UNIQUE VENTURES | AN27: =X27 -> 0.2 | AO27: =AG27*AN27 -> 1714 | AS27: =AO27+AP27+AQ27+AR27 -> 1714 | AT27: AMC2336146 | AU27: 45667 | AV27: Goods Received at Warehouse | AW27: 8570 | AX27: 25KIN/IGRN000021 | AY27: 45721 | AZ27: -13.5 | BA27: =AD27+AZ27 -> 586.5 | BB27: 0 | BC27: 0 | BD27: =IF(AK27>0,BA27+BB27+BC27,"0") -> 586.5 | BE27: =BA27-BD27 -> 0 | BF27: 0 | BG27: =BE27-BF27 -> 0 | BH27: =AS27-BD27 -> 1127.5 | BI27: =BH27 -> 1127.5 | BJ27: 45765 | BK27: SWIFT COPY NOT AVAILABLE | BO27: =BI27+BL27 -> 1127.5 | BP27: =BH27-BO27 -> 0 | BQ27: =IF(ROUND(BG27,2)>0,"Advance With Supplier",IF(ROUND(BP27,2)>0,"Payable Balance Supplier","Fully Paid")) -> Fully Paid | BS27: =IF(AX27<>"","Closed","Open") -> Closed | BT27: =IF(BS27="Open",TODAY()-J27,"Closed") -> Closed
A28: Unique Ventures | B28: PRF_Details_Not Availbale | C28: PRF_Details_Not Availbale | D28: Kinshasa | E28: PRF_Details_Not Availbale | F28: 0 | G28: =IF(AG28="","GRN Not Received",AW28/AG28) -> 1 | H28: =IF(E28="PRF_Details_Not Availbale","PRF Qty Not Available",IF(G28="GRN Not Received","GRN Not Received",--E28*--G28)) -> PRF Qty Not Available | I28: 043/2024 | J28: 45388 | K28: 10000 | L28: 0.43 | M28: =K28*L28 -> 4300 | N28: 0 | O28: 0 | P28: =M28+O28 -> 4300 | Q28: 23-24/108 | R28: 45381 | S28: Pharmax India Pvt Ltd | T28: FG07419 | U28: =IFERROR(VLOOKUP(T28,'item master'!B:C,2,0),"") -> LABTOL 5MG/ML (LABÉTALOL ) 5ML INJ. B/5 AMP | V28: =K28 -> 10000 | W28: 0 | X28: =L28 -> 0.43 | Y28: =V28*X28 -> 4300 | Z28: 0 | AA28: =Y28+Z28 -> 4300 | AB28: 0.3 | AC28: =Y28*AB28 -> 1290 | AD28: =AC28 -> 1290 | AE28: 45463 | AF28: EPHCOP17203Y9ZGA | AG28: 9250 | AH28: =AG28 -> 9250 | AJ28: =V28-AG28 -> 750 | AK28: 24-25/322 | AL28: 45625 | AM28: UNIQUE VENTURES | AN28: =X28 -> 0.43 | AO28: =AG28*AN28 -> 3977.5 | AS28: =AO28+AP28+AQ28+AR28 -> 3977.5 | AT28: AMC2336146 | AU28: 45667 | AV28: Goods Received at Warehouse | AW28: 9250 | AX28: 25KIN/IGRN000021 | AY28: 45721 | AZ28: -30.6 | BA28: =AD28+AZ28 -> 1259.4 | BB28: 0 | BC28: 0 | BD28: =IF(AK28>0,BA28+BB28+BC28,"0") -> 1259.4 | BE28: =BA28-BD28 -> 0 | BF28: 0 | BG28: =BE28-BF28 -> 0 | BH28: =AS28-BD28 -> 2718.1 | BI28: =BH28 -> 2718.1 | BJ28: 45765 | BK28: SWIFT COPY NOT AVAILABLE | BO28: =BI28+BL28 -> 2718.1 | BP28: =BH28-BO28 -> 0 | BQ28: =IF(ROUND(BG28,2)>0,"Advance With Supplier",IF(ROUND(BP28,2)>0,"Payable Balance Supplier","Fully Paid")) -> Fully Paid | BS28: =IF(AX28<>"","Closed","Open") -> Closed | BT28: =IF(BS28="Open",TODAY()-J28,"Closed") -> Closed
A29: Unique Ventures | B29: PRF_Details_Not Availbale | C29: PRF_Details_Not Availbale | D29: Kinshasa | E29: PRF_Details_Not Availbale | F29: 0 | G29: =IF(AG29="","GRN Not Received",AW29/AG29) -> 1 | H29: =IF(E29="PRF_Details_Not Availbale","PRF Qty Not Available",IF(G29="GRN Not Received","GRN Not Received",--E29*--G29)) -> PRF Qty Not Available | I29: 043/2024 | J29: 45388 | K29: 10000 | L29: 0.3 | M29: =K29*L29 -> 3000 | N29: 0 | O29: 0 | P29: =M29+O29 -> 3000 | Q29: 23-24/108 | R29: 45381 | S29: Pharmax India Pvt Ltd | T29: FG07422 | U29: =IFERROR(VLOOKUP(T29,'item master'!B:C,2,0),"") -> UNISTIGMINE 0.5MG/ML (NÉOSTIGMINE) INJ. B/5 AMP | V29: =K29 -> 10000 | W29: 0 | X29: =L29 -> 0.3 | Y29: =V29*X29 -> 3000 | Z29: 0 | AA29: =Y29+Z29 -> 3000 | AB29: 0.3 | AC29: =Y29*AB29 -> 900 | AD29: =AC29 -> 900 | AE29: 45463 | AF29: EPHCOP17203Y9ZGA | AG29: 10360 | AH29: =AG29 -> 10360 | AJ29: =V29-AG29 -> -360 | AK29: 24-25/322 | AL29: 45625 | AM29: UNIQUE VENTURES | AN29: =X29 -> 0.3 | AO29: =AG29*AN29 -> 3108 | AS29: =AO29+AP29+AQ29+AR29 -> 3108 | AT29: AMC2336146 | AU29: 45667 | AV29: Goods Received at Warehouse | AW29: 10360 | AX29: 25KIN/IGRN000021 | AY29: 45721 | AZ29: -660 | BA29: =AD29+AZ29 -> 240 | BB29: 0 | BC29: 0 | BD29: =IF(AK29>0,BA29+BB29+BC29,"0") -> 240 | BE29: =BA29-BD29 -> 0 | BF29: 0 | BG29: =BE29-BF29 -> 0 | BH29: =AS29-BD29 -> 2868 | BI29: =BH29 -> 2868 | BJ29: 45765 | BK29: SWIFT COPY NOT AVAILABLE | BO29: =BI29+BL29 -> 2868 | BP29: =BH29-BO29 -> 0 | BQ29: =IF(ROUND(BG29,2)>0,"Advance With Supplier",IF(ROUND(BP29,2)>0,"Payable Balance Supplier","Fully Paid")) -> Fully Paid | BS29: =IF(AX29<>"","Closed","Open") -> Closed | BT29: =IF(BS29="Open",TODAY()-J29,"Closed") -> Closed
A30: Unique Ventures | B30: PRF_Details_Not Availbale | C30: PRF_Details_Not Availbale | D30: Kinshasa | E30: PRF_Details_Not Availbale | F30: 0 | G30: =IF(AG30="","GRN Not Received",AW30/AG30) -> 1 | H30: =IF(E30="PRF_Details_Not Availbale","PRF Qty Not Available",IF(G30="GRN Not Received","GRN Not Received",--E30*--G30)) -> PRF Qty Not Available | I30: 043/2024 | J30: 45388 | K30: 10000 | L30: 0.2 | M30: =K30*L30 -> 2000 | N30: 0 | O30: 0 | P30: =M30+O30 -> 2000 | Q30: 23-24/108 | R30: 45381 | S30: Pharmax India Pvt Ltd | T30: FG07426 | U30: =IFERROR(VLOOKUP(T30,'item master'!B:C,2,0),"") -> FELOXAM 20MG/ML (PIROXICAM) INJ. B/2AMP | V30: =K30 -> 10000 | W30: 0 | X30: =L30 -> 0.2 | Y30: =V30*X30 -> 2000 | Z30: 0 | AA30: =Y30+Z30 -> 2000 | AB30: 0.3 | AC30: =Y30*AB30 -> 600 | AD30: =AC30 -> 600 | AE30: 45463 | AF30: EPHCOP17203Y9ZGA | AG30: 11085 | AH30: =AG30 -> 11085 | AJ30: =V30-AG30 -> -1085 | AK30: 24-25/436 | AL30: 45695 | AM30: UNIQUE VENTURES | AN30: 0.2 | AO30: =AG30*AN30 -> 2217 | AS30: =AO30+AP30+AQ30+AR30 -> 2217 | AT30: 2515134444 | AV30: Goods Received at Warehouse | AW30: 11085 | AX30: 25KIN1/IGRN000088 | AZ30: 13.77 | BA30: =AD30+AZ30 -> 613.77 | BB30: 0 | BC30: 0 | BD30: =IF(AK30>0,BA30+BB30+BC30,"0") -> 613.77 | BE30: =BA30-BD30 -> 0 | BF30: 0 | BG30: =BE30-BF30 -> 0 | BH30: =AS30-BD30 -> 1603.23 | BI30: =BH30 -> 1603.23 | BJ30: 45765 | BK30: SWIFT COPY NOT AVAILABLE | BO30: =BI30+BL30 -> 1603.23 | BP30: =BH30-BO30 -> 0 | BQ30: =IF(ROUND(BG30,2)>0,"Advance With Supplier",IF(ROUND(BP30,2)>0,"Payable Balance Supplier","Fully Paid")) -> Fully Paid | BS30: =IF(AX30<>"","Closed","Open") -> Closed | BT30: =IF(BS30="Open",TODAY()-J30,"Closed") -> Closed
A31: Unique Ventures | B31: PRF_Details_Not Availbale | C31: PRF_Details_Not Availbale | D31: Kinshasa | E31: PRF_Details_Not Availbale | F31: 0 | G31: =IF(AG31="","GRN Not Received",AW31/AG31) -> 1 | H31: =IF(E31="PRF_Details_Not Availbale","PRF Qty Not Available",IF(G31="GRN Not Received","GRN Not Received",--E31*--G31)) -> PRF Qty Not Available | I31: 043/2024 | J31: 45388 | K31: 3000 | L31: 0.75 | M31: =K31*L31 -> 2250 | N31: 0 | O31: 0 | P31: =M31+O31 -> 2250 | Q31: 23-24/108 | R31: 45381 | S31: Pharmax India Pvt Ltd | T31: FG07417 | U31: =IFERROR(VLOOKUP(T31,'item master'!B:C,2,0),"") -> HALDOQUE 5MG/ML (HALOPÉRIDOLUM) INJ. B/5 AMP | V31: =K31 -> 3000 | W31: 0 | X31: =L31 -> 0.75 | Y31: =V31*X31 -> 2250 | Z31: 0 | AA31: =Y31+Z31 -> 2250 | AB31: 0.3 | AC31: =Y31*AB31 -> 675 | AD31: =AC31 -> 675 | AE31: 45463 | AF31: EPHCOP17203Y9ZGA | AG31: 2580 | AH31: =AG31 -> 2580 | AJ31: =V31-AG31 -> 420 | AK31: 24-25/322 | AL31: 45625 | AM31: UNIQUE VENTURES | AN31: =X31 -> 0.75 | AO31: =AG31*AN31 -> 1935 | AS31: =AO31+AP31+AQ31+AR31 -> 1935 | AT31: AMC2336146 | AU31: 45667 | AV31: Goods Received at Warehouse | AW31: 2580 | AX31: 25KIN/IGRN000021 | AY31: 45721 | AZ31: 30 | BA31: =AD31+AZ31 -> 705 | BB31: 0 | BC31: 0 | BD31: =IF(AK31>0,BA31+BB31+BC31,"0") -> 705 | BE31: =BA31-BD31 -> 0 | BF31: 0 | BG31: =BE31-BF31 -> 0 | BH31: =AS31-BD31 -> 1230 | BI31: =BH31 -> 1230 | BJ31: 45765 | BK31: SWIFT COPY NOT AVAILABLE | BO31: =BI31+BL31 -> 1230 | BP31: =BH31-BO31 -> 0 | BQ31: =IF(ROUND(BG31,2)>0,"Advance With Supplier",IF(ROUND(BP31,2)>0,"Payable Balance Supplier","Fully Paid")) -> Fully Paid | BS31: =IF(AX31<>"","Closed","Open") -> Closed | BT31: =IF(BS31="Open",TODAY()-J31,"Closed") -> Closed
A32: Unique Ventures | B32: PRF_Details_Not Availbale | C32: PRF_Details_Not Availbale | D32: Kinshasa | E32: PRF_Details_Not Availbale | F32: 0 | G32: =IF(AG32="","GRN Not Received",AW32/AG32) -> 1 | H32: =IF(E32="PRF_Details_Not Availbale","PRF Qty Not Available",IF(G32="GRN Not Received","GRN Not Received",--E32*--G32)) -> PRF Qty Not Available | I32: 043/2024 | J32: 45388 | K32: 2000 | L32: 0.89 | M32: =K32*L32 -> 1780 | N32: 0 | O32: 0 | P32: =M32+O32 -> 1780 | Q32: 23-24/108 | R32: 45381 | S32: Pharmax India Pvt Ltd | T32: FG07416 | U32: =IFERROR(VLOOKUP(T32,'item master'!B:C,2,0),"") -> HALDOQUE DECONOAS 50MG/ML (HALOPÉRIDOL) INJ.B/5 AMP | V32: =K32 -> 2000 | W32: 0 | X32: =L32 -> 0.89 | Y32: =V32*X32 -> 1780 | Z32: 0 | AA32: =Y32+Z32 -> 1780 | AB32: 0.3 | AC32: =Y32*AB32 -> 534 | AD32: =AC32 -> 534 | AE32: 45463 | AF32: EPHCOP17203Y9ZGA | AG32: 1660 | AH32: =AG32 -> 1660 | AJ32: =V32-AG32 -> 340 | AK32: 24-25/322 | AL32: 45625 | AM32: UNIQUE VENTURES | AN32: =X32 -> 0.89 | AO32: =AG32*AN32 -> 1477.4 | AS32: =AO32+AP32+AQ32+AR32 -> 1477.4 | AT32: AMC2336146 | AU32: 45667 | AV32: Goods Received at Warehouse | AW32: 1660 | AX32: 25KIN/IGRN000021 | AY32: 45721 | AZ32: 0 | BA32: =AD32+AZ32 -> 534 | BB32: 0 | BC32: 0 | BD32: =IF(AK32>0,BA32+BB32+BC32,"0") -> 534 | BE32: =BA32-BD32 -> 0 | BF32: 0 | BG32: =BE32-BF32 -> 0 | BH32: =AS32-BD32 -> 943.4 | BI32: =BH32 -> 943.4 | BJ32: 45765 | BK32: SWIFT COPY NOT AVAILABLE | BO32: =BI32+BL32 -> 943.4 | BP32: =BH32-BO32 -> 0 | BQ32: =IF(ROUND(BG32,2)>0,"Advance With Supplier",IF(ROUND(BP32,2)>0,"Payable Balance Supplier","Fully Paid")) -> Fully Paid | BS32: =IF(AX32<>"","Closed","Open") -> Closed | BT32: =IF(BS32="Open",TODAY()-J32,"Closed") -> Closed
A33: Unique Ventures | B33: PRF_Details_Not Availbale | C33: PRF_Details_Not Availbale | D33: Kinshasa | E33: PRF_Details_Not Availbale | F33: 0 | G33: =IF(AG33="","GRN Not Received",AW33/AG33) -> 1 | H33: =IF(E33="PRF_Details_Not Availbale","PRF Qty Not Available",IF(G33="GRN Not Received","GRN Not Received",--E33*--G33)) -> PRF Qty Not Available | I33: 043/2024 | J33: 45388 | K33: 5000 | L33: 0.42 | M33: =K33*L33 -> 2100 | N33: 0 | O33: 0 | P33: =M33+O33 -> 2100 | Q33: 23-24/108 | R33: 45381 | S33: Pharmax India Pvt Ltd | T33: FG07421 | U33: =IFERROR(VLOOKUP(T33,'item master'!B:C,2,0),"") -> SOLU-PREDNOL 40MG (METHYLPREDNISOLONE) INJ.B/1 VIAL+SOLVENT 2ML | V33: =K33 -> 5000 | W33: 0 | X33: =L33 -> 0.42 | Y33: =V33*X33 -> 2100 | Z33: 0 | AA33: =Y33+Z33 -> 2100 | AB33: 0.3 | AC33: =Y33*AB33 -> 630 | AD33: =AC33 -> 630 | AE33: 45463 | AF33: EPHCOP17203Y9ZGA | AG33: 4800 | AH33: =AG33 -> 4800 | AJ33: =V33-AG33 -> 200 | AK33: 24-25/322 | AL33: 45625 | AM33: UNIQUE VENTURES | AN33: 0.42 | AO33: =AG33*AN33 -> 2016 | AS33: =AO33+AP33+AQ33+AR33 -> 2016 | AT33: AMC2336146 | AU33: 45667 | AV33: Goods Received at Warehouse | AW33: 4800 | AX33: 25KIN/IGRN000021 | AY33: 45721 | AZ33: 0 | BA33: =AD33+AZ33 -> 630 | BB33: 0 | BC33: 0 | BD33: =IF(AK33>0,BA33+BB33+BC33,"0") -> 630 | BE33: =BA33-BD33 -> 0 | BF33: 0 | BG33: =BE33-BF33 -> 0 | BH33: =AS33-BD33 -> 1386 | BI33: =BH33 -> 1386 | BJ33: 45765 | BK33: SWIFT COPY NOT AVAILABLE | BO33: =BI33+BL33 -> 1386 | BP33: =BH33-BO33 -> 0 | BQ33: =IF(ROUND(BG33,2)>0,"Advance With Supplier",IF(ROUND(BP33,2)>0,"Payable Balance Supplier","Fully Paid")) -> Fully Paid | BS33: =IF(AX33<>"","Closed","Open") -> Closed | BT33: =IF(BS33="Open",TODAY()-J33,"Closed") -> Closed
A34: Unique Ventures | B34: PRF_Details_Not Availbale | C34: PRF_Details_Not Availbale | D34: Kinshasa | E34: PRF_Details_Not Availbale | F34: 0 | G34: =IF(AG34="","GRN Not Received",AW34/AG34) -> 1 | H34: =IF(E34="PRF_Details_Not Availbale","PRF Qty Not Available",IF(G34="GRN Not Received","GRN Not Received",--E34*--G34)) -> PRF Qty Not Available | I34: 043/2024 | J34: 45388 | K34: 5000 | L34: 0.83 | M34: =K34*L34 -> 4150 | N34: 0 | O34: 0 | P34: =M34+O34 -> 4150 | Q34: 23-24/108 | R34: 45381 | S34: Pharmax India Pvt Ltd | T34: FG07420 | U34: =IFERROR(VLOOKUP(T34,'item master'!B:C,2,0),"") -> SOLU-PREDNOL 125MG (MÉTHYLPREDNISOLONE) INJ.B/1 VIAL + SOLVENT 2ML | V34: =K34 -> 5000 | W34: 0 | X34: =L34 -> 0.83 | Y34: =V34*X34 -> 4150 | Z34: 0 | AA34: =Y34+Z34 -> 4150 | AB34: 0.3 | AC34: =Y34*AB34 -> 1245 | AD34: =AC34 -> 1245 | AE34: 45463 | AF34: EPHCOP17203Y9ZGA | AG34: 4000 | AH34: =AG34 -> 4000 | AJ34: =V34-AG34 -> 1000 | AK34: 24-25/322 | AL34: 45625 | AM34: UNIQUE VENTURES | AN34: 0.83 | AO34: =AG34*AN34 -> 3320 | AS34: =AO34+AP34+AQ34+AR34 -> 3320 | AT34: AMC2336146 | AU34: 45667 | AV34: Goods Received at Warehouse | AW34: 4000 | AX34: 25KIN/IGRN000021 | AY34: 45721 | AZ34: 0 | BA34: =AD34+AZ34 -> 1245 | BB34: 0 | BC34: 0 | BD34: =IF(AK34>0,BA34+BB34+BC34,"0") -> 1245 | BE34: =BA34-BD34 -> 0 | BF34: 0 | BG34: =BE34-BF34 -> 0 | BH34: =AS34-BD34 -> 2075 | BI34: =BH34 -> 2075 | BJ34: 45765 | BK34: SWIFT COPY NOT AVAILABLE | BO34: =BI34+BL34 -> 2075 | BP34: =BH34-BO34 -> 0 | BQ34: =IF(ROUND(BG34,2)>0,"Advance With Supplier",IF(ROUND(BP34,2)>0,"Payable Balance Supplier","Fully Paid")) -> Fully Paid | BS34: =IF(AX34<>"","Closed","Open") -> Closed | BT34: =IF(BS34="Open",TODAY()-J34,"Closed") -> Closed
A35: Unique Ventures | B35: PRF_Details_Not Availbale | C35: PRF_Details_Not Availbale | D35: Kinshasa | E35: PRF_Details_Not Availbale | F35: 0 | G35: =IF(AG35="","GRN Not Received",AW35/AG35) -> 1 | H35: =IF(E35="PRF_Details_Not Availbale","PRF Qty Not Available",IF(G35="GRN Not Received","GRN Not Received",--E35*--G35)) -> PRF Qty Not Available | I35: 043/2024 | J35: 45388 | K35: 20000 | L35: 0.3 | M35: =K35*L35 -> 6000 | N35: 0 | O35: 0 | P35: =M35+O35 -> 6000 | Q35: 23-24/108 | R35: 45381 | S35: Pharmax India Pvt Ltd | T35: FG07414 | U35: =IFERROR(VLOOKUP(T35,'item master'!B:C,2,0),"") -> SPASMOSTOP 40MG/2ML ( DROTAVÉRINE ) INJ. B/5 AMP | V35: =K35 -> 20000 | W35: 0 | X35: =L35 -> 0.3 | Y35: =V35*X35 -> 6000 | Z35: 0 | AA35: =Y35+Z35 -> 6000 | AB35: 0.3 | AC35: =Y35*AB35 -> 1800 | AD35: =AC35 -> 1800 | AE35: 45463 | AF35: EPHCOP17203Y9ZGA | AG35: 20340 | AH35: =AG35 -> 20340 | AJ35: =V35-AG35 -> -340 | AK35: 24-25/192 | AL35: 45537 | AM35: UNIQUE VENTURES | AN35: 0.3 | AO35: =AG35*AN35 -> 6102 | AS35: =AO35+AP35+AQ35+AR35 -> 6102 | AT35: 244450371 | AV35: Goods Received at Warehouse | AW35: 20340 | AX35: 24KIN/IGRN000302 | AY35: 45608 | AZ35: 0 | BA35: =AD35+AZ35 -> 1800 | BB35: 0 | BC35: 30.6 | BD35: =IF(AK35>0,BA35+BB35+BC35,"0") -> 1830.6 | BE35: =BA35-BD35 -> -30.6 | BF35: -30.6 | BG35: =BE35-BF35 -> 9.2370556e-14 | BH35: =AS35-BD35 -> 4271.4 | BI35: =BH35 -> 4271.4 | BJ35: 45586 | BK35: EPHCOP29504UC6MI | BO35: =BI35+BL35 -> 4271.4 | BP35: =BH35-BO35 -> 0 | BQ35: =IF(ROUND(BG35,2)>0,"Advance With Supplier",IF(ROUND(BP35,2)>0,"Payable Balance Supplier","Fully Paid")) -> Fully Paid | BS35: =IF(AX35<>"","Closed","Open") -> Closed | BT35: =IF(BS35="Open",TODAY()-J35,"Closed") -> Closed
A36: Unique Ventures | B36: 1293.24 | C36: 45381 | D36: Kinshasa | E36: 500000 | F36: Pack of 6 Amps | G36: =IF(AG36="","GRN Not Received",AW36/AG36) -> 1 | H36: =IF(E36="PRF_Details_Not Availbale","PRF Qty Not Available",IF(G36="GRN Not Received","GRN Not Received",--E36*--G36)) -> 500000 | I36: 043/2024 | J36: 45388 | K36: 500000 | L36: 0.2 | M36: =K36*L36 -> 100000 | N36: 0 | O36: 0 | P36: =M36+O36 -> 100000 | Q36: 23-24/112 | R36: 45381 | S36: Pharmax India Pvt Ltd | T36: FG03621 | U36: =IFERROR(VLOOKUP(T36,'item master'!B:C,2,0),"") -> ARTEMETHER 80MG/ML INJ B/6AMP | V36: =K36 -> 500000 | W36: 0 | X36: =L36 -> 0.2 | Y36: =V36*X36 -> 100000 | Z36: 0 | AA36: =Y36+Z36 -> 100000 | AB36: 0.3 | AC36: =Y36*AB36 -> 30000 | AD36: =AC36 -> 30000 | AE36: 45463 | AF36: EPHCOP17203Y9ZGA | AG36: 511000 | AH36: =AG36 -> 511000 | AJ36: =V36-AG36 -> -11000 | AK36: 24-25/078 | AL36: 45457 | AM36: UNIQUE VENTURES | AN36: 0.2 | AO36: =AG36*AN36 -> 102200 | AS36: =AO36+AP36+AQ36+AR36 -> 102200 | AT36: AMC2229366 | AU36: 45500 | AV36: Goods Received at Warehouse | AW36: 511000 | AX36: 24KIN/IGRN000234 | AY36: 45544 | AZ36: 0 | BA36: =AD36+AZ36 -> 30000 | BB36: 0 | BC36: 660 | BD36: =IF(AK36>0,BA36+BB36+BC36,"0") -> 30660 | BE36: =BA36-BD36 -> -660 | BF36: -660 | BG36: =BE36-BF36 -> 0 | BH36: =AS36-BD36 -> 71540 | BI36: =BH36 -> 71540 | BJ36: 45500 | BK36: EPHCOP209047ZI1N | BO36: =BI36+BL36 -> 71540 | BP36: =BH36-BO36 -> 0 | BQ36: =IF(ROUND(BG36,2)>0,"Advance With Supplier",IF(ROUND(BP36,2)>0,"Payable Balance Supplier","Fully Paid")) -> Fully Paid | BS36: =IF(AX36<>"","Closed","Open") -> Closed | BT36: =IF(BS36="Open",TODAY()-J36,"Closed") -> Closed
A37: Unique Ventures | B37: 1384.24 | C37: 45553 | D37: Kinshasa | E37: 4000 | F37: Pack of 10 Amps | G37: =IF(AG37="","GRN Not Received",AW37/AG37) -> 1 | H37: =IF(E37="PRF_Details_Not Availbale","PRF Qty Not Available",IF(G37="GRN Not Received","GRN Not Received",--E37*--G37)) -> 4000 | I37: 0136/2024 | J37: 45555 | K37: 4000 | L37: 0.74 | M37: =K37*L37 -> 2960 | N37: 0 | O37: 0 | P37: =M37+O37 -> 2960 | Q37: 24-25/018 | R37: 45553 | S37: Pharmax India Pvt Ltd | T37: FG00537 | U37: =IFERROR(VLOOKUP(T37,'item master'!B:C,2,0),"") -> CAFEINE B/10AMP | V37: 4000 | W37: 0 | X37: 0.74 | Y37: =V37*X37 -> 2960 | Z37: 0 | AA37: =Y37+Z37 -> 2960 | AB37: 0.3 | AC37: =Y37*AB37 -> 888 | AD37: =AC37 -> 888 | AE37: 45568 | AF37: EPHCOP27704Q5SYK | AG37: 3090 | AH37: =AG37 -> 3090 | AJ37: =V37-AG37 -> 910 | AK37: 24-25/387 | AL37: 45668 | AM37: UNIQUE VENTURES | AN37: 0.74 | AO37: =AG37*AN37 -> 2286.6 | AS37: =AO37+AP37+AQ37+AR37 -> 2286.6 | AT37: AMC2353209 | AU37: 45700 | AV37: Goods Received at Warehouse | AW37: 3090 | AX37: 25KIN1/IGRN000048 | AY37: 45747 | AZ37: 0 | BA37: =AD37+AZ37 -> 888 | BB37: 0 | BC37: 0 | BD37: =IF(AK37>0,BA37+BB37+BC37,"0") -> 888 | BE37: =BA37-BD37 -> 0 | BF37: 0 | BG37: =BE37-BF37 -> 0 | BH37: =AS37-BD37 -> 1398.6 | BI37: =BH37 -> 1398.6 | BJ37: 45765 | BK37: SWIFT COPY NOT AVAILABLE | BO37: =BI37+BL37 -> 1398.6 | BP37: =BH37-BO37 -> 0 | BQ37: =IF(ROUND(BG37,2)>0,"Advance With Supplier",IF(ROUND(BP37,2)>0,"Payable Balance Supplier","Fully Paid")) -> Fully Paid | BS37: =IF(AX37<>"","Closed","Open") -> Closed | BT37: =IF(BS37="Open",TODAY()-J37,"Closed") -> Closed
A38: Unique Ventures | B38: 1384.24 | C38: 45553 | D38: Kinshasa | E38: 200000 | F38: Pack of 100 Amps | G38: =IF(AG38="","GRN Not Received",AW38/AG38) -> 1 | H38: =IF(E38="PRF_Details_Not Availbale","PRF Qty Not Available",IF(G38="GRN Not Received","GRN Not Received",--E38*--G38)) -> 200000 | I38: 0136/2024 | J38: 45555 | K38: 200000 | L38: 0.0675 | M38: =K38*L38 -> 13500 | N38: 0 | O38: 0 | P38: =M38+O38 -> 13500 | Q38: 24-25/018 | R38: 45553 | S38: Pharmax India Pvt Ltd | T38: FG04611 | U38: =IFERROR(VLOOKUP(T38,'item master'!B:C,2,0),"") -> CHLORAMPHENICOL 0.5% COLLYRE 10ML | V38: 200000 | W38: 0 | X38: 0.0675 | Y38: =V38*X38 -> 13500 | Z38: 0 | AA38: =Y38+Z38 -> 13500 | AB38: 0.3 | AC38: =Y38*AB38 -> 4050 | AD38: =AC38 -> 4050 | AE38: 45568 | AF38: EPHCOP27704Q5SYK | AG38: 200000 | AH38: =AG38 -> 200000 | AJ38: =V38-AG38 -> 0 | AK38: 24-25/436 | AL38: 45695 | AM38: UNIQUE VENTURES | AN38: 0.0675 | AO38: =AG38*AN38 -> 13500 | AS38: =AO38+AP38+AQ38+AR38 -> 13500 | AT38: 2515134444 | AV38: Goods Received at Warehouse | AW38: 200000 | AX38: 25KIN1/IGRN000088 | AZ38: 0 | BA38: =AD38+AZ38 -> 4050 | BB38: 0 | BC38: 0 | BD38: =IF(AK38>0,BA38+BB38+BC38,"0") -> 4050 | BE38: =BA38-BD38 -> 0 | BF38: 0 | BG38: =BE38-BF38 -> 0 | BH38: =AS38-BD38 -> 9450 | BI38: =BH38 -> 9450 | BJ38: 45765 | BK38: SWIFT COPY NOT AVAILABLE | BO38: =BI38+BL38 -> 9450 | BP38: =BH38-BO38 -> 0 | BQ38: =IF(ROUND(BG38,2)>0,"Advance With Supplier",IF(ROUND(BP38,2)>0,"Payable Balance Supplier","Fully Paid")) -> Fully Paid | BS38: =IF(AX38<>"","Closed","Open") -> Closed | BT38: =IF(BS38="Open",TODAY()-J38,"Closed") -> Closed
A39: Unique Ventures | B39: 1384.24 | C39: 45553 | D39: Kinshasa | E39: 4000 | F39: Per Pack 100 Amp | G39: =IF(AG39="","GRN Not Received",AW39/AG39) -> 10 | H39: =IF(E39="PRF_Details_Not Availbale","PRF Qty Not Available",IF(G39="GRN Not Received","GRN Not Received",--E39*--G39)) -> 40000 | I39: 0136/2024 | J39: 45555 | K39: 4000 | L39: 4.4 | M39: =K39*L39 -> 17600 | N39: 0 | O39: 0 | P39: =M39+O39 -> 17600 | Q39: 24-25/018 | R39: 45553 | S39: Pharmax India Pvt Ltd | T39: FG03867 | U39: =IFERROR(VLOOKUP(T39,'item master'!B:C,2,0),"") -> DIAZEPAM 10MG/2ML INJ B/10AMP | V39: 4000 | W39: 0 | X39: 4.4 | Y39: =V39*X39 -> 17600 | Z39: 0 | AA39: =Y39+Z39 -> 17600 | AB39: 0.3 | AC39: =Y39*AB39 -> 5280 | AD39: =AC39 -> 5280 | AE39: 45568 | AF39: EPHCOP27704Q5SYK | AG39: 3926 | AH39: =AG39 -> 3926 | AJ39: =V39-AG39 -> 74 | AK39: 24-25/387 | AL39: 45668 | AM39: UNIQUE VENTURES | AN39: 4.4 | AO39: =AG39*AN39 -> 17274.4 | AS39: =AO39+AP39+AQ39+AR39 -> 17274.4 | AT39: AMC2353209 | AU39: 45700 | AV39: Goods Received at Warehouse | AW39: 39260 | AX39: 25KIN1/IGRN000048 | AY39: 45747 | AZ39: 0 | BA39: =AD39+AZ39 -> 5280 | BB39: 0 | BC39: 0 | BD39: =IF(AK39>0,BA39+BB39+BC39,"0") -> 5280 | BE39: =BA39-BD39 -> 0 | BF39: 0 | BG39: =BE39-BF39 -> 0 | BH39: =AS39-BD39 -> 11994.4 | BI39: =BH39 -> 11994.4 | BJ39: 45765 | BK39: SWIFT COPY NOT AVAILABLE | BO39: =BI39+BL39 -> 11994.4 | BP39: =BH39-BO39 -> 0 | BQ39: =IF(ROUND(BG39,2)>0,"Advance With Supplier",IF(ROUND(BP39,2)>0,"Payable Balance Supplier","Fully Paid")) -> Fully Paid | BS39: =IF(AX39<>"","Closed","Open") -> Closed | BT39: =IF(BS39="Open",TODAY()-J39,"Closed") -> Closed
A40: Unique Ventures | B40: 1384.24 | C40: 45553 | D40: Kinshasa | E40: 100000 | F40: 0 | G40: =IF(AG40="","GRN Not Received",AW40/AG40) -> 1 | H40: =IF(E40="PRF_Details_Not Availbale","PRF Qty Not Available",IF(G40="GRN Not Received","GRN Not Received",--E40*--G40)) -> 100000 | I40: 0136/2024 | J40: 45555 | K40: 1000000 | L40: 0.1 | M40: =K40*L40 -> 100000 | N40: 0 | O40: 0 | P40: =M40+O40 -> 100000 | Q40: 24-25/018 | R40: 45553 | S40: Pharmax India Pvt Ltd | T40: FG04047 | U40: =IFERROR(VLOOKUP(T40,'item master'!B:C,2,0),"") -> LINCOMYCINE 600MG INJ.B/1 VIAL | V40: 1000000 | W40: 0 | X40: 0.1 | Y40: =V40*X40 -> 100000 | Z40: 0 | AA40: =Y40+Z40 -> 100000 | AB40: 0.3 | AC40: =Y40*AB40 -> 30000 | AD40: =AC40 -> 30000 | AE40: 45568 | AF40: EPHCOP27704Q5SYK | AG40: 568000 | AH40: =AG40 -> 568000 | AJ40: 0 | AK40: 24-25/436 | AL40: 45695 | AM40: UNIQUE VENTURES | AN40: 0.1 | AO40: =AG40*AN40 -> 56800 | AS40: =AO40+AP40+AQ40+AR40 -> 56800 | AT40: 2515134444 | AV40: Goods Received at Warehouse | AW40: 568000 | AX40: 25KIN1/IGRN000088 | AY40: 45785 | AZ40: 0 | BA40: =AD40+AZ40 -> 30000 | BB40: 660 | BC40: 0 | BD40: =IF(AK40>0,BA40+BB40+BC40,"0") -> 30660 | BE40: =BA40-BD40 -> -660 | BF40: -660 | BG40: =BE40-BF40 -> 0 | BH40: =AS40-BD40 -> 26140 | BI40: =BH40 -> 26140 | BJ40: 45765 | BK40: SWIFT COPY NOT AVAILABLE | BO40: =BI40+BL40 -> 26140 | BP40: =BH40-BO40 -> 0 | BQ40: =IF(ROUND(BG40,2)>0,"Advance With Supplier",IF(ROUND(BP40,2)>0,"Payable Balance Supplier","Fully Paid")) -> Fully Paid | BS40: =IF(AX40<>"","Closed","Open") -> Closed | BT40: =IF(BS40="Open",TODAY()-J40,"Closed") -> Closed
A41: Unique Ventures | B41: 1384.24 | C41: 45553 | D41: Kinshasa | F41: 0 | G41: =IF(AG41="","GRN Not Received",AW41/AG41) -> 1 | H41: =IF(E41="PRF_Details_Not Availbale","PRF Qty Not Available",IF(G41="GRN Not Received","GRN Not Received",--E41*--G41)) -> 0 | I41: 0136/2024 | J41: 45555 | K41: 0 | L41: 0 | M41: =K41*L41 -> 0 | N41: 0 | O41: 0 | P41: =M41+O41 -> 0 | Q41: 24-25/018 | R41: 45553 | S41: Pharmax India Pvt Ltd | T41: FG04047 | U41: =IFERROR(VLOOKUP(T41,'item master'!B:C,2,0),"") -> LINCOMYCINE 600MG INJ.B/1 VIAL | V41: 0 | W41: 0 | X41: 0 | Y41: =V41*X41 -> 0 | Z41: 0 | AA41: =Y41+Z41 -> 0 | AB41: 0.3 | AC41: =Y41*AB41 -> 0 | AD41: =AC41 -> 0 | AF41: EPHCOP27704Q5SYK | AG41: 436000 | AH41: =AG41 -> 436000 | AJ41: 0 | AK41: 24-25/482 | AL41: 45721 | AM41: UNIQUE VENTURES | AN41: 0.1 | AO41: =AG41*AN41 -> 43600 | AS41: =AO41+AP41+AQ41+AR41 -> 43600 | AT41: 2515134444 | AV41: Goods Received at Warehouse | AW41: 436000 | AX41: 25KIN1/IGRN000088 | AY41: 45785 | AZ41: 0 | BA41: =AD41+AZ41 -> 0 | BB41: 0 | BC41: 0 | BD41: =IF(AK41>0,BA41+BB41+BC41,"0") -> 0 | BE41: =BA41-BD41 -> 0 | BF41: 0 | BG41: =BE41-BF41 -> 0 | BH41: =AS41-BD41 -> 43600 | BI41: =BH41 -> 43600 | BJ41: 45895 | BK41: EPHCOP23807H9WMK | BO41: =BI41+BL41 -> 43600 | BP41: =BH41-BO41 -> 0 | BQ41: =IF(ROUND(BG41,2)>0,"Advance With Supplier",IF(ROUND(BP41,2)>0,"Payable Balance Supplier","Fully Paid")) -> Fully Paid | BS41: =IF(AX41<>"","Closed","Open") -> Closed | BT41: =IF(BS41="Open",TODAY()-J41,"Closed") -> Closed
A42: Unique Ventures | B42: 1384.24 | C42: 45553 | D42: Kinshasa | E42: 30000 | F42: Per Vial | G42: =IF(AG42="","GRN Not Received",AW42/AG42) -> 1 | H42: =IF(E42="PRF_Details_Not Availbale","PRF Qty Not Available",IF(G42="GRN Not Received","GRN Not Received",--E42*--G42)) -> 30000 | I42: 0136/2024 | J42: 45555 | K42: 30000 | L42: 0.31 | M42: =K42*L42 -> 9300 | N42: 0 | O42: 0 | P42: =M42+O42 -> 9300 | Q42: 24-25/018 | R42: 45553 | S42: Pharmax India Pvt Ltd | T42: FG06811 | U42: =IFERROR(VLOOKUP(T42,'item master'!B:C,2,0),"") -> UNIKORT-40 (TRIAMCINOLONE) B/1 VIAL+SER | V42: 30000 | W42: 0 | X42: 0.31 | Y42: =V42*X42 -> 9300 | Z42: 0 | AA42: =Y42+Z42 -> 9300 | AB42: 0.3 | AC42: =Y42*AB42 -> 2790 | AD42: =AC42 -> 2790 | AE42: 45568 | AF42: EPHCOP27704Q5SYK | AG42: 30900 | AH42: =AG42 -> 30900 | AJ42: =V42-AG42 -> -900 | AK42: 24-25/387 | AL42: 45668 | AM42: UNIQUE VENTURES | AN42: 0.31 | AO42: =AG42*AN42 -> 9579 | AS42: =AO42+AP42+AQ42+AR42 -> 9579 | AT42: AMC2353209 | AU42: 45700 | AV42: Goods Received at Warehouse | AW42: 30900 | AX42: 25KIN1/IGRN000048 | AY42: 45747 | AZ42: 0 | BA42: =AD42+AZ42 -> 2790 | BB42: 1350 | BC42: 0 | BD42: =IF(AK42>0,BA42+BB42+BC42,"0") -> 4140 | BE42: =BA42-BD42 -> -1350 | BF42: -1350 | BG42: =BE42-BF42 -> 0 | BH42: =AS42-BD42 -> 5439 | BI42: =BH42 -> 5439 | BJ42: 45765 | BK42: SWIFT COPY NOT AVAILABLE | BO42: =BI42+BL42 -> 5439 | BP42: =BH42-BO42 -> 0 | BQ42: =IF(ROUND(BG42,2)>0,"Advance With Supplier",IF(ROUND(BP42,2)>0,"Payable Balance Supplier","Fully Paid")) -> Fully Paid | BS42: =IF(AX42<>"","Closed","Open") -> Closed | BT42: =IF(BS42="Open",TODAY()-J42,"Closed") -> Closed
A43: Unique Ventures | B43: 1384.24 | C43: 45553 | D43: Kinshasa | E43: 40000 | F43: Per Vial | G43: =IF(AG43="","GRN Not Received",AW43/AG43) -> 1 | H43: =IF(E43="PRF_Details_Not Availbale","PRF Qty Not Available",IF(G43="GRN Not Received","GRN Not Received",--E43*--G43)) -> 40000 | I43: 0136/2024 | J43: 45555 | K43: 40000 | L43: 0.5 | M43: =K43*L43 -> 20000 | N43: 0 | O43: 0 | P43: =M43+O43 -> 20000 | Q43: 24-25/018 | R43: 45553 | S43: Pharmax India Pvt Ltd | T43: FG06812 | U43: =IFERROR(VLOOKUP(T43,'item master'!B:C,2,0),"") -> UNIKORT-80 (TRIAMCINOLONE) B/1 VIAL +SER | V43: 40000 | W43: 0 | X43: 0.5 | Y43: =V43*X43 -> 20000 | Z43: 0 | AA43: =Y43+Z43 -> 20000 | AB43: 0.3 | AC43: =Y43*AB43 -> 6000 | AD43: =AC43 -> 6000 | AE43: 45568 | AF43: EPHCOP27704Q5SYK | AG43: 40200 | AH43: =AG43 -> 40200 | AJ43: =V43-AG43 -> -200 | AK43: 24-25/387 | AL43: 45668 | AM43: UNIQUE VENTURES | AN43: 0.5 | AO43: =AG43*AN43 -> 20100 | AS43: =AO43+AP43+AQ43+AR43 -> 20100 | AT43: AMC2353209 | AU43: 45700 | AV43: Goods Received at Warehouse | AW43: 40200 | AX43: 25KIN1/IGRN000048 | AY43: 45747 | AZ43: 0 | BA43: =AD43+AZ43 -> 6000 | BB43: 2460 | BC43: 0 | BD43: =IF(AK43>0,BA43+BB43+BC43,"0") -> 8460 | BE43: =BA43-BD43 -> -2460 | BF43: -2460 | BG43: =BE43-BF43 -> 0 | BH43: =AS43-BD43 -> 11640 | BI43: =BH43 -> 11640 | BJ43: 45765 | BK43: SWIFT COPY NOT AVAILABLE | BO43: =BI43+BL43 -> 11640 | BP43: =BH43-BO43 -> 0 | BQ43: =IF(ROUND(BG43,2)>0,"Advance With Supplier",IF(ROUND(BP43,2)>0,"Payable Balance Supplier","Fully Paid")) -> Fully Paid | BS43: =IF(AX43<>"","Closed","Open") -> Closed | BT43: =IF(BS43="Open",TODAY()-J43,"Closed") -> Closed
A44: Unique Ventures | B44: 1400.24 | C44: 45583 | D44: Kinshasa | E44: 20000 | F44: Per Vial | G44: =IF(AG44="","GRN Not Received",AW44/AG44) -> 1 | H44: =IF(E44="PRF_Details_Not Availbale","PRF Qty Not Available",IF(G44="GRN Not Received","GRN Not Received",--E44*--G44)) -> 20000 | I44: 0147/2024 | J44: 45567 | K44: 20000 | L44: 0.11 | M44: =K44*L44 -> 2200 | N44: 0 | O44: 0 | P44: =M44+O44 -> 2200 | Q44: 24-25/019 | R44: 45582 | S44: Pharmax India Pvt Ltd | T44: FG08743 | U44: =IFERROR(VLOOKUP(T44,'item master'!B:C,2,0),"") -> UNIDEX – DEXAMETHASONE + NEOMYCINE GOUTTES OCULAIRES / OTIQUES 10 ML | V44: =K44 -> 20000 | W44: 0 | X44: =L44 -> 0.11 | Y44: =V44*X44 -> 2200 | Z44: 0 | AA44: =Y44+Z44 -> 2200 | AB44: 0.3 | AC44: =Y44*AB44 -> 660 | AD44: 660 | AE44: 45614 | AF44: EPHCOP3230529TJX | AG44: 18720 | AH44: =AG44 -> 18720 | AJ44: =V44-AG44 -> 1280 | AK44: 25-26/079 | AL44: 45804 | AM44: UNIQUE VENTURES | AN44: 0.11 | AO44: =AG44*AN44 -> 2059.2 | AS44: =AO44+AP44+AQ44+AR44 -> 2059.2 | AT44: 255404858 | AV44: Goods Received at Warehouse | AW44: 18720 | AX44: 25KIN1/IGRN000203 | AY44: 45891 | AZ44: -660 | BA44: =AD44+AZ44 -> 0 | BB44: 6360 | BC44: 0 | BD44: =IF(AK44>0,BA44+BB44+BC44,"0") -> 6360 | BE44: =BA44-BD44 -> -6360 | BF44: -6360 | BG44: =BE44-BF44 -> 0 | BH44: =AS44-BD44 -> -4300.8 | BI44: =BH44 -> -4300.8 | BJ44: 45895 | BK44: EPHCOP23807H9WMK | BO44: =BI44+BL44 -> -4300.8 | BP44: =BH44-BO44 -> 0 | BQ44: =IF(ROUND(BG44,2)>0,"Advance With Supplier",IF(ROUND(BP44,2)>0,"Payable Balance Supplier","Fully Paid")) -> Fully Paid | BS44: =IF(AX44<>"","Closed","Open") -> Closed | BT44: =IF(BS44="Open",TODAY()-J44,"Closed") -> Closed
A45: Unique Ventures | B45: 1400.24 | C45: 45583 | D45: Kinshasa | E45: 5000 | F45: Pack of 5 Amps | G45: =IF(AG45="","GRN Not Received",AW45/AG45) -> 1 | H45: =IF(E45="PRF_Details_Not Availbale","PRF Qty Not Available",IF(G45="GRN Not Received","GRN Not Received",--E45*--G45)) -> 5000 | I45: 0147/2024 | J45: 45567 | M45: =K45*L45 -> 0 | N45: 0 | O45: 0 | P45: =M45+O45 -> 0 | Q45: 24-25/019 | R45: 45582 | S45: Pharmax India Pvt Ltd | T45: FG08689 | U45: =IFERROR(VLOOKUP(T45,'item master'!B:C,2,0),"") -> ACUPAQUE (NEFOPAM 20MG/2 ML IV/IM) SOL. INJ. B/5AMP | W45: 0 | Z45: 0 | AA45: =Y45+Z45 -> 0 | AG45: 3000 | AH45: =AG45 -> 3000 | AJ45: =V45-AG45 -> -3000 | AK45: 25-26/334 | AL45: 45958 | AM45: UNIQUE VENTURES | AN45: 0.9 | AO45: =AG45*AN45 -> 2700 | AS45: =AO45+AP45+AQ45+AR45 -> 2700 | AT45: AMC2465942 | AV45: Goods Received at Warehouse | AW45: 3000 | AX45: 26KIN1/IGRN000009 | AY45: 46030 | AZ45: 0 | BA45: =AD45+AZ45 -> 0 | BB45: 0 | BC45: 0 | BD45: =IF(AK45>0,BA45+BB45+BC45,"0") -> 0 | BE45: =BA45-BD45 -> 0 | BG45: =BE45-BF45 -> 0 | BH45: =AS45-BD45 -> 2700 | BI45: =BH45 -> 2700 | BJ45: 45989 | BK45: CFZEE33208EPHCOP | BO45: =BI45+BL45 -> 2700 | BP45: =BH45-BO45 -> 0 | BQ45: =IF(ROUND(BG45,2)>0,"Advance With Supplier",IF(ROUND(BP45,2)>0,"Payable Balance Supplier","Fully Paid")) -> Fully Paid | BS45: =IF(AX45<>"","Closed","Open") -> Closed | BT45: =IF(BS45="Open",TODAY()-J45,"Closed") -> Closed
A46: Unique Ventures | B46: 1400.24 | C46: 45583 | D46: Kinshasa | F46: Pack of 5 Amps | G46: =IF(AG46="","GRN Not Received",AW46/AG46) -> 1 | H46: =IF(E46="PRF_Details_Not Availbale","PRF Qty Not Available",IF(G46="GRN Not Received","GRN Not Received",--E46*--G46)) -> 0 | I46: 0147/2024 | J46: 45567 | K46: 5000 | L46: 0.9 | M46: =K46*L46 -> 4500 | N46: 0 | O46: 0 | P46: =M46+O46 -> 4500 | Q46: 24-25/019 | R46: 45582 | S46: Pharmax India Pvt Ltd | T46: FG08689 | U46: =IFERROR(VLOOKUP(T46,'item master'!B:C,2,0),"") -> ACUPAQUE (NEFOPAM 20MG/2 ML IV/IM) SOL. INJ. B/5AMP | V46: =K46 -> 5000 | W46: 0 | X46: =L46 -> 0.9 | Y46: =V46*X46 -> 4500 | Z46: 0 | AA46: =Y46+Z46 -> 4500 | AB46: 0.3 | AC46: =Y46*AB46 -> 1350 | AD46: 1350 | AE46: 45614 | AF46: EPHCOP3230529TJX | AG46: 5270 | AH46: =AG46 -> 5270 | AJ46: =V46-AG46 -> -270 | AK46: 25-26/196 | AL46: 45870 | AM46: UNIQUE VENTURES | AN46: 0.9 | AO46: =AG46*AN46 -> 4743 | AS46: =AO46+AP46+AQ46+AR46 -> 4743 | AT46: 2519141100 | AV46: Goods Received at Warehouse | AW46: 5270 | AX46: 25KIN1/IGRN000289 | AY46: 45962 | AZ46: -1350 | BA46: =AD46+AZ46 -> 0 | BB46: 2400 | BC46: 0 | BD46: =IF(AK46>0,BA46+BB46+BC46,"0") -> 2400 | BE46: =BA46-BD46 -> -2400 | BF46: -2400 | BG46: =BE46-BF46 -> 0 | BH46: =AS46-BD46 -> 2343 | BI46: =BH46 -> 2343 | BJ46: 45895 | BK46: EPHCOP23807H9WMK | BO46: =BI46+BL46 -> 2343 | BP46: =BH46-BO46 -> 0 | BQ46: =IF(ROUND(BG46,2)>0,"Advance With Supplier",IF(ROUND(BP46,2)>0,"Payable Balance Supplier","Fully Paid")) -> Fully Paid | BS46: =IF(AX46<>"","Closed","Open") -> Closed | BT46: =IF(BS46="Open",TODAY()-J46,"Closed") -> Closed
A47: Unique Ventures | B47: 1400.24 | C47: 45583 | D47: Kinshasa | E47: 10000 | F47: Pack of 5 Amps | G47: =IF(AG47="","GRN Not Received",AW47/AG47) -> 1 | H47: =IF(E47="PRF_Details_Not Availbale","PRF Qty Not Available",IF(G47="GRN Not Received","GRN Not Received",--E47*--G47)) -> 10000 | I47: 0147/2024 | J47: 45567 | K47: 10000 | L47: 0.82 | M47: =K47*L47 -> 8200 | N47: 0 | O47: 0 | P47: =M47+O47 -> 8200 | Q47: 24-25/019 | R47: 45582 | S47: Pharmax India Pvt Ltd | T47: FG08690 | U47: =IFERROR(VLOOKUP(T47,'item master'!B:C,2,0),"") -> CATA 150 (CHLORHYDRATE DE CLONIDINE 150 MCG/1 ML) – 5 AMPOULES DE 1 ML | V47: =K47 -> 10000 | W47: 0 | X47: =L47 -> 0.82 | Y47: =V47*X47 -> 8200 | Z47: 0 | AA47: =Y47+Z47 -> 8200 | AB47: 0.3 | AC47: =Y47*AB47 -> 2460 | AD47: 2460 | AE47: 45614 | AF47: EPHCOP3230529TJX | AG47: 9630 | AH47: =AG47 -> 9630 | AJ47: =V47-AG47 -> 370 | AK47: 25-26/079 | AL47: 45804 | AM47: UNIQUE VENTURES | AN47: 0.82 | AO47: =AG47*AN47 -> 7896.6 | AS47: =AO47+AP47+AQ47+AR47 -> 7896.6 | AT47: 255404858 | AV47: Goods Received at Warehouse | AW47: 9630 | AX47: 25KIN1/IGRN000203 | AY47: 45891 | AZ47: -2460 | BA47: =AD47+AZ47 -> 0 | BB47: 10560 | BC47: 0 | BD47: =IF(AK47>0,BA47+BB47+BC47,"0") -> 10560 | BE47: =BA47-BD47 -> -10560 | BF47: -10560 | BG47: =BE47-BF47 -> 0 | BH47: =AS47-BD47 -> -2663.4 | BI47: =BH47 -> -2663.4 | BJ47: 45895 | BK47: EPHCOP23807H9WMK | BO47: =BI47+BL47 -> -2663.4 | BP47: =BH47-BO47 -> 0 | BQ47: =IF(ROUND(BG47,2)>0,"Advance With Supplier",IF(ROUND(BP47,2)>0,"Payable Balance Supplier","Fully Paid")) -> Fully Paid | BS47: =IF(AX47<>"","Closed","Open") -> Closed | BT47: =IF(BS47="Open",TODAY()-J47,"Closed") -> Closed
A48: Unique Ventures | B48: 1476.25 | C48: 45702 | D48: Kinshasa | E48: 4000 | F48: Per Pack 100 Amp | G48: =IF(AG48="","GRN Not Received",AW48/AG48) -> 10 | H48: =IF(E48="PRF_Details_Not Availbale","PRF Qty Not Available",IF(G48="GRN Not Received","GRN Not Received",--E48*--G48)) -> 40000 | I48: 0037/2025 | J48: 45706 | K48: 4000 | L48: 5.3 | M48: =K48*L48 -> 21200 | N48: 0 | O48: 0 | P48: =M48+O48 -> 21200 | Q48: 24/25/084 | R48: 45702 | S48: Pharmax India Pvt Ltd | T48: FG01261 | U48: =IFERROR(VLOOKUP(T48,'item master'!B:C,2,0),"") -> ERGOMETRINE B/10AMP | V48: =K48 -> 4000 | W48: 0 | X48: =L48 -> 5.3 | Y48: =V48*X48 -> 21200 | Z48: 0 | AA48: =Y48+Z48 -> 21200 | AB48: 0.3 | AC48: =Y48*AB48 -> 6360 | AD48: 6360 | AE48: 45755 | AF48: EPHCOP097068N250 | AG48: 4000 | AH48: =AG48 -> 4000 | AJ48: =V48-AG48 -> 0 | AK48: 25-26/334 | AL48: 45958 | AM48: UNIQUE VENTURES | AN48: 5.3 | AO48: =AG48*AN48 -> 21200 | AS48: =AO48+AP48+AQ48+AR48 -> 21200 | AT48: AMC2465942 | AU48: 45987 | AV48: Goods Received at Warehouse | AW48: 40000 | AX48: 26KIN1/IGRN000009 | AY48: 46030 | AZ48: -828 | BA48: =AD48+AZ48 -> 5532 | BB48: 0 | BC48: 0 | BD48: =IF(AK48>0,BA48+BB48+BC48,"0") -> 5532 | BE48: =BA48-BD48 -> 0 | BG48: =BE48-BF48 -> 0 | BH48: =AS48-BD48 -> 15668 | BI48: =BH48 -> 15668 | BJ48: 45989 | BK48: CFZEE33208EPHCOP | BO48: =BI48+BL48 -> 15668 | BP48: =BH48-BO48 -> 0 | BQ48: =IF(ROUND(BG48,2)>0,"Advance With Supplier",IF(ROUND(BP48,2)>0,"Payable Balance Supplier","Fully Paid")) -> Fully Paid | BS48: =IF(AX48<>"","Closed","Open") -> Closed | BT48: =IF(BS48="Open",TODAY()-J48,"Closed") -> Closed
A49: Unique Ventures | B49: 1476.25 | C49: 45702 | D49: Kinshasa | E49: 5280 | F49: 5 Ml | G49: =IF(AG49="","GRN Not Received",AW49/AG49) -> 1 | H49: =IF(E49="PRF_Details_Not Availbale","PRF Qty Not Available",IF(G49="GRN Not Received","GRN Not Received",--E49*--G49)) -> 5280 | I49: 0037/2025 | J49: 45706 | K49: 5280 | L49: 0.5 | M49: =K49*L49 -> 2640 | N49: 0 | O49: 0 | P49: =M49+O49 -> 2640 | Q49: 24/25/084 | R49: 45702 | S49: Pharmax India Pvt Ltd | T49: FG06808 | U49: =IFERROR(VLOOKUP(T49,'item master'!B:C,2,0),"") -> MOX PLUS VISION (MOX+DEX+HYDRO) COLLYRE 5ML | V49: =K49 -> 5280 | W49: 0 | X49: =L49 -> 0.5 | Y49: =V49*X49 -> 2640 | Z49: 0 | AA49: =Y49+Z49 -> 2640 | AB49: 0.3 | AC49: =Y49*AB49 -> 792 | AD49: 792 | AE49: 45755 | AF49: EPHCOP097068N250 | AG49: 5280 | AH49: =AG49 -> 5280 | AJ49: =V49-AG49 -> 0 | AK49: 25-26/079 | AL49: 45804 | AM49: UNIQUE VENTURES | AN49: 0.5 | AO49: =AG49*AN49 -> 2640 | AS49: =AO49+AP49+AQ49+AR49 -> 2640 | AT49: 255404858 | AV49: Goods Received at Warehouse | AW49: 5280 | AX49: 25KIN1/IGRN000203 | AY49: 45891 | AZ49: -530 | BA49: =AD49+AZ49 -> 262 | BB49: 2850 | BC49: 0 | BD49: =IF(AK49>0,BA49+BB49+BC49,"0") -> 3112 | BE49: =BA49-BD49 -> -2850 | BF49: -2850 | BG49: =BE49-BF49 -> 0 | BH49: =AS49-BD49 -> -472 | BI49: =BH49 -> -472 | BJ49: 45895 | BK49: EPHCOP23807H9WMK | BO49: =BI49+BL49 -> -472 | BP49: =BH49-BO49 -> 0 | BQ49: =IF(ROUND(BG49,2)>0,"Advance With Supplier",IF(ROUND(BP49,2)>0,"Payable Balance Supplier","Fully Paid")) -> Fully Paid | BS49: =IF(AX49<>"","Closed","Open") -> Closed | BT49: =IF(BS49="Open",TODAY()-J49,"Closed") -> Closed
A50: Unique Ventures | B50: 1476.25 | C50: 45702 | D50: Kinshasa | E50: 5280 | F50: 10 ml | G50: =IF(AG50="","GRN Not Received",AW50/AG50) -> 1 | H50: =IF(E50="PRF_Details_Not Availbale","PRF Qty Not Available",IF(G50="GRN Not Received","GRN Not Received",--E50*--G50)) -> 5280 | I50: 0037/2025 | J50: 45706 | K50: 5280 | L50: 0.35 | M50: =K50*L50 -> 1848 | N50: 0 | O50: 0 | P50: =M50+O50 -> 1848 | Q50: 24/25/084 | R50: 45702 | S50: Pharmax India Pvt Ltd | T50: FG06802 | U50: =IFERROR(VLOOKUP(T50,'item master'!B:C,2,0),"") -> MOX VISION (MOXYFLOXACIN) COLLYRE 10ML | V50: =K50 -> 5280 | W50: 0 | X50: =L50 -> 0.35 | Y50: =V50*X50 -> 1848 | Z50: 0 | AA50: =Y50+Z50 -> 1848 | AB50: 0.3 | AC50: =Y50*AB50 -> 554.4 | AD50: 554.4 | AE50: 45755 | AF50: EPHCOP097068N250 | AG50: 5220 | AH50: =AG50 -> 5220 | AJ50: =V50-AG50 -> 60 | AK50: 25-26/079 | AL50: 45804 | AM50: UNIQUE VENTURES | AN50: 0.35 | AO50: =AG50*AN50 -> 1827 | AS50: =AO50+AP50+AQ50+AR50 -> 1827 | AT50: 255404858 | AV50: Goods Received at Warehouse | AW50: 5220 | AX50: 25KIN1/IGRN000203 | AY50: 45891 | AZ50: -828 | BA50: =AD50+AZ50 -> -273.6 | BB50: 1800 | BC50: 0 | BD50: =IF(AK50>0,BA50+BB50+BC50,"0") -> 1526.4 | BE50: =BA50-BD50 -> -1800 | BF50: -1800 | BG50: =BE50-BF50 -> 0 | BH50: =AS50-BD50 -> 300.6 | BI50: =BH50 -> 300.6 | BJ50: 45895 | BK50: EPHCOP23807H9WMK | BO50: =BI50+BL50 -> 300.6 | BP50: =BH50-BO50 -> 0 | BQ50: =IF(ROUND(BG50,2)>0,"Advance With Supplier",IF(ROUND(BP50,2)>0,"Payable Balance Supplier","Fully Paid")) -> Fully Paid | BS50: =IF(AX50<>"","Closed","Open") -> Closed | BT50: =IF(BS50="Open",TODAY()-J50,"Closed") -> Closed
A51: Unique Ventures | B51: 1476.25 | C51: 45702 | D51: Kinshasa | E51: 5280 | F51: 5 ml | G51: =IF(AG51="","GRN Not Received",AW51/AG51) -> 1 | H51: =IF(E51="PRF_Details_Not Availbale","PRF Qty Not Available",IF(G51="GRN Not Received","GRN Not Received",--E51*--G51)) -> 5280 | I51: 0037/2025 | J51: 45706 | K51: 5280 | L51: 0.68 | M51: =K51*L51 -> 3590.4 | N51: 0 | O51: 0 | P51: =M51+O51 -> 3590.4 | Q51: 24/25/084 | R51: 45702 | S51: Pharmax India Pvt Ltd | T51: FG06807 | U51: =IFERROR(VLOOKUP(T51,'item master'!B:C,2,0),"") -> NATAQ VISION (NATAMYCINE) 5% COLLYRE 5ML | V51: =K51 -> 5280 | W51: 0 | X51: =L51 -> 0.68 | Y51: =V51*X51 -> 3590.4 | Z51: 0 | AA51: =Y51+Z51 -> 3590.4 | AB51: 0.3 | AC51: =Y51*AB51 -> 1077.12 | AD51: 1077.12 | AE51: 45755 | AF51: EPHCOP097068N250 | AG51: 5110 | AH51: =AG51 -> 5110 | AJ51: =V51-AG51 -> 170 | AK51: 25-26/079 | AL51: 45804 | AM51: UNIQUE VENTURES | AN51: 0.68 | AO51: =AG51*AN51 -> 3474.8 | AS51: =AO51+AP51+AQ51+AR51 -> 3474.8 | AT51: 255404858 | AV51: Goods Received at Warehouse | AW51: 5110 | AX51: 25KIN1/IGRN000203 | AY51: 45891 | AZ51: 0 | BA51: =AD51+AZ51 -> 1077.12 | BB51: 828 | BC51: 0 | BD51: =IF(AK51>0,BA51+BB51+BC51,"0") -> 1905.12 | BE51: =BA51-BD51 -> -828 | BF51: -828 | BG51: =BE51-BF51 -> 0 | BH51: =AS51-BD51 -> 1569.68 | BI51: =BH51 -> 1569.68 | BJ51: 45895 | BK51: EPHCOP23807H9WMK | BO51: =BI51+BL51 -> 1569.68 | BP51: =BH51-BO51 -> 0 | BQ51: =IF(ROUND(BG51,2)>0,"Advance With Supplier",IF(ROUND(BP51,2)>0,"Payable Balance Supplier","Fully Paid")) -> Fully Paid | BS51: =IF(AX51<>"","Closed","Open") -> Closed | BT51: =IF(BS51="Open",TODAY()-J51,"Closed") -> Closed
A52: Unique Ventures | B52: 1476.25 | C52: 45702 | D52: Kinshasa | E52: 5280 | F52: 1 Vial | G52: =IF(AG52="","GRN Not Received",AW52/AG52) -> 1 | H52: =IF(E52="PRF_Details_Not Availbale","PRF Qty Not Available",IF(G52="GRN Not Received","GRN Not Received",--E52*--G52)) -> 5280 | I52: 0037/2025 | J52: 45706 | K52: 5280 | L52: 0.38 | M52: =K52*L52 -> 2006.4 | N52: 0 | O52: 0 | P52: =M52+O52 -> 2006.4 | Q52: 24/25/084 | R52: 45702 | S52: Pharmax India Pvt Ltd | T52: FG06809 | U52: =IFERROR(VLOOKUP(T52,'item master'!B:C,2,0),"") -> TRIPI FORTE VISION (TROP+PHENYLE) COLLYRE 5ML | V52: =K52 -> 5280 | W52: 0 | X52: =L52 -> 0.38 | Y52: =V52*X52 -> 2006.4 | Z52: 0 | AA52: =Y52+Z52 -> 2006.4 | AB52: 0.3 | AC52: =Y52*AB52 -> 601.92 | AD52: 601.92 | AE52: 45755 | AF52: EPHCOP097068N250 | AG52: 5530 | AH52: =AG52 -> 5530 | AJ52: =V52-AG52 -> -250 | AK52: 25-26/079 | AL52: 45804 | AM52: UNIQUE VENTURES | AN52: 0.38 | AO52: =AG52*AN52 -> 2101.4 | AS52: =AO52+AP52+AQ52+AR52 -> 2101.4 | AT52: 255404858 | AV52: Goods Received at Warehouse | AW52: =5280+250 -> 5530 | AX52: 25KIN1/IGRN000203 | AY52: 45891 | AZ52: 0 | BA52: =AD52+AZ52 -> 601.92 | BB52: 0 | BC52: 0 | BD52: =IF(AK52>0,BA52+BB52+BC52,"0") -> 601.92 | BE52: =BA52-BD52 -> 0 | BF52: =BB52-BE52 -> 0 | BG52: =BE52-BF52 -> 0 | BH52: =AS52-BD52 -> 1499.48 | BI52: =BH52 -> 1499.48 | BJ52: 45895 | BK52: EPHCOP23807H9WMK | BO52: =BI52+BL52 -> 1499.48 | BP52: =BH52-BO52 -> 0 | BQ52: =IF(ROUND(BG52,2)>0,"Advance With Supplier",IF(ROUND(BP52,2)>0,"Payable Balance Supplier","Fully Paid")) -> Fully Paid | BS52: =IF(AX52<>"","Closed","Open") -> Closed | BT52: =IF(BS52="Open",TODAY()-J52,"Closed") -> Closed
A53: Unique Ventures | B53: 1476.25 | C53: 45702 | D53: Kinshasa | E53: 10000 | F53: Per Vial | G53: =IF(AG53="","GRN Not Received",AW53/AG53) -> 1 | H53: =IF(E53="PRF_Details_Not Availbale","PRF Qty Not Available",IF(G53="GRN Not Received","GRN Not Received",--E53*--G53)) -> 10000 | I53: 0037/2025 | J53: 45706 | K53: 10000 | L53: 0.31 | M53: =K53*L53 -> 3100 | N53: 0 | O53: 0 | P53: =M53+O53 -> 3100 | Q53: 24/25/084 | R53: 45702 | S53: Pharmax India Pvt Ltd | T53: FG06811 | U53: =IFERROR(VLOOKUP(T53,'item master'!B:C,2,0),"") -> UNIKORT-40 (TRIAMCINOLONE) B/1 VIAL+SER | V53: =K53 -> 10000 | W53: 0 | X53: =L53 -> 0.31 | Y53: =V53*X53 -> 3100 | Z53: 0 | AA53: =Y53+Z53 -> 3100 | AB53: 0.3 | AC53: =Y53*AB53 -> 930 | AD53: 930 | AE53: 45755 | AF53: EPHCOP097068N250 | AG53: 10200 | AH53: =AG53 -> 10200 | AJ53: =V53-AG53 -> -200 | AK53: 25-26/196 | AL53: 45870 | AM53: UNIQUE VENTURES | AN53: 0.31 | AO53: =AG53*AN53 -> 3162 | AS53: =AO53+AP53+AQ53+AR53 -> 3162 | AT53: 2519141100 | AV53: Goods Received at Warehouse | AW53: 10200 | AX53: 25KIN1/IGRN000289 | AY53: 45962 | AZ53: 0 | BA53: =AD53+AZ53 -> 930 | BB53: 0 | BC53: 0 | BD53: =IF(AK53>0,BA53+BB53+BC53,"0") -> 930 | BE53: =BA53-BD53 -> 0 | BF53: =BB53-BE53 -> 0 | BG53: =BE53-BF53 -> 0 | BH53: =AS53-BD53 -> 2232 | BI53: =BH53 -> 2232 | BJ53: 45895 | BK53: EPHCOP23807H9WMK | BO53: =BI53+BL53 -> 2232 | BP53: =BH53-BO53 -> 0 | BQ53: =IF(ROUND(BG53,2)>0,"Advance With Supplier",IF(ROUND(BP53,2)>0,"Payable Balance Supplier","Fully Paid")) -> Fully Paid | BS53: =IF(AX53<>"","Closed","Open") -> Closed | BT53: =IF(BS53="Open",TODAY()-J53,"Closed") -> Closed
A54: Unique Ventures | B54: 1526.25 | C54: 45758 | D54: Kinshasa | E54: 5000 | F54: Pack of 5 Amps | G54: =IF(AG54="","GRN Not Received",AW54/AG54) -> 1 | H54: =IF(E54="PRF_Details_Not Availbale","PRF Qty Not Available",IF(G54="GRN Not Received","GRN Not Received",--E54*--G54)) -> 5000 | I54: 0080/2025 | J54: 45764 | K54: 5000 | L54: 1.6 | M54: =K54*L54 -> 8000 | N54: 0 | O54: 0 | P54: =M54+O54 -> 8000 | Q54: 25-26/002 | R54: 45758 | S54: Pharmax India Pvt Ltd | T54: FG07410 | U54: =IFERROR(VLOOKUP(T54,'item master'!B:C,2,0),"") -> ATARIUM 50MG/5ML (ATACURIUM ) INJ. B/5 AMP. | V54: 5000 | W54: 0 | X54: 1.6 | Y54: =V54*X54 -> 8000 | Z54: 0 | AA54: =Y54+Z54 -> 8000 | AB54: 0.3 | AC54: =Y54*AB54 -> 2400 | AD54: 2400 | AE54: 45777 | AF54: EPHCOP12006G1J7C | AG54: 4680 | AH54: =AG54 -> 4680 | AJ54: =V54-AG54 -> 320 | AK54: 25-26/282 | AL54: 45925 | AM54: UNIQUE VENTURES | AN54: 1.6 | AO54: =AG54*AN54 -> 7488 | AS54: =AO54+AP54+AQ54+AR54 -> 7488 | AT54: 071-5553 0731 | AU54: 45926 | AV54: Goods Received at Warehouse | AW54: 4680 | AX54: 25KIN1/IGRN000273 | AY54: 45951 | AZ54: -6360 | BA54: =AD54+AZ54 -> -3960 | BB54: 0 | BC54: 0 | BD54: =IF(AK54>0,BA54+BB54+BC54,"0") -> -3960 | BE54: =BA54-BD54 -> 0 | BF54: =BB54-BE54 -> 0 | BG54: =BE54-BF54 -> 0 | BH54: =AS54-BD54 -> 11448 | BI54: =BH54 -> 11448 | BJ54: 45989 | BK54: CFZEE33208EPHCOP | BO54: =BI54+BL54 -> 11448 | BP54: =BH54-BO54 -> 0 | BQ54: =IF(ROUND(BG54,2)>0,"Advance With Supplier",IF(ROUND(BP54,2)>0,"Payable Balance Supplier","Fully Paid")) -> Fully Paid | BS54: =IF(AX54<>"","Closed","Open") -> Closed | BT54: =IF(BS54="Open",TODAY()-J54,"Closed") -> Closed
A55: Unique Ventures | B55: 1526.25 | C55: 45758 | D55: Kinshasa | E55: 8000 | F55: Per Pack 100 Amp | G55: =IF(AG55="","GRN Not Received",AW55/AG55) -> 10 | H55: =IF(E55="PRF_Details_Not Availbale","PRF Qty Not Available",IF(G55="GRN Not Received","GRN Not Received",--E55*--G55)) -> 80000 | I55: 0080/2025 | J55: 45764 | K55: 8000 | L55: 4.4 | M55: =K55*L55 -> 35200 | N55: 0 | O55: 0 | P55: =M55+O55 -> 35200 | Q55: 25-26/002 | R55: 45758 | S55: Pharmax India Pvt Ltd | T55: FG03867 | U55: =IFERROR(VLOOKUP(T55,'item master'!B:C,2,0),"") -> DIAZEPAM 10MG/2ML INJ B/10AMP | V55: 8000 | W55: 0 | X55: 4.4 | Y55: =V55*X55 -> 35200 | Z55: 0 | AA55: =Y55+Z55 -> 35200 | AB55: 0.3 | AC55: =Y55*AB55 -> 10560 | AD55: 10560 | AE55: 45777 | AF55: EPHCOP12006G1J7C | AG55: 8000 | AH55: =AG55 -> 8000 | AJ55: =V55-AG55 -> 0 | AK55: 25-26/311 | AL55: 45943 | AM55: UNIQUE VENTURES | AN55: 4.4 | AO55: =AG55*AN55 -> 35200 | AS55: =AO55+AP55+AQ55+AR55 -> 35200 | AT55: AMC2465942 | AU55: 45987 | AV55: Goods Received at Warehouse | AW55: 80000 | AX55: 26KIN1/IGRN000009 | AY55: 46030 | AZ55: -2400 | BA55: =AD55+AZ55 -> 8160 | BB55: 0 | BC55: 0 | BD55: =IF(AK55>0,BA55+BB55+BC55,"0") -> 8160 | BE55: =BA55-BD55 -> 0 | BF55: =BB55-BE55 -> 0 | BG55: =BE55-BF55 -> 0 | BH55: =AS55-BD55 -> 27040 | BI55: =BH55 -> 27040 | BJ55: 45989 | BK55: CFZEE33208EPHCOP | BO55: =BI55+BL55 -> 27040 | BP55: =BH55-BO55 -> 0 | BQ55: =IF(ROUND(BG55,2)>0,"Advance With Supplier",IF(ROUND(BP55,2)>0,"Payable Balance Supplier","Fully Paid")) -> Fully Paid | BS55: =IF(AX55<>"","Closed","Open") -> Closed | BT55: =IF(BS55="Open",TODAY()-J55,"Closed") -> Closed
A56: Unique Ventures | B56: 1526.25 | C56: 45758 | D56: Kinshasa | E56: 10000 | F56: Pack of 12 Amp | G56: =IF(AG56="","GRN Not Received",AW56/AG56) -> 1 | H56: =IF(E56="PRF_Details_Not Availbale","PRF Qty Not Available",IF(G56="GRN Not Received","GRN Not Received",--E56*--G56)) -> 10000 | I56: 0080/2025 | J56: 45764 | K56: 10000 | L56: 0.95 | M56: =K56*L56 -> 9500 | N56: 0 | O56: 0 | P56: =M56+O56 -> 9500 | Q56: 25-26/002 | R56: 45758 | S56: Pharmax India Pvt Ltd | T56: FG07264 | U56: =IFERROR(VLOOKUP(T56,'item master'!B:C,2,0),"") -> NOTROFIT (PIRACETAM) 1G/5ML INJ B/12 AMP*** | V56: 10000 | W56: 0 | X56: 0.95 | Y56: =V56*X56 -> 9500 | Z56: 0 | AA56: =Y56+Z56 -> 9500 | AB56: 0.3 | AC56: =Y56*AB56 -> 2850 | AD56: 2850 | AE56: 45777 | AF56: EPHCOP12006G1J7C | AG56: 10045 | AH56: =AG56 -> 10045 | AJ56: =V56-AG56 -> -45 | AK56: 25-26/269 | AL56: 45918 | AM56: UNIQUE VENTURES | AN56: 0.95 | AO56: =AG56*AN56 -> 9542.75 | AS56: =AO56+AP56+AQ56+AR56 -> 9542.75 | AT56: 261172994 | AU56: 45990 | AV56: Goods Received at Warehouse | AW56: 10045 | AX56: 26KIN1/IGRN000015 | AY56: 46037 | AZ56: -10560 | BA56: =AD56+AZ56 -> -7710 | BB56: =16308-20 -> 16288 | BC56: 0 | BD56: =IF(AK56>0,BA56+BB56+BC56,"0") -> 8578 | BE56: =BA56-BD56 -> -16288 | BF56: -16288 | BG56: =BE56-BF56 -> 0 | BH56: =AS56-BD56 -> 964.75 | BI56: =BH56 -> 964.75 | BJ56: 45989 | BK56: CFZEE33208EPHCOP | BO56: =BI56+BL56 -> 964.75 | BP56: =BH56-BO56 -> 0 | BQ56: =IF(ROUND(BG56,2)>0,"Advance With Supplier",IF(ROUND(BP56,2)>0,"Payable Balance Supplier","Fully Paid")) -> Fully Paid | BS56: =IF(AX56<>"","Closed","Open") -> Closed | BT56: =IF(BS56="Open",TODAY()-J56,"Closed") -> Closed
A57: Unique Ventures | B57: 1526.25 | C57: 45758 | D57: Kinshasa | E57: 20000 | F57: Pack of 5 Amps | G57: =IF(AG57="","GRN Not Received",AW57/AG57) -> 1 | H57: =IF(E57="PRF_Details_Not Availbale","PRF Qty Not Available",IF(G57="GRN Not Received","GRN Not Received",--E57*--G57)) -> 20000 | I57: 0080/2025 | J57: 45764 | K57: 20000 | L57: 0.3 | M57: =K57*L57 -> 6000 | N57: 0 | O57: 0 | P57: =M57+O57 -> 6000 | Q57: 25-26/002 | R57: 45758 | S57: Pharmax India Pvt Ltd | T57: FG07414 | U57: =IFERROR(VLOOKUP(T57,'item master'!B:C,2,0),"") -> SPASMOSTOP 40MG/2ML ( DROTAVÉRINE ) INJ. B/5 AMP | V57: 20000 | W57: 0 | X57: 0.3 | Y57: =V57*X57 -> 6000 | Z57: 0 | AA57: =Y57+Z57 -> 6000 | AB57: 0.3 | AC57: =Y57*AB57 -> 1800 | AD57: 1800 | AE57: 45777 | AF57: EPHCOP12006G1J7C | AG57: 20000 | AH57: =AG57 -> 20000 | AJ57: =V57-AG57 -> 0 | AK57: 25-26/269 | AL57: 45918 | AM57: UNIQUE VENTURES | AN57: 0.3 | AO57: =AG57*AN57 -> 6000 | AS57: =AO57+AP57+AQ57+AR57 -> 6000 | AT57: 261172994 | AU57: 45990 | AV57: Goods Received at Warehouse | AW57: 20000 | AX57: 26KIN1/IGRN000015 | AY57: 46037 | AZ57: -2850 | BA57: =AD57+AZ57 -> -1050 | BB57: 0 | BC57: 0 | BD57: =IF(AK57>0,BA57+BB57+BC57,"0") -> -1050 | BE57: =BA57-BD57 -> 0 | BF57: =BB57-BE57 -> 0 | BG57: =BE57-BF57 -> 0 | BH57: =AS57-BD57 -> 7050 | BI57: =BH57 -> 7050 | BJ57: 45989 | BK57: CFZEE33208EPHCOP | BO57: =BI57+BL57 -> 7050 | BP57: =BH57-BO57 -> 0 | BQ57: =IF(ROUND(BG57,2)>0,"Advance With Supplier",IF(ROUND(BP57,2)>0,"Payable Balance Supplier","Fully Paid")) -> Fully Paid | BS57: =IF(AX57<>"","Closed","Open") -> Closed | BT57: =IF(BS57="Open",TODAY()-J57,"Closed") -> Closed
A58: Unique Ventures | B58: 1597.25 | C58: 45887 | D58: Kinshasa | E58: 10000 | F58: Pack of 5 Amps | G58: =IF(AG58="","GRN Not Received",AW58/AG58) -> 1 | H58: =IF(E58="PRF_Details_Not Availbale","PRF Qty Not Available",IF(G58="GRN Not Received","GRN Not Received",--E58*--G58)) -> 10000 | I58: 0162/2025 | J58: 45892 | K58: 5000 | L58: 0.2 | M58: =K58*L58 -> 1000 | N58: 0 | O58: 0 | P58: =M58+O58 -> 1000 | Q58: 25-26/027 | R58: 45897 | S58: Pharmax India Pvt Ltd | T58: FG07412 | U58: =IFERROR(VLOOKUP(T58,'item master'!B:C,2,0),"") -> DICQUE AQUA 75MG/ML (DICLOFÉNAC ) INJ. B/5 AMP | V58: 5000 | W58: 0 | X58: 0.2 | Y58: =V58*X58 -> 1000 | Z58: 0 | AA58: =Y58+Z58 -> 1000 | AB58: 0.3 | AC58: =Y58*AB58 -> 300 | AD58: =AC58 -> 300 | AE58: 45909 | AF58: EPHCOP25207M201S | AG58: 4350 | AH58: =AG58 -> 4350 | AJ58: =V58-AG58 -> 650 | AK58: 25-26/424 | AL58: 46015 | AM58: UNIQUE VENTURES | AN58: =X58 -> 0.2 | AO58: =AG58*AN58 -> 870 | AS58: =AO58+AP58+AQ58+AR58 -> 870 | AT58: AMC2483036 | AU58: 46043 | AV58: Goods Received at Warehouse | AW58: 4350 | AX58: 26KIN1/IGRN000076 | AY58: 46091 | AZ58: -300 | BA58: =AD58+AZ58 -> 0 | BB58: 0 | BC58: 0 | BD58: =IF(AK58>0,BA58+BB58+BC58,"0") -> 0 | BE58: =BA58-BD58 -> 0 | BF58: =BB58-BE58 -> 0 | BG58: =BE58-BF58 -> 0 | BH58: =AS58-BD58 -> 870 | BI58: 870 | BJ58: 46234 | BO58: =BI58+BL58 -> 870 | BP58: =BH58-BO58 -> 0 | BQ58: =IF(ROUND(BG58,2)>0,"Advance With Supplier",IF(ROUND(BP58,2)>0,"Payable Balance Supplier","Fully Paid")) -> Fully Paid | BS58: =IF(AX58<>"","Closed","Open") -> Closed | BT58: =IF(BS58="Open",TODAY()-J58,"Closed") -> Closed
A59: Unique Ventures | B59: 1597.25 | C59: 45887 | D59: Kinshasa | E59: 4000 | F59: Pack of 10 Amps | G59: =IF(AG59="","GRN Not Received",AW59/AG59) -> 1 | H59: =IF(E59="PRF_Details_Not Availbale","PRF Qty Not Available",IF(G59="GRN Not Received","GRN Not Received",--E59*--G59)) -> 4000 | I59: 0162/2025 | J59: 45892 | K59: 4000 | L59: 0.74 | M59: =K59*L59 -> 2960 | N59: 0 | O59: 0 | P59: =M59+O59 -> 2960 | Q59: 25-26/027 | R59: 45897 | S59: Pharmax India Pvt Ltd | T59: FG00537 | U59: =IFERROR(VLOOKUP(T59,'item master'!B:C,2,0),"") -> CAFEINE B/10AMP | V59: 4000 | W59: 0 | X59: 0.74 | Y59: =V59*X59 -> 2960 | Z59: 0 | AA59: =Y59+Z59 -> 2960 | AB59: 0.3 | AC59: =Y59*AB59 -> 888 | AD59: =AC59 -> 888 | AE59: 45909 | AF59: EPHCOP25207M201S | AG59: 4000 | AH59: =AG59 -> 4000 | AJ59: =V59-AG59 -> 0 | AK59: 25-26/424 | AL59: 46015 | AM59: UNIQUE VENTURES | AN59: =X59 -> 0.74 | AO59: =AG59*AN59 -> 2960 | AS59: =AO59+AP59+AQ59+AR59 -> 2960 | AT59: AMC2483036 | AU59: 46043 | AV59: Goods Received at Warehouse | AW59: 4000 | AX59: 26KIN1/IGRN000076 | AY59: 46091 | AZ59: -888 | BA59: =AD59+AZ59 -> 0 | BB59: 0 | BC59: 0 | BD59: =IF(AK59>0,BA59+BB59+BC59,"0") -> 0 | BE59: =BA59-BD59 -> 0 | BF59: =BB59-BE59 -> 0 | BG59: =BE59-BF59 -> 0 | BH59: =AS59-BD59 -> 2960 | BI59: 2960 | BJ59: 46234 | BO59: =BI59+BL59 -> 2960 | BP59: =BH59-BO59 -> 0 | BQ59: =IF(ROUND(BG59,2)>0,"Advance With Supplier",IF(ROUND(BP59,2)>0,"Payable Balance Supplier","Fully Paid")) -> Fully Paid | BS59: =IF(AX59<>"","Closed","Open") -> Closed | BT59: =IF(BS59="Open",TODAY()-J59,"Closed") -> Closed
A60: Unique Ventures | B60: 1597.25 | C60: 45887 | D60: Kinshasa | E60: 12000 | F60: Per Vial | G60: =IF(AG60="","GRN Not Received",AW60/AG60) -> 0.96153846 | H60: =IF(E60="PRF_Details_Not Availbale","PRF Qty Not Available",IF(G60="GRN Not Received","GRN Not Received",--E60*--G60)) -> 11538.462 | I60: 0162/2025 | J60: 45892 | K60: 12000 | L60: 0.16 | M60: =K60*L60 -> 1920 | N60: 0 | O60: 0 | P60: =M60+O60 -> 1920 | Q60: 25-26/027 | R60: 45897 | S60: Pharmax India Pvt Ltd | T60: FG07413 | U60: =IFERROR(VLOOKUP(T60,'item master'!B:C,2,0),"") -> H-CID 20MG/2ML (FAMOTIDINE ) INJ. B/1 VIAL | V60: 12000 | W60: 0 | X60: 0.16 | Y60: =V60*X60 -> 1920 | Z60: 0 | AA60: =Y60+Z60 -> 1920 | AB60: 0.3 | AC60: =Y60*AB60 -> 576 | AD60: =AC60 -> 576 | AE60: 45909 | AF60: EPHCOP25207M201S | AG60: 12480 | AH60: =AG60 -> 12480 | AJ60: =V60-AG60 -> -480 | AK60: 25-26/424 | AL60: 46015 | AM60: UNIQUE VENTURES | AN60: =X60 -> 0.16 | AO60: =AG60*AN60 -> 1996.8 | AS60: =AO60+AP60+AQ60+AR60 -> 1996.8 | AT60: AMC2483036 | AU60: 46043 | AV60: Goods Received at Warehouse | AW60: 12000 | AX60: 26KIN1/IGRN000076 | AY60: 46091 | AZ60: -576 | BA60: =AD60+AZ60 -> 0 | BB60: 0 | BC60: 0 | BD60: =IF(AK60>0,BA60+BB60+BC60,"0") -> 0 | BE60: =BA60-BD60 -> 0 | BF60: =BB60-BE60 -> 0 | BG60: =BE60-BF60 -> 0 | BH60: =AS60-BD60 -> 1996.8 | BI60: 1996.8 | BJ60: 46234 | BO60: =BI60+BL60 -> 1996.8 | BP60: =BH60-BO60 -> 0 | BQ60: =IF(ROUND(BG60,2)>0,"Advance With Supplier",IF(ROUND(BP60,2)>0,"Payable Balance Supplier","Fully Paid")) -> Fully Paid | BS60: =IF(AX60<>"","Closed","Open") -> Closed | BT60: =IF(BS60="Open",TODAY()-J60,"Closed") -> Closed
A61: Unique Ventures | B61: 1597.25 | C61: 45887 | D61: Kinshasa | E61: 9600 | F61: 5 Ml | G61: =IF(AG61="","GRN Not Received",AW61/AG61) -> 1 | H61: =IF(E61="PRF_Details_Not Availbale","PRF Qty Not Available",IF(G61="GRN Not Received","GRN Not Received",--E61*--G61)) -> 9600 | I61: 0162/2025 | J61: 45892 | K61: 9600 | L61: 0.5 | M61: =K61*L61 -> 4800 | N61: 0 | O61: 0 | P61: =M61+O61 -> 4800 | Q61: 25-26/027 | R61: 45897 | S61: Pharmax India Pvt Ltd | T61: FG06808 | U61: =IFERROR(VLOOKUP(T61,'item master'!B:C,2,0),"") -> MOX PLUS VISION (MOX+DEX+HYDRO) COLLYRE 5ML | V61: 9600 | W61: 0 | X61: 0.5 | Y61: =V61*X61 -> 4800 | Z61: 0 | AA61: =Y61+Z61 -> 4800 | AB61: 0.3 | AC61: =Y61*AB61 -> 1440 | AD61: =AC61 -> 1440 | AE61: 45909 | AF61: EPHCOP25207M201S | AG61: 10420 | AH61: =AG61 -> 10420 | AJ61: =V61-AG61 -> -820 | AK61: 25-26/424 | AL61: 46015 | AM61: UNIQUE VENTURES | AN61: =X61 -> 0.5 | AO61: =AG61*AN61 -> 5210 | AS61: =AO61+AP61+AQ61+AR61 -> 5210 | AT61: AMC2483036 | AU61: 46043 | AV61: Goods Received at Warehouse | AW61: 10420 | AX61: 26KIN1/IGRN000076 | AY61: 46091 | AZ61: -1440 | BA61: =AD61+AZ61 -> 0 | BB61: 0 | BC61: 0 | BD61: =IF(AK61>0,BA61+BB61+BC61,"0") -> 0 | BE61: =BA61-BD61 -> 0 | BF61: =BB61-BE61 -> 0 | BG61: =BE61-BF61 -> 0 | BH61: =AS61-BD61 -> 5210 | BI61: 5210 | BJ61: 46234 | BO61: =BI61+BL61 -> 5210 | BP61: =BH61-BO61 -> 0 | BQ61: =IF(ROUND(BG61,2)>0,"Advance With Supplier",IF(ROUND(BP61,2)>0,"Payable Balance Supplier","Fully Paid")) -> Fully Paid | BS61: =IF(AX61<>"","Closed","Open") -> Closed | BT61: =IF(BS61="Open",TODAY()-J61,"Closed") -> Closed
A62: Unique Ventures | B62: 1597.25 | C62: 45887 | D62: Kinshasa | E62: 20000 | F62: Per Vial | G62: =IF(AG62="","GRN Not Received",AW62/AG62) -> 1 | H62: =IF(E62="PRF_Details_Not Availbale","PRF Qty Not Available",IF(G62="GRN Not Received","GRN Not Received",--E62*--G62)) -> 20000 | I62: 0162/2025 | J62: 45892 | K62: 20000 | L62: 0.95 | M62: =K62*L62 -> 19000 | N62: 0 | O62: 0 | P62: =M62+O62 -> 19000 | Q62: 25-26/027 | R62: 45897 | S62: Pharmax India Pvt Ltd | T62: FG06804 | U62: =IFERROR(VLOOKUP(T62,'item master'!B:C,2,0),"") -> TROBINIQUE-2G(SPECTINOMYCIN) B/1VIAL+3.2MLE.D | V62: 20000 | W62: 0 | X62: 0.95 | Y62: =V62*X62 -> 19000 | Z62: 0 | AA62: =Y62+Z62 -> 19000 | AB62: 0.3 | AC62: =Y62*AB62 -> 5700 | AD62: =AC62 -> 5700 | AE62: 45909 | AF62: EPHCOP25207M201S | AG62: 19500 | AH62: =AG62 -> 19500 | AJ62: =V62-AG62 -> 500 | AK62: 25-26/424 | AL62: 46015 | AM62: UNIQUE VENTURES | AN62: =X62 -> 0.95 | AO62: =AG62*AN62 -> 18525 | AS62: =AO62+AP62+AQ62+AR62 -> 18525 | AT62: AMC2483036 | AU62: 46043 | AV62: Goods Received at Warehouse | AW62: 19500 | AX62: 26KIN1/IGRN000076 | AY62: 46091 | AZ62: -5700 | BA62: =AD62+AZ62 -> 0 | BB62: 0 | BC62: 0 | BD62: =IF(AK62>0,BA62+BB62+BC62,"0") -> 0 | BE62: =BA62-BD62 -> 0 | BF62: =BB62-BE62 -> 0 | BG62: =BE62-BF62 -> 0 | BH62: =AS62-BD62 -> 18525 | BI62: 18525 | BJ62: 46234 | BO62: =BI62+BL62 -> 18525 | BP62: =BH62-BO62 -> 0 | BQ62: =IF(ROUND(BG62,2)>0,"Advance With Supplier",IF(ROUND(BP62,2)>0,"Payable Balance Supplier","Fully Paid")) -> Fully Paid | BS62: =IF(AX62<>"","Closed","Open") -> Closed | BT62: =IF(BS62="Open",TODAY()-J62,"Closed") -> Closed
A63: Unique Ventures | B63: 1597.25 | C63: 45887 | D63: Kinshasa | E63: 5000 | F63: 1 Vial | G63: =IF(AG63="","GRN Not Received",AW63/AG63) -> 1 | H63: =IF(E63="PRF_Details_Not Availbale","PRF Qty Not Available",IF(G63="GRN Not Received","GRN Not Received",--E63*--G63)) -> 5000 | I63: 0162/2025 | J63: 45892 | K63: 5000 | L63: 0.42 | M63: =K63*L63 -> 2100 | N63: 0 | O63: 0 | P63: =M63+O63 -> 2100 | Q63: 25-26/027 | R63: 45897 | S63: Pharmax India Pvt Ltd | T63: FG07421 | U63: =IFERROR(VLOOKUP(T63,'item master'!B:C,2,0),"") -> SOLU-PREDNOL 40MG (METHYLPREDNISOLONE) INJ.B/1 VIAL+SOLVENT 2ML | V63: 5000 | W63: 0 | X63: 0.42 | Y63: =V63*X63 -> 2100 | Z63: 0 | AA63: =Y63+Z63 -> 2100 | AB63: 0.3 | AC63: =Y63*AB63 -> 630 | AD63: =AC63 -> 630 | AE63: 45909 | AF63: EPHCOP25207M201S | AG63: 4940 | AH63: =AG63 -> 4940 | AJ63: =V63-AG63 -> 60 | AK63: 25-26/424 | AL63: 46015 | AM63: UNIQUE VENTURES | AN63: =X63 -> 0.42 | AO63: =AG63*AN63 -> 2074.8 | AS63: =AO63+AP63+AQ63+AR63 -> 2074.8 | AT63: AMC2483036 | AU63: 46043 | AV63: Goods Received at Warehouse | AW63: 4940 | AX63: 26KIN1/IGRN000076 | AY63: 46091 | AZ63: -630 | BA63: =AD63+AZ63 -> 0 | BB63: 0 | BC63: 0 | BD63: =IF(AK63>0,BA63+BB63+BC63,"0") -> 0 | BE63: =BA63-BD63 -> 0 | BF63: =BB63-BE63 -> 0 | BG63: =BE63-BF63 -> 0 | BH63: =AS63-BD63 -> 2074.8 | BI63: 2074.8 | BJ63: 46234 | BO63: =BI63+BL63 -> 2074.8 | BP63: =BH63-BO63 -> 0 | BQ63: =IF(ROUND(BG63,2)>0,"Advance With Supplier",IF(ROUND(BP63,2)>0,"Payable Balance Supplier","Fully Paid")) -> Fully Paid | BS63: =IF(AX63<>"","Closed","Open") -> Closed | BT63: =IF(BS63="Open",TODAY()-J63,"Closed") -> Closed
A64: Unique Ventures | B64: 1597.25 | C64: 45887 | D64: Kinshasa | E64: 5000 | F64: 1 Vial | G64: =IF(AG64="","GRN Not Received",AW64/AG64) -> 1 | H64: =IF(E64="PRF_Details_Not Availbale","PRF Qty Not Available",IF(G64="GRN Not Received","GRN Not Received",--E64*--G64)) -> 5000 | I64: 0162/2025 | J64: 45892 | K64: 5000 | L64: 0.83 | M64: =K64*L64 -> 4150 | N64: 0 | O64: 0 | P64: =M64+O64 -> 4150 | Q64: 25-26/027 | R64: 45897 | S64: Pharmax India Pvt Ltd | T64: FG07420 | U64: =IFERROR(VLOOKUP(T64,'item master'!B:C,2,0),"") -> SOLU-PREDNOL 125MG (MÉTHYLPREDNISOLONE) INJ.B/1 VIAL + SOLVENT 2ML | V64: 5000 | W64: 0 | X64: 0.83 | Y64: =V64*X64 -> 4150 | Z64: 0 | AA64: =Y64+Z64 -> 4150 | AB64: 0.3 | AC64: =Y64*AB64 -> 1245 | AD64: =AC64 -> 1245 | AE64: 45909 | AF64: EPHCOP25207M201S | AG64: 5080 | AH64: =AG64 -> 5080 | AJ64: =V64-AG64 -> -80 | AK64: 25-26/424 | AL64: 46015 | AM64: UNIQUE VENTURES | AN64: =X64 -> 0.83 | AO64: =AG64*AN64 -> 4216.4 | AS64: =AO64+AP64+AQ64+AR64 -> 4216.4 | AT64: AMC2483036 | AU64: 46043 | AV64: Goods Received at Warehouse | AW64: 5080 | AX64: 26KIN1/IGRN000076 | AY64: 46091 | AZ64: -1245 | BA64: =AD64+AZ64 -> 0 | BB64: 0 | BC64: 20 | BD64: =IF(AK64>0,BA64+BB64+BC64,"0") -> 20 | BE64: =BA64-BD64 -> -20 | BF64: -20 | BG64: =BE64-BF64 -> 0 | BH64: =AS64-BD64 -> 4196.4 | BI64: 4196.4 | BJ64: 46234 | BO64: =BI64+BL64 -> 4196.4 | BP64: =BH64-BO64 -> 0 | BQ64: =IF(ROUND(BG64,2)>0,"Advance With Supplier",IF(ROUND(BP64,2)>0,"Payable Balance Supplier","Fully Paid")) -> Fully Paid | BS64: =IF(AX64<>"","Closed","Open") -> Closed | BT64: =IF(BS64="Open",TODAY()-J64,"Closed") -> Closed
A65: Unique Ventures | B65: 1597.25 | C65: 45887 | D65: Kinshasa | E65: 3000 | F65: Pack of 5 Amps | G65: =IF(AG65="","GRN Not Received",AW65/AG65) -> 1 | H65: =IF(E65="PRF_Details_Not Availbale","PRF Qty Not Available",IF(G65="GRN Not Received","GRN Not Received",--E65*--G65)) -> 3000 | I65: 0162/2025 | J65: 45892 | K65: 10000 | L65: 0.75 | M65: =K65*L65 -> 7500 | N65: 0 | O65: 0 | P65: =M65+O65 -> 7500 | Q65: 25-26/027 | R65: 45897 | S65: Pharmax India Pvt Ltd | T65: FG07416 | U65: =IFERROR(VLOOKUP(T65,'item master'!B:C,2,0),"") -> HALDOQUE DECONOAS 50MG/ML (HALOPÉRIDOL) INJ.B/5 AMP | V65: 10000 | W65: 0 | X65: 0.75 | Y65: =V65*X65 -> 7500 | Z65: 0 | AA65: =Y65+Z65 -> 7500 | AB65: 0.3 | AC65: =Y65*AB65 -> 2250 | AD65: =AC65 -> 2250 | AE65: 45909 | AF65: EPHCOP25207M201S | AG65: 10140 | AH65: =AG65 -> 10140 | AJ65: =V65-AG65 -> -140 | AK65: 25-26/437 | AL65: 46024 | AM65: UNIQUE VENTURES | AN65: 0.75 | AO65: =AG65*AN65 -> 7605 | AS65: =AO65+AP65+AQ65+AR65 -> 7605 | AT65: 266199219 | AU65: 46091 | AV65: Goods Received at Warehouse | AW65: 10140 | AX65: 26KIN1/IGRN000130 | AZ65: -2250 | BA65: =AD65+AZ65 -> 0 | BB65: 0 | BC65: 0 | BD65: =IF(AK65>0,BA65+BB65+BC65,"0") -> 0 | BE65: =BA65-BD65 -> 0 | BF65: =BB65-BE65 -> 0 | BG65: =BE65-BF65 -> 0 | BH65: =AS65-BD65 -> 7605 | BI65: 7605 | BJ65: 46234 | BO65: =BI65+BL65 -> 7605 | BP65: =BH65-BO65 -> 0 | BQ65: =IF(ROUND(BG65,2)>0,"Advance With Supplier",IF(ROUND(BP65,2)>0,"Payable Balance Supplier","Fully Paid")) -> Fully Paid | BS65: =IF(AX65<>"","Closed","Open") -> Closed | BT65: =IF(BS65="Open",TODAY()-J65,"Closed") -> Closed
A66: Unique Ventures | B66: 1597.25 | C66: 45887 | D66: Kinshasa | E66: 10000 | F66: Pack of 5 Amps | G66: =IF(AG66="","GRN Not Received",AW66/AG66) -> 1 | H66: =IF(E66="PRF_Details_Not Availbale","PRF Qty Not Available",IF(G66="GRN Not Received","GRN Not Received",--E66*--G66)) -> 10000 | I66: 0162/2025 | J66: 45892 | K66: 3000 | L66: 0.89 | M66: =K66*L66 -> 2670 | N66: 0 | O66: 0 | P66: =M66+O66 -> 2670 | Q66: 25-26/027 | R66: 45897 | S66: Pharmax India Pvt Ltd | T66: FG07417 | U66: =IFERROR(VLOOKUP(T66,'item master'!B:C,2,0),"") -> HALDOQUE 5MG/ML (HALOPÉRIDOLUM) INJ. B/5 AMP | V66: 3000 | W66: 0 | X66: 0.89 | Y66: =V66*X66 -> 2670 | Z66: 0 | AA66: =Y66+Z66 -> 2670 | AB66: 0.3 | AC66: =Y66*AB66 -> 801 | AD66: =AC66 -> 801 | AE66: 45909 | AF66: EPHCOP25207M201S | AG66: 2400 | AH66: =AG66 -> 2400 | AJ66: =V66-AG66 -> 600 | AK66: 25-26/495A | AL66: 46067 | AM66: UNIQUE VENTURES | AN66: 0.89 | AO66: =AG66*AN66 -> 2136 | AS66: =AO66+AP66+AQ66+AR66 -> 2136 | AT66: 267565869 | AU66: 46108 | AV66: Goods Received at Warehouse | AW66: 2400 | AX66: 26KIN1/IGRN000135 | AZ66: -801 | BA66: =AD66+AZ66 -> 0 | BB66: 0 | BC66: 0 | BD66: =IF(AK66>0,BA66+BB66+BC66,"0") -> 0 | BE66: =BA66-BD66 -> 0 | BF66: =BB66-BE66 -> 0 | BG66: =BE66-BF66 -> 0 | BH66: =AS66-BD66 -> 2136 | BI66: 2136 | BJ66: 46234 | BO66: =BI66+BL66 -> 2136 | BP66: =BH66-BO66 -> 0 | BQ66: =IF(ROUND(BG66,2)>0,"Advance With Supplier",IF(ROUND(BP66,2)>0,"Payable Balance Supplier","Fully Paid")) -> Fully Paid | BS66: =IF(AX66<>"","Closed","Open") -> Closed | BT66: =IF(BS66="Open",TODAY()-J66,"Closed") -> Closed
A67: Unique Ventures | B67: 1597.25 | C67: 45887 | D67: Kinshasa | E67: 50000 | F67: Per Vial | G67: =IF(AG67="","GRN Not Received",AW67/AG67) -> 1 | H67: =IF(E67="PRF_Details_Not Availbale","PRF Qty Not Available",IF(G67="GRN Not Received","GRN Not Received",--E67*--G67)) -> 50000 | I67: 0162/2025 | J67: 45892 | K67: 50000 | L67: 0.11 | M67: =K67*L67 -> 5500 | N67: 0 | O67: 0 | P67: =M67+O67 -> 5500 | Q67: 25-26/027 | R67: 45897 | S67: Pharmax India Pvt Ltd | T67: FG08743 | U67: =IFERROR(VLOOKUP(T67,'item master'!B:C,2,0),"") -> UNIDEX – DEXAMETHASONE + NEOMYCINE GOUTTES OCULAIRES / OTIQUES 10 ML | V67: 50000 | W67: 0 | X67: 0.11 | Y67: =V67*X67 -> 5500 | Z67: 0 | AA67: =Y67+Z67 -> 5500 | AB67: 0.3 | AC67: =Y67*AB67 -> 1650 | AD67: =AC67 -> 1650 | AE67: 45909 | AF67: EPHCOP25207M201S | AG67: 50400 | AH67: =AG67 -> 50400 | AJ67: =V67-AG67 -> -400 | AK67: 25-26/437 | AL67: 46024 | AM67: UNIQUE VENTURES | AN67: 0.11 | AO67: =AG67*AN67 -> 5544 | AS67: =AO67+AP67+AQ67+AR67 -> 5544 | AT67: 266199219 | AU67: 46091 | AV67: Goods Received at Warehouse | AW67: 50400 | AX67: 26KIN1/IGRN000130 | AZ67: -1650 | BA67: =AD67+AZ67 -> 0 | BB67: 0 | BC67: 0 | BD67: =IF(AK67>0,BA67+BB67+BC67,"0") -> 0 | BE67: =BA67-BD67 -> 0 | BF67: =BB67-BE67 -> 0 | BG67: =BE67-BF67 -> 0 | BH67: =AS67-BD67 -> 5544 | BI67: 5544 | BJ67: 46234 | BO67: =BI67+BL67 -> 5544 | BP67: =BH67-BO67 -> 0 | BQ67: =IF(ROUND(BG67,2)>0,"Advance With Supplier",IF(ROUND(BP67,2)>0,"Payable Balance Supplier","Fully Paid")) -> Fully Paid | BS67: =IF(AX67<>"","Closed","Open") -> Closed | BT67: =IF(BS67="Open",TODAY()-J67,"Closed") -> Closed
A68: Unique Ventures | B68: 1597.25 | C68: 45887 | D68: Kinshasa | E68: 25000 | F68: Per Vial | G68: =IF(AG68="","GRN Not Received",AW68/AG68) -> 1 | H68: =IF(E68="PRF_Details_Not Availbale","PRF Qty Not Available",IF(G68="GRN Not Received","GRN Not Received",--E68*--G68)) -> 25000 | I68: 0162/2025 | J68: 45892 | K68: 25000 | L68: 0.22 | M68: =K68*L68 -> 5500 | N68: 0 | O68: 0 | P68: =M68+O68 -> 5500 | Q68: 25-26/027 | R68: 45897 | S68: Pharmax India Pvt Ltd | T68: FG07415 | U68: =IFERROR(VLOOKUP(T68,'item master'!B:C,2,0),"") -> VOMITRON 0.075 MG/1.5ML (PALONOSÉTRON) INJ. B/1 VIAL | V68: 25000 | W68: 0 | X68: 0.22 | Y68: =V68*X68 -> 5500 | Z68: 0 | AA68: =Y68+Z68 -> 5500 | AB68: 0.3 | AC68: =Y68*AB68 -> 1650 | AD68: =AC68 -> 1650 | AE68: 45909 | AF68: EPHCOP25207M201S | AG68: 25180 | AH68: =AG68 -> 25180 | AJ68: =V68-AG68 -> -180 | AK68: 25-26/334 | AL68: 45958 | AM68: UNIQUE VENTURES | AN68: 0.22 | AO68: =AG68*AN68 -> 5539.6 | AS68: =AO68+AP68+AQ68+AR68 -> 5539.6 | AT68: AMC2465942 | AU68: 45987 | AV68: Goods Received at Warehouse | AW68: 25180 | AX68: 26KIN1/IGRN000009 | AY68: 46030 | AZ68: =-1800 -> -1800 | BA68: =AD68+AZ68 -> -150 | BB68: 0 | BC68: 0 | BD68: =IF(AK68>0,BA68+BB68+BC68,"0") -> -150 | BE68: =BA68-BD68 -> 0 | BF68: =BB68-BE68 -> 0 | BG68: =BE68-BF68 -> 0 | BH68: =AS68-BD68 -> 5689.6 | BI68: =BH68 -> 5689.6 | BJ68: 45989 | BK68: CFZEE33208EPHCOP | BO68: =BI68+BL68 -> 5689.6 | BP68: =BH68-BO68 -> 0 | BQ68: =IF(ROUND(BG68,2)>0,"Advance With Supplier",IF(ROUND(BP68,2)>0,"Payable Balance Supplier","Fully Paid")) -> Fully Paid | BS68: =IF(AX68<>"","Closed","Open") -> Closed | BT68: =IF(BS68="Open",TODAY()-J68,"Closed") -> Closed
A69: Aizah Pharma FZCO | B69: 1629.25 | C69: 45898 | D69: Goma | E69: 3000 | F69: Pack of 10 Amps | G69: =IF(AG69="","GRN Not Received",AW69/AG69) -> 1 | H69: =IF(E69="PRF_Details_Not Availbale","PRF Qty Not Available",IF(G69="GRN Not Received","GRN Not Received",--E69*--G69)) -> 3000 | I69: 026/2025 | J69: 45961 | K69: 4000 | L69: 0.74 | M69: =K69*L69 -> 2960 | N69: 0 | O69: 0 | P69: =M69+O69 -> 2960 | Q69: 25-26/033 | R69: 45957 | S69: Pharmax India Pvt Ltd | T69: FG00537 | U69: =IFERROR(VLOOKUP(T69,'item master'!B:C,2,0),"") -> CAFEINE B/10AMP | V69: 4000 | W69: 0 | X69: 0.74 | Y69: =V69*X69 -> 2960 | Z69: 0 | AA69: =Y69+Z69 -> 2960 | AB69: 0.3 | AC69: =Y69*AB69 -> 888 | AD69: =AC69 -> 888 | AE69: 45973 | AF69: EPHCOP315086Q2D0 | AG69: 3720 | AH69: =AG69 -> 3720 | AJ69: =V69-AG69 -> 280 | AK69: 25-26/445 | AL69: 46029 | AM69: AIZAH PHARMA FZCO | AN69: 0.74 | AO69: =AG69*AN69 -> 2752.8 | AS69: =AO69+AP69+AQ69+AR69 -> 2752.8 | AT69: 265753941 | AU69: 46097 | AV69: Goods Received at Warehouse | AW69: 3720 | AX69: 26GMAI/IGRN000002 | AY69: 46185 | AZ69: 0 | BA69: =AD69+AZ69 -> 888 | BB69: 0 | BC69: 0 | BD69: =IF(AK69>0,BA69+BB69+BC69,"0") -> 888 | BE69: =BA69-BD69 -> 0 | BF69: =BB69-BE69 -> 0 | BG69: =BE69-BF69 -> 0 | BH69: =AS69-BD69 -> 1864.8 | BI69: 1864.8 | BJ69: 0 | BL69: 0 | BM69: 033DBFC262122569 | BN69: 46237 | BO69: =BI69+BL69 -> 1864.8 | BP69: =BH69-BO69 -> 0 | BQ69: =IF(ROUND(BG69,2)>0,"Advance With Supplier",IF(ROUND(BP69,2)>0,"Payable Balance Supplier","Fully Paid")) -> Fully Paid | BS69: =IF(AX69<>"","Closed","Open") -> Closed | BT69: =IF(BS69="Open",TODAY()-J69,"Closed") -> Closed
A70: Aizah Pharma FZCO | B70: 1629.25 | C70: 45898 | D70: Goma | E70: 9000 | F70: Per Vial | G70: =IF(AG70="","GRN Not Received",AW70/AG70) -> 0.7 | H70: =IF(E70="PRF_Details_Not Availbale","PRF Qty Not Available",IF(G70="GRN Not Received","GRN Not Received",--E70*--G70)) -> 6300 | I70: 026/2025 | J70: 45961 | K70: 6000 | L70: 0.31 | M70: =K70*L70 -> 1860 | N70: 0 | O70: 0 | P70: =M70+O70 -> 1860 | Q70: 25-26/033 | R70: 45957 | S70: Pharmax India Pvt Ltd | T70: FG06811 | U70: =IFERROR(VLOOKUP(T70,'item master'!B:C,2,0),"") -> UNIKORT-40 (TRIAMCINOLONE) B/1 VIAL+SER | V70: 6000 | W70: 0 | X70: 0.31 | Y70: =V70*X70 -> 1860 | Z70: 0 | AA70: =Y70+Z70 -> 1860 | AB70: 0.3 | AC70: =Y70*AB70 -> 558 | AD70: =AC70 -> 558 | AE70: 45973 | AF70: EPHCOP315086Q2D0 | AG70: 6000 | AH70: =AG70 -> 6000 | AJ70: =V70-AG70 -> 0 | AK70: 25-26/489 | AL70: 46064 | AM70: AIZAH PHARMA FZCO | AN70: 0.31 | AO70: =AG70*AN70 -> 1860 | AS70: =AO70+AP70+AQ70+AR70 -> 1860 | AT70: AMC2508816 | AU70: 46100 | AV70: Goods Received at Warehouse | AW70: 4200 | AX70: 26GMAI/IGRN000010 | AY70: 46185 | AZ70: 0 | BA70: =AD70+AZ70 -> 558 | BB70: 0 | BC70: 0 | BD70: =IF(AK70>0,BA70+BB70+BC70,"0") -> 558 | BE70: =BA70-BD70 -> 0 | BF70: =BB70-BE70 -> 0 | BG70: =BE70-BF70 -> 0 | BH70: =AS70-BD70 -> 1302 | BI70: 1542 | BL70: -240 | BM70: 033DBFC262122569 | BN70: 46237 | BO70: =BI70+BL70 -> 1302 | BP70: =BH70-BO70 -> 0 | BQ70: =IF(ROUND(BG70,2)>0,"Advance With Supplier",IF(ROUND(BP70,2)>0,"Payable Balance Supplier","Fully Paid")) -> Fully Paid | BS70: =IF(AX70<>"","Closed","Open") -> Closed | BT70: =IF(BS70="Open",TODAY()-J70,"Closed") -> Closed
A71: Aizah Pharma FZCO | B71: 1629.25 | C71: 45898 | D71: Goma | E71: 4000 | F71: Per Vial | G71: =IF(AG71="","GRN Not Received",AW71/AG71) -> 1.4285714 | H71: =IF(E71="PRF_Details_Not Availbale","PRF Qty Not Available",IF(G71="GRN Not Received","GRN Not Received",--E71*--G71)) -> 5714.2857 | I71: 026/2025 | J71: 45961 | K71: 10000 | L71: 0.5 | M71: =K71*L71 -> 5000 | N71: 0 | O71: 0 | P71: =M71+O71 -> 5000 | Q71: 25-26/033 | R71: 45957 | S71: Pharmax India Pvt Ltd | T71: FG06812 | U71: =IFERROR(VLOOKUP(T71,'item master'!B:C,2,0),"") -> UNIKORT-80 (TRIAMCINOLONE) B/1 VIAL +SER | V71: 10000 | W71: 0 | X71: 0.5 | Y71: =V71*X71 -> 5000 | Z71: 0 | AA71: =Y71+Z71 -> 5000 | AB71: 0.3 | AC71: =Y71*AB71 -> 1500 | AD71: =AC71 -> 1500 | AE71: 45973 | AF71: EPHCOP315086Q2D0 | AG71: 4200 | AH71: =AG71 -> 4200 | AJ71: =V71-AG71 -> 5800 | AK71: 25-26/489 | AL71: 46064 | AM71: AIZAH PHARMA FZCO | AN71: 0.5 | AO71: =AG71*AN71 -> 2100 | AS71: =AO71+AP71+AQ71+AR71 -> 2100 | AT71: AMC2508816 | AU71: 46100 | AV71: Goods Received at Warehouse | AW71: 6000 | AX71: 26GMAI/IGRN000010 | AY71: 46185 | AZ71: 0 | BA71: =AD71+AZ71 -> 1500 | BB71: 0 | BC71: 0 | BD71: =IF(AK71>0,BA71+BB71+BC71,"0") -> 1500 | BE71: =BA71-BD71 -> 0 | BF71: =BB71-BE71 -> 0 | BG71: =BE71-BF71 -> 0 | BH71: =AS71-BD71 -> 600 | BI71: 360 | BL71: 240 | BM71: 033DBFC262122569 | BN71: 46237 | BO71: =BI71+BL71 -> 600 | BP71: =BH71-BO71 -> 0 | BQ71: =IF(ROUND(BG71,2)>0,"Advance With Supplier",IF(ROUND(BP71,2)>0,"Payable Balance Supplier","Fully Paid")) -> Fully Paid | BS71: =IF(AX71<>"","Closed","Open") -> Closed | BT71: =IF(BS71="Open",TODAY()-J71,"Closed") -> Closed
A72: Aizah Pharma FZCO | B72: 1685.25 | C72: 45916 | D72: Kinshasa | E72: 50000 | F72: Per Vial | G72: =IF(AG72="","GRN Not Received",AW72/AG72) -> 1 | H72: =IF(E72="PRF_Details_Not Availbale","PRF Qty Not Available",IF(G72="GRN Not Received","GRN Not Received",--E72*--G72)) -> 50000 | I72: 004/2025 | J72: 45940 | K72: 50000 | L72: 0.11 | M72: =K72*L72 -> 5500 | N72: 0 | O72: 0 | P72: =M72+O72 -> 5500 | Q72: 25-26/032 | R72: 45938 | S72: Pharmax India Pvt Ltd | T72: FG08743 | U72: =IFERROR(VLOOKUP(T72,'item master'!B:C,2,0),"") -> UNIDEX – DEXAMETHASONE + NEOMYCINE GOUTTES OCULAIRES / OTIQUES 10 ML | V72: 50000 | W72: 0 | X72: 0.11 | Y72: =V72*X72 -> 5500 | Z72: 0 | AA72: =Y72+Z72 -> 5500 | AB72: 0.3 | AC72: =Y72*AB72 -> 1650 | AD72: 1650 | AE72: 45957 | AF72: EPHCOP299081055G | AG72: 50300 | AH72: =AG72 -> 50300 | AJ72: =V72-AG72 -> -300 | AK72: 25-26/437A | AL72: 46024 | AM72: AIZAH PHARMA FZCO | AN72: 0.11 | AO72: =AG72*AN72 -> 5533 | AS72: =AO72+AP72+AQ72+AR72 -> 5533 | AT72: 266199219 | AU72: 46091 | AV72: Goods Received at Warehouse | AW72: 50300 | AX72: 26KIN1/IGRN000130 | AZ72: 0 | BA72: =AD72+AZ72 -> 1650 | BB72: 0 | BC72: 0 | BD72: =IF(AK72>0,BA72+BB72+BC72,"0") -> 1650 | BE72: =BA72-BD72 -> 0 | BF72: =BB72-BE72 -> 0 | BG72: =BE72-BF72 -> 0 | BH72: =AS72-BD72 -> 3883 | BI72: 393.2 | BL72: 3489.8 | BM72: 033DBFC262122569 | BN72: 46237 | BO72: =BI72+BL72 -> 3883 | BP72: =BH72-BO72 -> 0 | BQ72: =IF(ROUND(BG72,2)>0,"Advance With Supplier",IF(ROUND(BP72,2)>0,"Payable Balance Supplier","Fully Paid")) -> Fully Paid | BS72: =IF(AX72<>"","Closed","Open") -> Closed | BT72: =IF(BS72="Open",TODAY()-J72,"Closed") -> Closed
A73: Aizah Pharma FZCO | B73: 1645.25 | C73: 45899 | D73: Lubumbashi | E73: 9000 | F73: Per Vial | G73: =IF(AG73="","GRN Not Received",AW73/AG73) -> 1 | H73: =IF(E73="PRF_Details_Not Availbale","PRF Qty Not Available",IF(G73="GRN Not Received","GRN Not Received",--E73*--G73)) -> 9000 | I73: 027/2025 | J73: 45961 | K73: 9000 | L73: 0.31 | M73: =K73*L73 -> 2790 | N73: 0 | O73: 0 | P73: =M73+O73 -> 2790 | Q73: 25-26/034 | R73: 45957 | S73: Pharmax India Pvt Ltd | T73: FG06811 | U73: =IFERROR(VLOOKUP(T73,'item master'!B:C,2,0),"") -> UNIKORT-40 (TRIAMCINOLONE) B/1 VIAL+SER | V73: 9000 | W73: 0 | X73: 0.31 | Y73: =V73*X73 -> 2790 | Z73: 0 | AA73: =Y73+Z73 -> 2790 | AB73: 0.3 | AC73: =Y73*AB73 -> 837 | AD73: 837 | AE73: 45973 | AF73: EPHCOP315086Q2D0 | AG73: 9000 | AH73: =AG73 -> 9000 | AJ73: =V73-AG73 -> 0 | AK73: 25-26/490 | AL73: 46064 | AM73: AIZAH PHARMA FZCO | AN73: 0.31 | AO73: =AG73*AN73 -> 2790 | AS73: =AO73+AP73+AQ73+AR73 -> 2790 | AT73: AMC2510432 | AU73: 46100 | AV73: Goods Received at Warehouse | AW73: 9000 | AX73: 26KATI/IGRN000017 | AY73: 46218 | AZ73: 0 | BA73: =AD73+AZ73 -> 837 | BB73: 0 | BC73: 0 | BD73: =IF(AK73>0,BA73+BB73+BC73,"0") -> 837 | BE73: =BA73-BD73 -> 0 | BF73: =BB73-BE73 -> 0 | BG73: =BE73-BF73 -> 0 | BH73: =AS73-BD73 -> 1953 | BI73: 0 | BL73: 1953 | BM73: 033DBFC262122569 | BN73: 46237 | BO73: =BI73+BL73 -> 1953 | BP73: =BH73-BO73 -> 0 | BQ73: =IF(ROUND(BG73,2)>0,"Advance With Supplier",IF(ROUND(BP73,2)>0,"Payable Balance Supplier","Fully Paid")) -> Fully Paid | BS73: =IF(AX73<>"","Closed","Open") -> Closed | BT73: =IF(BS73="Open",TODAY()-J73,"Closed") -> Closed
A74: Aizah Pharma FZCO | B74: 1645.25 | C74: 45899 | D74: Lubumbashi | E74: 9000 | F74: Per Vial | G74: =IF(AG74="","GRN Not Received",AW74/AG74) -> 1 | H74: =IF(E74="PRF_Details_Not Availbale","PRF Qty Not Available",IF(G74="GRN Not Received","GRN Not Received",--E74*--G74)) -> 9000 | I74: 027/2025 | J74: 45961 | K74: 10000 | L74: 0.5 | M74: =K74*L74 -> 5000 | N74: 0 | O74: 0 | P74: =M74+O74 -> 5000 | Q74: 25-26/034 | R74: 45957 | S74: Pharmax India Pvt Ltd | T74: FG06812 | U74: =IFERROR(VLOOKUP(T74,'item master'!B:C,2,0),"") -> UNIKORT-80 (TRIAMCINOLONE) B/1 VIAL +SER | V74: 10000 | W74: 0 | X74: 0.5 | Y74: =V74*X74 -> 5000 | Z74: 0 | AA74: =Y74+Z74 -> 5000 | AB74: 0.3 | AC74: =Y74*AB74 -> 1500 | AD74: 1500 | AE74: 45973 | AF74: EPHCOP315086Q2D0 | AG74: 9900 | AH74: =AG74 -> 9900 | AJ74: =V74-AG74 -> 100 | AK74: 25-26/490 | AL74: 46064 | AM74: AIZAH PHARMA FZCO | AN74: 0.5 | AO74: =AG74*AN74 -> 4950 | AS74: =AO74+AP74+AQ74+AR74 -> 4950 | AT74: AMC2510432 | AU74: 46100 | AV74: Goods Received at Warehouse | AW74: 9900 | AX74: 26KATI/IGRN000017 | AY74: 46218 | AZ74: 0 | BA74: =AD74+AZ74 -> 1500 | BB74: 0 | BC74: 0 | BD74: =IF(AK74>0,BA74+BB74+BC74,"0") -> 1500 | BE74: =BA74-BD74 -> 0 | BF74: =BB74-BE74 -> 0 | BG74: =BE74-BF74 -> 0 | BH74: =AS74-BD74 -> 3450 | BI74: 0 | BL74: 3450 | BM74: 033DBFC262122569 | BN74: 46237 | BO74: =BI74+BL74 -> 3450 | BP74: =BH74-BO74 -> 0 | BQ74: =IF(ROUND(BG74,2)>0,"Advance With Supplier",IF(ROUND(BP74,2)>0,"Payable Balance Supplier","Fully Paid")) -> Fully Paid | BS74: =IF(AX74<>"","Closed","Open") -> Closed | BT74: =IF(BS74="Open",TODAY()-J74,"Closed") -> Closed
A75: Aizah Pharma FZCO | B75: 1718.25 | C75: 45964 | D75: Kinshasa | E75: 80000 | F75: Per Pack 100 Amp | G75: =IF(AG75="","GRN Not Received",AW75/AG75) -> 10 | H75: =IF(E75="PRF_Details_Not Availbale","PRF Qty Not Available",IF(G75="GRN Not Received","GRN Not Received",--E75*--G75)) -> 800000 | I75: 033/2025 | J75: 45969 | K75: 8000 | L75: 3.3 | M75: =K75*L75 -> 26400 | N75: 0 | O75: 0 | P75: =M75+O75 -> 26400 | Q75: 25-26/035 | R75: 45964 | S75: Pharmax India Pvt Ltd | T75: FG04064 | U75: =IFERROR(VLOOKUP(T75,'item master'!B:C,2,0),"") -> PAPAVERINE 40MG/ML INJ. 10AMP | V75: 8000 | W75: 0 | X75: 3.3 | Y75: =V75*X75 -> 26400 | Z75: 0 | AA75: =Y75+Z75 -> 26400 | AB75: 0.3 | AC75: =Y75*AB75 -> 7920 | AD75: 7920 | AE75: 45982 | AF75: EPHCOP325089OJB5 | AG75: 8040 | AH75: =AG75 -> 8040 | AJ75: =V75-AG75 -> -40 | AK75: 25-26/495A | AL75: 46067 | AM75: AIZAH PHARMA FZCO | AN75: 3.3 | AO75: =AG75*AN75 -> 26532 | AS75: =AO75+AP75+AQ75+AR75 -> 26532 | AT75: 267565869 | AU75: 46108 | AV75: Goods Received at Warehouse | AW75: 80400 | AX75: 26KIN1/IGRN000135 | AY75: 46146 | AZ75: 0 | BA75: =AD75+AZ75 -> 7920 | BB75: 0 | BC75: 0 | BD75: =IF(AK75>0,BA75+BB75+BC75,"0") -> 7920 | BE75: =BA75-BD75 -> 0 | BF75: =BB75-BE75 -> 0 | BG75: =BE75-BF75 -> 0 | BH75: =AS75-BD75 -> 18612 | BI75: 0 | BL75: 18612 | BM75: 033DBFC262122569 | BN75: 46237 | BO75: =BI75+BL75 -> 18612 | BP75: =BH75-BO75 -> 0 | BQ75: =IF(ROUND(BG75,2)>0,"Advance With Supplier",IF(ROUND(BP75,2)>0,"Payable Balance Supplier","Fully Paid")) -> Fully Paid | BS75: =IF(AX75<>"","Closed","Open") -> Closed | BT75: =IF(BS75="Open",TODAY()-J75,"Closed") -> Closed
A76: Aizah Pharma FZCO | B76: 1738.25 | C76: 46001 | D76: Kinshasa | E76: 5000 | F76: Pack of 5 Amps | G76: =IF(AG76="","GRN Not Received",AW76/AG76) -> 1 | H76: =IF(E76="PRF_Details_Not Availbale","PRF Qty Not Available",IF(G76="GRN Not Received","GRN Not Received",--E76*--G76)) -> 5000 | I76: 072/2025 | J76: 46007 | K76: 5000 | L76: 1.6 | M76: =K76*L76 -> 8000 | N76: 0 | O76: 0 | P76: =M76+O76 -> 8000 | Q76: 25-26/036 | R76: 46006 | S76: Pharmax India Pvt Ltd | T76: FG07410 | U76: =IFERROR(VLOOKUP(T76,'item master'!B:C,2,0),"") -> ATARIUM 50MG/5ML (ATACURIUM ) INJ. B/5 AMP. | V76: 5000 | W76: 0 | X76: 1.6 | Y76: =V76*X76 -> 8000 | Z76: 0 | AA76: =Y76+Z76 -> 8000 | AB76: 0.3 | AC76: =Y76*AB76 -> 2400 | AD76: 0 | AG76: 3520 | AH76: =AG76 -> 3520 | AJ76: =V76-AG76 -> 1480 | AK76: 26-27/060 | AL76: 46163 | AM76: AIZAH PHARMA FZCO | AN76: 1.6 | AO76: =AG76*AN76 -> 5632 | AS76: =AO76+AP76+AQ76+AR76 -> 5632 | AT76: 071-6141 5944 | AU76: 46165 | AV76: Goods Received at Warehouse | AW76: 3520 | AX76: 26KIN1/IGRN000194 | AY76: 46192 | AZ76: 0 | BA76: =AD76+AZ76 -> 0 | BB76: 0 | BC76: 0 | BD76: =IF(AK76>0,BA76+BB76+BC76,"0") -> 0 | BE76: =BA76-BD76 -> 0 | BF76: =BB76-BE76 -> 0 | BG76: =BE76-BF76 -> 0 | BH76: =AS76-BD76 -> 5632 | BI76: 0 | BL76: 5632 | BM76: 033DBFC262122569 | BN76: 46237 | BO76: =BI76+BL76 -> 5632 | BP76: =BH76-BO76 -> 0 | BQ76: =IF(ROUND(BG76,2)>0,"Advance With Supplier",IF(ROUND(BP76,2)>0,"Payable Balance Supplier","Fully Paid")) -> Fully Paid | BS76: =IF(AX76<>"","Closed","Open") -> Closed | BT76: =IF(BS76="Open",TODAY()-J76,"Closed") -> Closed
A77: Aizah Pharma FZCO | B77: 1761.25 | C77: 46037 | D77: Kinshasa | E77: 80000 | F77: Per Pack 100 Amp | G77: =IF(AG77="","GRN Not Received",AW77/AG77) -> 0 | H77: =IF(E77="PRF_Details_Not Availbale","PRF Qty Not Available",IF(G77="GRN Not Received","GRN Not Received",--E77*--G77)) -> 0 | I77: 018/2026 | J77: 46044 | K77: 8000 | L77: 4.4 | M77: =K77*L77 -> 35200 | N77: 0 | O77: 0 | P77: =M77+O77 -> 35200 | Q77: 25-26/045 | R77: 46044 | S77: Pharmax India Pvt Ltd | T77: FG03867 | U77: =IFERROR(VLOOKUP(T77,'item master'!B:C,2,0),"") -> DIAZEPAM 10MG/2ML INJ B/10AMP | V77: 8000 | W77: 0 | X77: 4.4 | Y77: =V77*X77 -> 35200 | Z77: 0 | AA77: =Y77+Z77 -> 35200 | AB77: 0.3 | AC77: =Y77*AB77 -> 10560 | AD77: =AC77 -> 10560 | AE77: 46055 | AF77: 033DBFC260334522 | AG77: 8000 | AH77: =AG77 -> 8000 | AJ77: =V77-AG77 -> 0 | AK77: 26-27/106 | AL77: 46198 | AM77: AIZAH PHARMA FZCO | AN77: 4.4 | AO77: =AG77*AN77 -> 35200 | AS77: =AO77+AP77+AQ77+AR77 -> 35200 | AT77: NO BL RECEIVED | AV77: Final Invoice Received – Awaiting BL | AZ77: 0 | BA77: =AD77+AZ77 -> 10560 | BB77: 0 | BC77: 0 | BD77: =IF(AK77>0,BA77+BB77+BC77,"0") -> 10560 | BE77: =BA77-BD77 -> 0 | BF77: =BB77-BE77 -> 0 | BG77: =BE77-BF77 -> 0 | BH77: =AS77-BD77 -> 24640 | BI77: 0 | BO77: =BI77+BL77 -> 0 | BP77: =BH77-BO77 -> 24640 | BQ77: =IF(ROUND(BG77,2)>0,"Advance With Supplier",IF(ROUND(BP77,2)>0,"Payable Balance Supplier","Fully Paid")) -> Payable Balance Supplier | BS77: =IF(AX77<>"","Closed","Open") -> Open | BT77: =IF(BS77="Open",TODAY()-J77,"Closed") -> 219
A78: Aizah Pharma FZCO | B78: 1761.25 | C78: 46037 | D78: Kinshasa | E78: 5000 | F78: Per Vial | G78: =IF(AG78="","GRN Not Received",AW78/AG78) -> 1 | H78: =IF(E78="PRF_Details_Not Availbale","PRF Qty Not Available",IF(G78="GRN Not Received","GRN Not Received",--E78*--G78)) -> 5000 | I78: 018/2026 | J78: 46044 | K78: 10000 | L78: 1.1 | M78: =K78*L78 -> 11000 | N78: 0 | O78: 0 | P78: =M78+O78 -> 11000 | Q78: 25-26/045 | R78: 46044 | S78: Pharmax India Pvt Ltd | T78: FG06678 | U78: =IFERROR(VLOOKUP(T78,'item master'!B:C,2,0),"") -> HEPAQUE (HEPARIN) 25000UI/5ML INJ. B/1 VIAL | V78: 10000 | W78: 0 | X78: 1.1 | Y78: =V78*X78 -> 11000 | Z78: 0 | AA78: =Y78+Z78 -> 11000 | AB78: 0.3 | AC78: =Y78*AB78 -> 3300 | AD78: =AC78 -> 3300 | AE78: 46055 | AF78: 033DBFC260334522 | AG78: 10080 | AH78: =AG78 -> 10080 | AJ78: =V78-AG78 -> -80 | AK78: 26-27/102 | AL78: 46225 | AM78: AIZAH PHARMA FZCO | AN78: 1.1 | AO78: =AG78*AN78 -> 11088 | AS78: =AO78+AP78+AQ78+AR78 -> 11088 | AT78: 071-6099 3601 | AU78: 46198 | AV78: Goods Received at Warehouse | AW78: 10080 | AX78: 26KIN1/IGRN000229 | AY78: 46225 | AZ78: 0 | BA78: =AD78+AZ78 -> 3300 | BB78: 0 | BC78: 0 | BD78: =IF(AK78>0,BA78+BB78+BC78,"0") -> 3300 | BE78: =BA78-BD78 -> 0 | BF78: =BB78-BE78 -> 0 | BG78: =BE78-BF78 -> 0 | BH78: =AS78-BD78 -> 7788 | BI78: 0 | BL78: 7788 | BM78: 033DBFC262122569 | BN78: 46237 | BO78: =BI78+BL78 -> 7788 | BP78: =BH78-BO78 -> 0 | BQ78: =IF(ROUND(BG78,2)>0,"Advance With Supplier",IF(ROUND(BP78,2)>0,"Payable Balance Supplier","Fully Paid")) -> Fully Paid | BS78: =IF(AX78<>"","Closed","Open") -> Closed | BT78: =IF(BS78="Open",TODAY()-J78,"Closed") -> Closed
A79: Aizah Pharma FZCO | B79: 1761.25 | C79: 46037 | D79: Kinshasa | E79: 4000 | F79: Per Pack 100 Amp | G79: =IF(AG79="","GRN Not Received",AW79/AG79) -> 0 | H79: =IF(E79="PRF_Details_Not Availbale","PRF Qty Not Available",IF(G79="GRN Not Received","GRN Not Received",--E79*--G79)) -> 0 | I79: 018/2026 | J79: 46044 | K79: 4000 | L79: 5.4 | M79: =K79*L79 -> 21600 | N79: 0 | O79: 0 | P79: =M79+O79 -> 21600 | Q79: 25-26/045 | R79: 46044 | S79: Pharmax India Pvt Ltd | T79: FG01261 | U79: =IFERROR(VLOOKUP(T79,'item master'!B:C,2,0),"") -> ERGOMETRINE B/10AMP | V79: 4000 | W79: 0 | X79: 5.4 | Y79: =V79*X79 -> 21600 | Z79: 0 | AA79: =Y79+Z79 -> 21600 | AB79: 0.3 | AC79: =Y79*AB79 -> 6480 | AD79: =AC79 -> 6480 | AE79: 46055 | AF79: 033DBFC260334522 | AG79: 4000 | AH79: =AG79 -> 4000 | AJ79: =V79-AG79 -> 0 | AK79: 26-27/106 | AL79: 46198 | AM79: AIZAH PHARMA FZCO | AN79: 5.4 | AO79: =AG79*AN79 -> 21600 | AS79: =AO79+AP79+AQ79+AR79 -> 21600 | AT79: NO BL RECEIVED | AV79: Final Invoice Received – Awaiting BL | AZ79: 0 | BA79: =AD79+AZ79 -> 6480 | BB79: 0 | BC79: 0 | BD79: =IF(AK79>0,BA79+BB79+BC79,"0") -> 6480 | BE79: =BA79-BD79 -> 0 | BF79: =BB79-BE79 -> 0 | BG79: =BE79-BF79 -> 0 | BH79: =AS79-BD79 -> 15120 | BI79: 0 | BO79: =BI79+BL79 -> 0 | BP79: =BH79-BO79 -> 15120 | BQ79: =IF(ROUND(BG79,2)>0,"Advance With Supplier",IF(ROUND(BP79,2)>0,"Payable Balance Supplier","Fully Paid")) -> Payable Balance Supplier | BS79: =IF(AX79<>"","Closed","Open") -> Open | BT79: =IF(BS79="Open",TODAY()-J79,"Closed") -> 219
A80: Aizah Pharma FZCO | B80: 1761.25 | C80: 46037 | D80: Kinshasa | E80: 20000 | F80: Per Vial | G80: =IF(AG80="","GRN Not Received",AW80/AG80) -> 0 | H80: =IF(E80="PRF_Details_Not Availbale","PRF Qty Not Available",IF(G80="GRN Not Received","GRN Not Received",--E80*--G80)) -> 0 | I80: 018/2026 | J80: 46044 | K80: 20000 | L80: 1 | M80: =K80*L80 -> 20000 | N80: 0 | O80: 0 | P80: =M80+O80 -> 20000 | Q80: 25-26/045 | R80: 46044 | S80: Pharmax India Pvt Ltd | T80: FG06804 | U80: =IFERROR(VLOOKUP(T80,'item master'!B:C,2,0),"") -> TROBINIQUE-2G(SPECTINOMYCIN) B/1VIAL+3.2MLE.D | V80: 20000 | W80: 0 | X80: 1 | Y80: =V80*X80 -> 20000 | Z80: 0 | AA80: =Y80+Z80 -> 20000 | AB80: 0.3 | AC80: =Y80*AB80 -> 6000 | AD80: =AC80 -> 6000 | AE80: 46055 | AF80: 033DBFC260334522 | AG80: 20000 | AH80: =AG80 -> 20000 | AJ80: =V80-AG80 -> 0 | AK80: 25-26/555 | AL80: 46111 | AM80: AIZAH PHARMA FZCO | AN80: 1 | AO80: =AG80*AN80 -> 20000 | AS80: =AO80+AP80+AQ80+AR80 -> 20000 | AT80: 269716880 | AU80: 46163 | AV80: Transit | AZ80: 0 | BA80: =AD80+AZ80 -> 6000 | BB80: 0 | BC80: 0 | BD80: =IF(AK80>0,BA80+BB80+BC80,"0") -> 6000 | BE80: =BA80-BD80 -> 0 | BF80: =BB80-BE80 -> 0 | BG80: =BE80-BF80 -> 0 | BH80: =AS80-BD80 -> 14000 | BI80: 0 | BL80: 14000 | BM80: 033DBFC262122569 | BN80: 46237 | BO80: =BI80+BL80 -> 14000 | BP80: =BH80-BO80 -> 0 | BQ80: =IF(ROUND(BG80,2)>0,"Advance With Supplier",IF(ROUND(BP80,2)>0,"Payable Balance Supplier","Fully Paid")) -> Fully Paid | BS80: =IF(AX80<>"","Closed","Open") -> Closed | BT80: =IF(BS80="Open",TODAY()-J80,"Closed") -> Closed
A81: Aizah Pharma FZCO | B81: 1761.25 | C81: 46037 | D81: Kinshasa | E81: 1000 | F81: Per Vial | G81: =IF(AG81="","GRN Not Received",AW81/AG81) -> 1 | H81: =IF(E81="PRF_Details_Not Availbale","PRF Qty Not Available",IF(G81="GRN Not Received","GRN Not Received",--E81*--G81)) -> 1000 | I81: 018/2026 | J81: 46044 | K81: 2000 | L81: 3 | M81: =K81*L81 -> 6000 | N81: 0 | O81: 0 | P81: =M81+O81 -> 6000 | Q81: 25-26/045 | R81: 46044 | S81: Pharmax India Pvt Ltd | T81: FG06805 | U81: =IFERROR(VLOOKUP(T81,'item master'!B:C,2,0),"") -> SUXAMETHONIUM 100MG/2ML B/10AMP | V81: 2000 | W81: 0 | X81: 3 | Y81: =V81*X81 -> 6000 | Z81: 0 | AA81: =Y81+Z81 -> 6000 | AB81: 0.3 | AC81: =Y81*AB81 -> 1800 | AD81: =AC81 -> 1800 | AE81: 46055 | AF81: 033DBFC260334522 | AG81: 2140 | AH81: =AG81 -> 2140 | AJ81: =V81-AG81 -> -140 | AK81: 26-27/060 | AL81: 46163 | AM81: AIZAH PHARMA FZCO | AN81: 3 | AO81: =AG81*AN81 -> 6420 | AS81: =AO81+AP81+AQ81+AR81 -> 6420 | AT81: 071-6141 5944 | AU81: 46165 | AV81: Goods Received at Warehouse | AW81: 2140 | AX81: 26KIN1/IGRN000194 | AY81: 46192 | AZ81: 0 | BA81: =AD81+AZ81 -> 1800 | BB81: 0 | BC81: 0 | BD81: =IF(AK81>0,BA81+BB81+BC81,"0") -> 1800 | BE81: =BA81-BD81 -> 0 | BF81: =BB81-BE81 -> 0 | BG81: =BE81-BF81 -> 0 | BH81: =AS81-BD81 -> 4620 | BI81: 0 | BL81: 4620 | BM81: 033DBFC262122569 | BN81: 46237 | BO81: =BI81+BL81 -> 4620 | BP81: =BH81-BO81 -> 0 | BQ81: =IF(ROUND(BG81,2)>0,"Advance With Supplier",IF(ROUND(BP81,2)>0,"Payable Balance Supplier","Fully Paid")) -> Fully Paid | BS81: =IF(AX81<>"","Closed","Open") -> Closed | BT81: =IF(BS81="Open",TODAY()-J81,"Closed") -> Closed
A82: Aizah Pharma FZCO | B82: 1761.25 | C82: 46037 | D82: Kinshasa | E82: 20000 | F82: Per Vial | G82: =IF(AG82="","GRN Not Received",AW82/AG82) -> 0 | H82: =IF(E82="PRF_Details_Not Availbale","PRF Qty Not Available",IF(G82="GRN Not Received","GRN Not Received",--E82*--G82)) -> 0 | I82: 018/2026 | J82: 46044 | K82: 20000 | L82: 0.5 | M82: =K82*L82 -> 10000 | N82: 0 | O82: 0 | P82: =M82+O82 -> 10000 | Q82: 25-26/045 | R82: 46044 | S82: Pharmax India Pvt Ltd | T82: FG06812 | U82: =IFERROR(VLOOKUP(T82,'item master'!B:C,2,0),"") -> UNIKORT-80 (TRIAMCINOLONE) B/1 VIAL +SER | V82: 20000 | W82: 0 | X82: 0.5 | Y82: =V82*X82 -> 10000 | Z82: 0 | AA82: =Y82+Z82 -> 10000 | AB82: 0.3 | AC82: =Y82*AB82 -> 3000 | AD82: =AC82 -> 3000 | AE82: 46055 | AF82: 033DBFC260334522 | AG82: 26400 | AH82: =AG82 -> 26400 | AJ82: =V82-AG82 -> -6400 | AK82: 26-27/106 | AL82: 46198 | AM82: AIZAH PHARMA FZCO | AN82: 0.5 | AO82: =AG82*AN82 -> 13200 | AS82: =AO82+AP82+AQ82+AR82 -> 13200 | AT82: NO BL RECEIVED | AV82: Final Invoice Received – Awaiting BL | AZ82: 0 | BA82: =AD82+AZ82 -> 3000 | BB82: 0 | BC82: 0 | BD82: =IF(AK82>0,BA82+BB82+BC82,"0") -> 3000 | BE82: =BA82-BD82 -> 0 | BF82: =BB82-BE82 -> 0 | BG82: =BE82-BF82 -> 0 | BH82: =AS82-BD82 -> 10200 | BI82: 0 | BO82: =BI82+BL82 -> 0 | BP82: =BH82-BO82 -> 10200 | BQ82: =IF(ROUND(BG82,2)>0,"Advance With Supplier",IF(ROUND(BP82,2)>0,"Payable Balance Supplier","Fully Paid")) -> Payable Balance Supplier | BS82: =IF(AX82<>"","Closed","Open") -> Open | BT82: =IF(BS82="Open",TODAY()-J82,"Closed") -> 219
A83: Aizah Pharma FZCO | B83: 1772.26 | C83: 46037 | D83: Kinshasa | E83: 100000 | F83: Per Vial | G83: =IF(AG83="","GRN Not Received",AW83/AG83) -> 0 | H83: =IF(E83="PRF_Details_Not Availbale","PRF Qty Not Available",IF(G83="GRN Not Received","GRN Not Received",--E83*--G83)) -> 0 | I83: 018/2026 | J83: 46044 | K83: 100000 | L83: 0.11 | M83: =K83*L83 -> 11000 | N83: 0 | O83: 0 | P83: =M83+O83 -> 11000 | Q83: 25-26/045 | R83: 46044 | S83: Pharmax India Pvt Ltd | T83: FG08743 | U83: =IFERROR(VLOOKUP(T83,'item master'!B:C,2,0),"") -> UNIDEX – DEXAMETHASONE + NEOMYCINE GOUTTES OCULAIRES / OTIQUES 10 ML | V83: 100000 | W83: 0 | X83: 0.11 | Y83: =V83*X83 -> 11000 | Z83: 0 | AA83: =Y83+Z83 -> 11000 | AB83: 0.3 | AC83: =Y83*AB83 -> 3300 | AD83: =AC83 -> 3300 | AE83: 46055 | AF83: 033DBFC260334522 | AG83: 99150 | AH83: =AG83 -> 99150 | AJ83: =V83-AG83 -> 850 | AK83: 26-27/106 | AL83: 46198 | AM83: AIZAH PHARMA FZCO | AN83: 0.11 | AO83: =AG83*AN83 -> 10906.5 | AS83: =AO83+AP83+AQ83+AR83 -> 10906.5 | AT83: NO BL RECEIVED | AV83: Final Invoice Received – Awaiting BL | AZ83: 0 | BA83: =AD83+AZ83 -> 3300 | BB83: 0 | BC83: 0 | BD83: =IF(AK83>0,BA83+BB83+BC83,"0") -> 3300 | BE83: =BA83-BD83 -> 0 | BF83: =BB83-BE83 -> 0 | BG83: =BE83-BF83 -> 0 | BH83: =AS83-BD83 -> 7606.5 | BI83: 0 | BO83: =BI83+BL83 -> 0 | BP83: =BH83-BO83 -> 7606.5 | BQ83: =IF(ROUND(BG83,2)>0,"Advance With Supplier",IF(ROUND(BP83,2)>0,"Payable Balance Supplier","Fully Paid")) -> Payable Balance Supplier | BS83: =IF(AX83<>"","Closed","Open") -> Open | BT83: =IF(BS83="Open",TODAY()-J83,"Closed") -> 219
A84: Aizah Pharma FZCO | B84: 1765.25 | C84: 46020 | D84: Lubumbashi | E84: 6000 | F84: Per Pack 100 Amp | G84: =IF(AG84="","GRN Not Received",AW84/AG84) -> 0 | H84: =IF(E84="PRF_Details_Not Availbale","PRF Qty Not Available",IF(G84="GRN Not Received","GRN Not Received",--E84*--G84)) -> 0 | I84: 019/2026 | J84: 46044 | K84: 600 | L84: 5.4 | M84: =K84*L84 -> 3240 | N84: 0 | O84: 0 | P84: =M84+O84 -> 3240 | Q84: 25-26/046 | R84: 46044 | S84: Pharmax India Pvt Ltd | T84: FG01261 | U84: =IFERROR(VLOOKUP(T84,'item master'!B:C,2,0),"") -> ERGOMETRINE B/10AMP | V84: 600 | W84: 0 | X84: 5.4 | Y84: =V84*X84 -> 3240 | Z84: 0 | AA84: =Y84+Z84 -> 3240 | AB84: 0.3 | AC84: =Y84*AB84 -> 972 | AD84: =AC84 -> 972 | AE84: 46055 | AF84: 033DBFC260334522 | AG84: 600 | AH84: =AG84 -> 600 | AJ84: =V84-AG84 -> 0 | AK84: 26-27/106 | AL84: 46198 | AM84: AIZAH PHARMA FZCO | AN84: 5.4 | AO84: =AG84*AN84 -> 3240 | AS84: =AO84+AP84+AQ84+AR84 -> 3240 | AT84: NO BL RECEIVED | AV84: Final Invoice Received – Awaiting BL | AZ84: 0 | BA84: =AD84+AZ84 -> 972 | BB84: 0 | BC84: 0 | BD84: =IF(AK84>0,BA84+BB84+BC84,"0") -> 972 | BE84: =BA84-BD84 -> 0 | BF84: =BB84-BE84 -> 0 | BG84: =BE84-BF84 -> 0 | BH84: =AS84-BD84 -> 2268 | BI84: 0 | BO84: =BI84+BL84 -> 0 | BP84: =BH84-BO84 -> 2268 | BQ84: =IF(ROUND(BG84,2)>0,"Advance With Supplier",IF(ROUND(BP84,2)>0,"Payable Balance Supplier","Fully Paid")) -> Payable Balance Supplier | BS84: =IF(AX84<>"","Closed","Open") -> Open | BT84: =IF(BS84="Open",TODAY()-J84,"Closed") -> 219
A85: Aizah Pharma FZCO | B85: 1765.25 | C85: 46020 | D85: Lubumbashi | E85: 7500 | F85: Per Vial | G85: =IF(AG85="","GRN Not Received",AW85/AG85) -> 0 | H85: =IF(E85="PRF_Details_Not Availbale","PRF Qty Not Available",IF(G85="GRN Not Received","GRN Not Received",--E85*--G85)) -> 0 | I85: 019/2026 | J85: 46044 | K85: 7500 | L85: 1 | M85: =K85*L85 -> 7500 | N85: 0 | O85: 0 | P85: =M85+O85 -> 7500 | Q85: 25-26/046 | R85: 46044 | S85: Pharmax India Pvt Ltd | T85: FG06804 | U85: =IFERROR(VLOOKUP(T85,'item master'!B:C,2,0),"") -> TROBINIQUE-2G(SPECTINOMYCIN) B/1VIAL+3.2MLE.D | V85: 7500 | W85: 0 | X85: 1 | Y85: =V85*X85 -> 7500 | Z85: 0 | AA85: =Y85+Z85 -> 7500 | AB85: 0.3 | AC85: =Y85*AB85 -> 2250 | AD85: =AC85 -> 2250 | AE85: 46055 | AF85: 033DBFC260334522 | AG85: 7500 | AH85: =AG85 -> 7500 | AJ85: =V85-AG85 -> 0 | AK85: 25-26/556 | AL85: 46111 | AM85: AIZAH PHARMA FZCO | AN85: 1 | AO85: =AG85*AN85 -> 7500 | AS85: =AO85+AP85+AQ85+AR85 -> 7500 | AT85: 269667137 | AU85: 46155 | AV85: Transit | AZ85: 0 | BA85: =AD85+AZ85 -> 2250 | BB85: 0 | BC85: 0 | BD85: =IF(AK85>0,BA85+BB85+BC85,"0") -> 2250 | BE85: =BA85-BD85 -> 0 | BF85: =BB85-BE85 -> 0 | BG85: =BE85-BF85 -> 0 | BH85: =AS85-BD85 -> 5250 | BI85: 0 | BL85: 5250 | BM85: 033DBFC262122569 | BN85: 46237 | BO85: =BI85+BL85 -> 5250 | BP85: =BH85-BO85 -> 0 | BQ85: =IF(ROUND(BG85,2)>0,"Advance With Supplier",IF(ROUND(BP85,2)>0,"Payable Balance Supplier","Fully Paid")) -> Fully Paid | BS85: =IF(AX85<>"","Closed","Open") -> Open | BT85: =IF(BS85="Open",TODAY()-J85,"Closed") -> 219
A86: Aizah Pharma FZCO | B86: 1911.26 | C86: 46185 | D86: Kinshasa | E86: 10000 | F86: Per Vial | G86: =IF(AG86="","GRN Not Received",AW86/AG86) -> GRN Not Received | H86: =IF(E86="PRF_Details_Not Availbale","PRF Qty Not Available",IF(G86="GRN Not Received","GRN Not Received",--E86*--G86)) -> GRN Not Received | I86: 0141/2026 | J86: 46205 | K86: 10000 | L86: 0.83 | M86: =K86*L86 -> 8300 | N86: 0 | O86: 0 | P86: =M86+O86 -> 8300 | Q86: 26-27/019 | R86: 46205 | S86: Pharmax India Pvt Ltd | T86: FG07420 | U86: =IFERROR(VLOOKUP(T86,'item master'!B:C,2,0),"") -> SOLU-PREDNOL 125MG (MÉTHYLPREDNISOLONE) INJ.B/1 VIAL + SOLVENT 2ML | V86: 10000 | W86: 0 | X86: 0.83 | Y86: =V86*X86 -> 8300 | Z86: 0 | AA86: =Y86+Z86 -> 8300 | AB86: 0.3 | AC86: =Y86*AB86 -> 2490 | AD86: =AC86 -> 2490 | AE86: 46209 | AF86: 033DBFC261872417 | AH86: =AG86 -> 0 | AJ86: =V86-AG86 -> 10000 | AO86: =AG86*AN86 -> 0 | AS86: =AO86+AP86+AQ86+AR86 -> 0 | AV86: PO Issued – Awaiting BL | AZ86: 0 | BA86: =AD86+AZ86 -> 2490 | BB86: 0 | BC86: 0 | BD86: =IF(AK86>0,BA86+BB86+BC86,"0") -> 0 | BE86: =BA86-BD86 -> 2490 | BF86: =BB86-BE86 -> -2490 | BG86: =BE86-BF86 -> 4980 | BH86: =AS86-BD86 -> 0 | BI86: 0 | BO86: =BI86+BL86 -> 0 | BP86: =BH86-BO86 -> 0 | BQ86: =IF(ROUND(BG86,2)>0,"Advance With Supplier",IF(ROUND(BP86,2)>0,"Payable Balance Supplier","Fully Paid")) -> Advance With Supplier | BS86: =IF(AX86<>"","Closed","Open") -> Open | BT86: =IF(BS86="Open",TODAY()-J86,"Closed") -> 58
A87: Aizah Pharma FZCO | B87: 1911.26 | C87: 46185 | D87: Kinshasa | E87: 10000 | F87: Per Vial | G87: =IF(AG87="","GRN Not Received",AW87/AG87) -> GRN Not Received | H87: =IF(E87="PRF_Details_Not Availbale","PRF Qty Not Available",IF(G87="GRN Not Received","GRN Not Received",--E87*--G87)) -> GRN Not Received | I87: 0141/2026 | J87: 46205 | K87: 10000 | L87: 0.42 | M87: =K87*L87 -> 4200 | N87: 0 | O87: 0 | P87: =M87+O87 -> 4200 | Q87: 26-27/019 | R87: 46205 | S87: Pharmax India Pvt Ltd | T87: FG07421 | U87: =IFERROR(VLOOKUP(T87,'item master'!B:C,2,0),"") -> SOLU-PREDNOL 40MG (METHYLPREDNISOLONE) INJ.B/1 VIAL+SOLVENT 2ML | V87: 10000 | W87: 0 | X87: 0.42 | Y87: =V87*X87 -> 4200 | Z87: 0 | AA87: =Y87+Z87 -> 4200 | AB87: 0.3 | AC87: =Y87*AB87 -> 1260 | AD87: =AC87 -> 1260 | AE87: 46209 | AF87: 033DBFC261872417 | AH87: =AG87 -> 0 | AJ87: =V87-AG87 -> 10000 | AO87: =AG87*AN87 -> 0 | AS87: =AO87+AP87+AQ87+AR87 -> 0 | AV87: PO Issued – Awaiting BL | AZ87: 0 | BA87: =AD87+AZ87 -> 1260 | BB87: 0 | BC87: 0 | BD87: =IF(AK87>0,BA87+BB87+BC87,"0") -> 0 | BE87: =BA87-BD87 -> 1260 | BF87: =BB87-BE87 -> -1260 | BG87: =BE87-BF87 -> 2520 | BH87: =AS87-BD87 -> 0 | BI87: 0 | BO87: =BI87+BL87 -> 0 | BP87: =BH87-BO87 -> 0 | BQ87: =IF(ROUND(BG87,2)>0,"Advance With Supplier",IF(ROUND(BP87,2)>0,"Payable Balance Supplier","Fully Paid")) -> Advance With Supplier | BS87: =IF(AX87<>"","Closed","Open") -> Open | BT87: =IF(BS87="Open",TODAY()-J87,"Closed") -> 58
A88: Aizah Pharma FZCO | B88: 1911.26 | C88: 46185 | D88: Kinshasa | E88: 10000 | F88: Per Vial | G88: =IF(AG88="","GRN Not Received",AW88/AG88) -> GRN Not Received | H88: =IF(E88="PRF_Details_Not Availbale","PRF Qty Not Available",IF(G88="GRN Not Received","GRN Not Received",--E88*--G88)) -> GRN Not Received | I88: 0141/2026 | J88: 46205 | K88: 10000 | L88: 0.57 | M88: =K88*L88 -> 5700 | N88: 0 | O88: 0 | P88: =M88+O88 -> 5700 | Q88: 26-27/019 | R88: 46205 | S88: Pharmax India Pvt Ltd | T88: FG06812 | U88: =IFERROR(VLOOKUP(T88,'item master'!B:C,2,0),"") -> UNIKORT-80 (TRIAMCINOLONE) B/1 VIAL +SER | V88: 10000 | W88: 0 | X88: 0.57 | Y88: =V88*X88 -> 5700 | Z88: 0 | AA88: =Y88+Z88 -> 5700 | AB88: 0.3 | AC88: =Y88*AB88 -> 1710 | AD88: =AC88 -> 1710 | AE88: 46209 | AF88: 033DBFC261872417 | AH88: =AG88 -> 0 | AJ88: =V88-AG88 -> 10000 | AO88: =AG88*AN88 -> 0 | AS88: =AO88+AP88+AQ88+AR88 -> 0 | AV88: PO Issued – Awaiting BL | AZ88: 0 | BA88: =AD88+AZ88 -> 1710 | BB88: 0 | BC88: 0 | BD88: =IF(AK88>0,BA88+BB88+BC88,"0") -> 0 | BE88: =BA88-BD88 -> 1710 | BF88: =BB88-BE88 -> -1710 | BG88: =BE88-BF88 -> 3420 | BH88: =AS88-BD88 -> 0 | BI88: 0 | BO88: =BI88+BL88 -> 0 | BP88: =BH88-BO88 -> 0 | BQ88: =IF(ROUND(BG88,2)>0,"Advance With Supplier",IF(ROUND(BP88,2)>0,"Payable Balance Supplier","Fully Paid")) -> Advance With Supplier | BS88: =IF(AX88<>"","Closed","Open") -> Open | BT88: =IF(BS88="Open",TODAY()-J88,"Closed") -> 58
A89: Aizah Pharma FZCO | B89: 1877.26 | C89: 46157 | D89: Kinshasa | E89: 120000 | F89: Per Pack 100 Amp | G89: =IF(AG89="","GRN Not Received",AW89/AG89) -> 0 | H89: =IF(E89="PRF_Details_Not Availbale","PRF Qty Not Available",IF(G89="GRN Not Received","GRN Not Received",--E89*--G89)) -> 0 | I89: 0104/2026 | J89: 46174 | K89: 12000 | L89: 3.3 | M89: =K89*L89 -> 39600 | N89: 0 | O89: 0 | P89: =M89+O89 -> 39600 | Q89: 26-27/006 | R89: 46157 | S89: Pharmax India Pvt Ltd | T89: FG04064 | U89: =IFERROR(VLOOKUP(T89,'item master'!B:C,2,0),"") -> PAPAVERINE 40MG/ML INJ. 10AMP | V89: 12000 | X89: 3.3 | Y89: =V89*X89 -> 39600 | Z89: 0 | AA89: =Y89+Z89 -> 39600 | AB89: 0.3 | AC89: =Y89*AB89 -> 11880 | AD89: =AC89 -> 11880 | AE89: 46177 | AF89: 033DBFC261542771 | AG89: 1200 | AH89: =AG89 -> 1200 | AJ89: =V89-AG89 -> 10800 | AK89: 26-27/156 | AL89: 46233 | AM89: AIZAH PHARMA FZCO | AN89: 3.3 | AO89: =AG89*AN89 -> 3960 | AS89: =AO89+AP89+AQ89+AR89 -> 3960 | AT89: 071-6185 5312 | AU89: 46245 | AV89: PO Issued – Awaiting BL | AZ89: 0 | BA89: =AD89+AZ89 -> 11880 | BB89: 0 | BC89: 0 | BD89: =IF(AK89>0,BA89+BB89+BC89,"0") -> 11880 | BE89: =BA89-BD89 -> 0 | BF89: =BB89-BE89 -> 0 | BG89: =BE89-BF89 -> 0 | BH89: =AS89-BD89 -> -7920 | BI89: 0 | BO89: =BI89+BL89 -> 0 | BP89: =BH89-BO89 -> -7920 | BQ89: =IF(ROUND(BG89,2)>0,"Advance With Supplier",IF(ROUND(BP89,2)>0,"Payable Balance Supplier","Fully Paid")) -> Fully Paid | BS89: =IF(AX89<>"","Closed","Open") -> Open | BT89: =IF(BS89="Open",TODAY()-J89,"Closed") -> 89
A90: Aizah Pharma FZCO | B90: 1877.26 | C90: 46157 | D90: Kinshasa | E90: 200000 | F90: Per Pack 100 Amp | G90: =IF(AG90="","GRN Not Received",AW90/AG90) -> GRN Not Received | H90: =IF(E90="PRF_Details_Not Availbale","PRF Qty Not Available",IF(G90="GRN Not Received","GRN Not Received",--E90*--G90)) -> GRN Not Received | I90: 0104/2026 | J90: 46174 | K90: 20000 | L90: 2.7 | M90: =K90*L90 -> 54000 | N90: 0 | O90: 0 | P90: =M90+O90 -> 54000 | Q90: 26-27/006 | R90: 46157 | S90: Pharmax India Pvt Ltd | T90: FG04769 | U90: =IFERROR(VLOOKUP(T90,'item master'!B:C,2,0),"") -> OXYTOCINE 10UI/1ML INJ. B/10AMP | V90: 20000 | X90: 2.7 | Y90: =V90*X90 -> 54000 | Z90: 0 | AA90: =Y90+Z90 -> 54000 | AB90: 0.3 | AC90: =Y90*AB90 -> 16200 | AD90: =AC90 -> 16200 | AE90: 46177 | AF90: 033DBFC261542771 | AH90: =AG90 -> 0 | AJ90: =V90-AG90 -> 20000 | AO90: =AG90*AN90 -> 0 | AS90: =AO90+AP90+AQ90+AR90 -> 0 | AV90: PO Issued – Awaiting BL | AZ90: 0 | BA90: =AD90+AZ90 -> 16200 | BB90: 0 | BC90: 0 | BD90: =IF(AK90>0,BA90+BB90+BC90,"0") -> 0 | BE90: =BA90-BD90 -> 16200 | BF90: =BB90-BE90 -> -16200 | BG90: =BE90-BF90 -> 32400 | BH90: =AS90-BD90 -> 0 | BI90: 0 | BO90: =BI90+BL90 -> 0 | BP90: =BH90-BO90 -> 0 | BQ90: =IF(ROUND(BG90,2)>0,"Advance With Supplier",IF(ROUND(BP90,2)>0,"Payable Balance Supplier","Fully Paid")) -> Advance With Supplier | BS90: =IF(AX90<>"","Closed","Open") -> Open | BT90: =IF(BS90="Open",TODAY()-J90,"Closed") -> 89
A91: Aizah Pharma FZCO | B91: 1877.26 | C91: 46157 | D91: Kinshasa | E91: 1000 | F91: Pack of 10 Amps | G91: =IF(AG91="","GRN Not Received",AW91/AG91) -> GRN Not Received | H91: =IF(E91="PRF_Details_Not Availbale","PRF Qty Not Available",IF(G91="GRN Not Received","GRN Not Received",--E91*--G91)) -> GRN Not Received | I91: 0104/2026 | J91: 46174 | K91: 4000 | L91: 0.85 | M91: =K91*L91 -> 3400 | N91: 0 | O91: 0 | P91: =M91+O91 -> 3400 | Q91: 26-27/006 | R91: 46157 | S91: Pharmax India Pvt Ltd | T91: FG00537 | U91: =IFERROR(VLOOKUP(T91,'item master'!B:C,2,0),"") -> CAFEINE B/10AMP | V91: 4000 | X91: 0.85 | Y91: =V91*X91 -> 3400 | Z91: 0 | AA91: =Y91+Z91 -> 3400 | AB91: 0.3 | AC91: =Y91*AB91 -> 1020 | AD91: =AC91 -> 1020 | AE91: 46177 | AF91: 033DBFC261542771 | AH91: =AG91 -> 0 | AJ91: =V91-AG91 -> 4000 | AO91: =AG91*AN91 -> 0 | AS91: =AO91+AP91+AQ91+AR91 -> 0 | AV91: PO Issued – Awaiting BL | AZ91: 0 | BA91: =AD91+AZ91 -> 1020 | BB91: 0 | BC91: 0 | BD91: =IF(AK91>0,BA91+BB91+BC91,"0") -> 0 | BE91: =BA91-BD91 -> 1020 | BF91: =BB91-BE91 -> -1020 | BG91: =BE91-BF91 -> 2040 | BH91: =AS91-BD91 -> 0 | BI91: 0 | BO91: =BI91+BL91 -> 0 | BP91: =BH91-BO91 -> 0 | BQ91: =IF(ROUND(BG91,2)>0,"Advance With Supplier",IF(ROUND(BP91,2)>0,"Payable Balance Supplier","Fully Paid")) -> Advance With Supplier | BS91: =IF(AX91<>"","Closed","Open") -> Open | BT91: =IF(BS91="Open",TODAY()-J91,"Closed") -> 89
A92: Aizah Pharma FZCO | B92: 1877.26 | C92: 46157 | D92: Kinshasa | E92: 10000 | F92: Per Vial | G92: =IF(AG92="","GRN Not Received",AW92/AG92) -> GRN Not Received | H92: =IF(E92="PRF_Details_Not Availbale","PRF Qty Not Available",IF(G92="GRN Not Received","GRN Not Received",--E92*--G92)) -> GRN Not Received | I92: 0104/2026 | J92: 46174 | K92: 10000 | L92: 1.1 | M92: =K92*L92 -> 11000 | N92: 0 | O92: 0 | P92: =M92+O92 -> 11000 | Q92: 26-27/006 | R92: 46157 | S92: Pharmax India Pvt Ltd | T92: FG06678 | U92: =IFERROR(VLOOKUP(T92,'item master'!B:C,2,0),"") -> HEPAQUE (HEPARIN) 25000UI/5ML INJ. B/1 VIAL | V92: 10000 | X92: 1.1 | Y92: =V92*X92 -> 11000 | Z92: 0 | AA92: =Y92+Z92 -> 11000 | AB92: 0.3 | AC92: =Y92*AB92 -> 3300 | AD92: =AC92 -> 3300 | AE92: 46177 | AF92: 033DBFC261542771 | AH92: =AG92 -> 0 | AJ92: =V92-AG92 -> 10000 | AO92: =AG92*AN92 -> 0 | AS92: =AO92+AP92+AQ92+AR92 -> 0 | AV92: PO Issued – Awaiting BL | AZ92: 0 | BA92: =AD92+AZ92 -> 3300 | BB92: 0 | BC92: 0 | BD92: =IF(AK92>0,BA92+BB92+BC92,"0") -> 0 | BE92: =BA92-BD92 -> 3300 | BF92: =BB92-BE92 -> -3300 | BG92: =BE92-BF92 -> 6600 | BH92: =AS92-BD92 -> 0 | BI92: 0 | BO92: =BI92+BL92 -> 0 | BP92: =BH92-BO92 -> 0 | BQ92: =IF(ROUND(BG92,2)>0,"Advance With Supplier",IF(ROUND(BP92,2)>0,"Payable Balance Supplier","Fully Paid")) -> Advance With Supplier | BS92: =IF(AX92<>"","Closed","Open") -> Open | BT92: =IF(BS92="Open",TODAY()-J92,"Closed") -> 89
A93: Aizah Pharma FZCO | B93: 1877.26 | C93: 46157 | D93: Kinshasa | E93: 10000 | F93: 10 ML | G93: =IF(AG93="","GRN Not Received",AW93/AG93) -> GRN Not Received | H93: =IF(E93="PRF_Details_Not Availbale","PRF Qty Not Available",IF(G93="GRN Not Received","GRN Not Received",--E93*--G93)) -> GRN Not Received | I93: 0104/2026 | J93: 46174 | K93: 10000 | L93: 0.35 | M93: =K93*L93 -> 3500 | N93: 0 | O93: 0 | P93: =M93+O93 -> 3500 | Q93: 26-27/006 | R93: 46157 | S93: Pharmax India Pvt Ltd | T93: FG06802 | U93: =IFERROR(VLOOKUP(T93,'item master'!B:C,2,0),"") -> MOX VISION (MOXYFLOXACIN) COLLYRE 10ML | V93: 10000 | X93: 0.35 | Y93: =V93*X93 -> 3500 | Z93: 0 | AA93: =Y93+Z93 -> 3500 | AB93: 0.3 | AC93: =Y93*AB93 -> 1050 | AD93: =AC93 -> 1050 | AE93: 46177 | AF93: 033DBFC261542771 | AH93: =AG93 -> 0 | AJ93: =V93-AG93 -> 10000 | AO93: =AG93*AN93 -> 0 | AS93: =AO93+AP93+AQ93+AR93 -> 0 | AV93: PO Issued – Awaiting BL | AZ93: 0 | BA93: =AD93+AZ93 -> 1050 | BB93: 0 | BC93: 0 | BD93: =IF(AK93>0,BA93+BB93+BC93,"0") -> 0 | BE93: =BA93-BD93 -> 1050 | BF93: =BB93-BE93 -> -1050 | BG93: =BE93-BF93 -> 2100 | BH93: =AS93-BD93 -> 0 | BI93: 0 | BO93: =BI93+BL93 -> 0 | BP93: =BH93-BO93 -> 0 | BQ93: =IF(ROUND(BG93,2)>0,"Advance With Supplier",IF(ROUND(BP93,2)>0,"Payable Balance Supplier","Fully Paid")) -> Advance With Supplier | BS93: =IF(AX93<>"","Closed","Open") -> Open | BT93: =IF(BS93="Open",TODAY()-J93,"Closed") -> 89
A94: Aizah Pharma FZCO | B94: 1877.26 | C94: 46157 | D94: Kinshasa | E94: 10000 | F94: Per Vial | G94: =IF(AG94="","GRN Not Received",AW94/AG94) -> GRN Not Received | H94: =IF(E94="PRF_Details_Not Availbale","PRF Qty Not Available",IF(G94="GRN Not Received","GRN Not Received",--E94*--G94)) -> GRN Not Received | I94: 0104/2026 | J94: 46174 | K94: 10000 | L94: 1.05 | M94: =K94*L94 -> 10500 | N94: 0 | O94: 0 | P94: =M94+O94 -> 10500 | Q94: 26-27/006 | R94: 46157 | S94: Pharmax India Pvt Ltd | T94: FG06804 | U94: =IFERROR(VLOOKUP(T94,'item master'!B:C,2,0),"") -> TROBINIQUE-2G(SPECTINOMYCIN) B/1VIAL+3.2MLE.D | V94: 10000 | X94: 1.05 | Y94: =V94*X94 -> 10500 | Z94: 0 | AA94: =Y94+Z94 -> 10500 | AB94: 0.3 | AC94: =Y94*AB94 -> 3150 | AD94: =AC94 -> 3150 | AE94: 46177 | AF94: 033DBFC261542771 | AH94: =AG94 -> 0 | AJ94: =V94-AG94 -> 10000 | AO94: =AG94*AN94 -> 0 | AS94: =AO94+AP94+AQ94+AR94 -> 0 | AV94: PO Issued – Awaiting BL | AZ94: 0 | BA94: =AD94+AZ94 -> 3150 | BB94: 0 | BC94: 0 | BD94: =IF(AK94>0,BA94+BB94+BC94,"0") -> 0 | BE94: =BA94-BD94 -> 3150 | BF94: =BB94-BE94 -> -3150 | BG94: =BE94-BF94 -> 6300 | BH94: =AS94-BD94 -> 0 | BI94: 0 | BO94: =BI94+BL94 -> 0 | BP94: =BH94-BO94 -> 0 | BQ94: =IF(ROUND(BG94,2)>0,"Advance With Supplier",IF(ROUND(BP94,2)>0,"Payable Balance Supplier","Fully Paid")) -> Advance With Supplier | BS94: =IF(AX94<>"","Closed","Open") -> Open | BT94: =IF(BS94="Open",TODAY()-J94,"Closed") -> 89
A95: Aizah Pharma FZCO | B95: 1877.26 | C95: 46157 | D95: Kinshasa | E95: 5000 | F95: 5 ml | G95: =IF(AG95="","GRN Not Received",AW95/AG95) -> GRN Not Received | H95: =IF(E95="PRF_Details_Not Availbale","PRF Qty Not Available",IF(G95="GRN Not Received","GRN Not Received",--E95*--G95)) -> GRN Not Received | I95: 0104/2026 | J95: 46174 | K95: 5000 | L95: 2.3 | M95: =K95*L95 -> 11500 | N95: 0 | O95: 0 | P95: =M95+O95 -> 11500 | Q95: 26-27/006 | R95: 46157 | S95: Pharmax India Pvt Ltd | T95: FG06806 | U95: =IFERROR(VLOOKUP(T95,'item master'!B:C,2,0),"") -> OCUTIM PLUS VISION (TIMO+PILO) COLLYRE 5ML | V95: 5000 | X95: 2.3 | Y95: =V95*X95 -> 11500 | Z95: 0 | AA95: =Y95+Z95 -> 11500 | AB95: 0.3 | AC95: =Y95*AB95 -> 3450 | AD95: =AC95 -> 3450 | AE95: 46177 | AF95: 033DBFC261542771 | AH95: =AG95 -> 0 | AJ95: =V95-AG95 -> 5000 | AO95: =AG95*AN95 -> 0 | AS95: =AO95+AP95+AQ95+AR95 -> 0 | AV95: PO Issued – Awaiting BL | AZ95: 0 | BA95: =AD95+AZ95 -> 3450 | BB95: 0 | BC95: 0 | BD95: =IF(AK95>0,BA95+BB95+BC95,"0") -> 0 | BE95: =BA95-BD95 -> 3450 | BF95: =BB95-BE95 -> -3450 | BG95: =BE95-BF95 -> 6900 | BH95: =AS95-BD95 -> 0 | BI95: 0 | BO95: =BI95+BL95 -> 0 | BP95: =BH95-BO95 -> 0 | BQ95: =IF(ROUND(BG95,2)>0,"Advance With Supplier",IF(ROUND(BP95,2)>0,"Payable Balance Supplier","Fully Paid")) -> Advance With Supplier | BS95: =IF(AX95<>"","Closed","Open") -> Open | BT95: =IF(BS95="Open",TODAY()-J95,"Closed") -> 89
A96: Aizah Pharma FZCO | B96: 1877.26 | C96: 46157 | D96: Kinshasa | E96: 10000 | F96: 5 ml | G96: =IF(AG96="","GRN Not Received",AW96/AG96) -> GRN Not Received | H96: =IF(E96="PRF_Details_Not Availbale","PRF Qty Not Available",IF(G96="GRN Not Received","GRN Not Received",--E96*--G96)) -> GRN Not Received | I96: 0104/2026 | J96: 46174 | K96: 10000 | L96: 0.32 | M96: =K96*L96 -> 3200 | N96: 0 | O96: 0 | P96: =M96+O96 -> 3200 | Q96: 26-27/006 | R96: 46157 | S96: Pharmax India Pvt Ltd | T96: FG06810 | U96: =IFERROR(VLOOKUP(T96,'item master'!B:C,2,0),"") -> GENTAC PLUS-VISION (GEN+DEX+TET) COLLYRE 5ML | V96: 10000 | X96: 0.32 | Y96: =V96*X96 -> 3200 | Z96: 0 | AA96: =Y96+Z96 -> 3200 | AB96: 0.3 | AC96: =Y96*AB96 -> 960 | AD96: =AC96 -> 960 | AE96: 46177 | AF96: 033DBFC261542771 | AH96: =AG96 -> 0 | AJ96: =V96-AG96 -> 10000 | AO96: =AG96*AN96 -> 0 | AS96: =AO96+AP96+AQ96+AR96 -> 0 | AV96: PO Issued – Awaiting BL | AZ96: 0 | BA96: =AD96+AZ96 -> 960 | BB96: 0 | BC96: 0 | BD96: =IF(AK96>0,BA96+BB96+BC96,"0") -> 0 | BE96: =BA96-BD96 -> 960 | BF96: =BB96-BE96 -> -960 | BG96: =BE96-BF96 -> 1920 | BH96: =AS96-BD96 -> 0 | BI96: 0 | BO96: =BI96+BL96 -> 0 | BP96: =BH96-BO96 -> 0 | BQ96: =IF(ROUND(BG96,2)>0,"Advance With Supplier",IF(ROUND(BP96,2)>0,"Payable Balance Supplier","Fully Paid")) -> Advance With Supplier | BS96: =IF(AX96<>"","Closed","Open") -> Open | BT96: =IF(BS96="Open",TODAY()-J96,"Closed") -> 89
A97: Aizah Pharma FZCO | B97: 1877.26 | C97: 46157 | D97: Kinshasa | E97: 10000 | F97: Per Vial | G97: =IF(AG97="","GRN Not Received",AW97/AG97) -> GRN Not Received | H97: =IF(E97="PRF_Details_Not Availbale","PRF Qty Not Available",IF(G97="GRN Not Received","GRN Not Received",--E97*--G97)) -> GRN Not Received | I97: 0104/2026 | J97: 46174 | K97: 10000 | L97: 0.35 | M97: =K97*L97 -> 3500 | N97: 0 | O97: 0 | P97: =M97+O97 -> 3500 | Q97: 26-27/006 | R97: 46157 | S97: Pharmax India Pvt Ltd | T97: FG06811 | U97: =IFERROR(VLOOKUP(T97,'item master'!B:C,2,0),"") -> UNIKORT-40 (TRIAMCINOLONE) B/1 VIAL+SER | V97: 10000 | X97: 0.35 | Y97: =V97*X97 -> 3500 | Z97: 0 | AA97: =Y97+Z97 -> 3500 | AB97: 0.3 | AC97: =Y97*AB97 -> 1050 | AD97: =AC97 -> 1050 | AE97: 46177 | AF97: 033DBFC261542771 | AH97: =AG97 -> 0 | AJ97: =V97-AG97 -> 10000 | AO97: =AG97*AN97 -> 0 | AS97: =AO97+AP97+AQ97+AR97 -> 0 | AV97: PO Issued – Awaiting BL | AZ97: 0 | BA97: =AD97+AZ97 -> 1050 | BB97: 0 | BC97: 0 | BD97: =IF(AK97>0,BA97+BB97+BC97,"0") -> 0 | BE97: =BA97-BD97 -> 1050 | BF97: =BB97-BE97 -> -1050 | BG97: =BE97-BF97 -> 2100 | BH97: =AS97-BD97 -> 0 | BI97: 0 | BO97: =BI97+BL97 -> 0 | BP97: =BH97-BO97 -> 0 | BQ97: =IF(ROUND(BG97,2)>0,"Advance With Supplier",IF(ROUND(BP97,2)>0,"Payable Balance Supplier","Fully Paid")) -> Advance With Supplier | BS97: =IF(AX97<>"","Closed","Open") -> Open | BT97: =IF(BS97="Open",TODAY()-J97,"Closed") -> 89
A98: Aizah Pharma FZCO | B98: 1877.26 | C98: 46157 | D98: Kinshasa | E98: 10000 | F98: Per Vial | G98: =IF(AG98="","GRN Not Received",AW98/AG98) -> GRN Not Received | H98: =IF(E98="PRF_Details_Not Availbale","PRF Qty Not Available",IF(G98="GRN Not Received","GRN Not Received",--E98*--G98)) -> GRN Not Received | I98: 0104/2026 | J98: 46174 | K98: 10000 | L98: 0.57 | M98: =K98*L98 -> 5700 | N98: 0 | O98: 0 | P98: =M98+O98 -> 5700 | Q98: 26-27/006 | R98: 46157 | S98: Pharmax India Pvt Ltd | T98: FG06812 | U98: =IFERROR(VLOOKUP(T98,'item master'!B:C,2,0),"") -> UNIKORT-80 (TRIAMCINOLONE) B/1 VIAL +SER | V98: 10000 | X98: 0.57 | Y98: =V98*X98 -> 5700 | Z98: 0 | AA98: =Y98+Z98 -> 5700 | AB98: 0.3 | AC98: =Y98*AB98 -> 1710 | AD98: =AC98 -> 1710 | AE98: 46177 | AF98: 033DBFC261542771 | AH98: =AG98 -> 0 | AJ98: =V98-AG98 -> 10000 | AO98: =AG98*AN98 -> 0 | AS98: =AO98+AP98+AQ98+AR98 -> 0 | AV98: PO Issued – Awaiting BL | AZ98: 0 | BA98: =AD98+AZ98 -> 1710 | BB98: 0 | BC98: 0 | BD98: =IF(AK98>0,BA98+BB98+BC98,"0") -> 0 | BE98: =BA98-BD98 -> 1710 | BF98: =BB98-BE98 -> -1710 | BG98: =BE98-BF98 -> 3420 | BH98: =AS98-BD98 -> 0 | BI98: 0 | BO98: =BI98+BL98 -> 0 | BP98: =BH98-BO98 -> 0 | BQ98: =IF(ROUND(BG98,2)>0,"Advance With Supplier",IF(ROUND(BP98,2)>0,"Payable Balance Supplier","Fully Paid")) -> Advance With Supplier | BS98: =IF(AX98<>"","Closed","Open") -> Open | BT98: =IF(BS98="Open",TODAY()-J98,"Closed") -> 89
A99: Aizah Pharma FZCO | B99: 1877.26 | C99: 46157 | D99: Kinshasa | E99: 5000 | F99: Pack of 5 Amps | G99: =IF(AG99="","GRN Not Received",AW99/AG99) -> GRN Not Received | H99: =IF(E99="PRF_Details_Not Availbale","PRF Qty Not Available",IF(G99="GRN Not Received","GRN Not Received",--E99*--G99)) -> GRN Not Received | I99: 0104/2026 | J99: 46174 | K99: 5000 | L99: 1.75 | M99: =K99*L99 -> 8750 | N99: 0 | O99: 0 | P99: =M99+O99 -> 8750 | Q99: 26-27/006 | R99: 46157 | S99: Pharmax India Pvt Ltd | T99: FG07410 | U99: =IFERROR(VLOOKUP(T99,'item master'!B:C,2,0),"") -> ATARIUM 50MG/5ML (ATACURIUM ) INJ. B/5 AMP. | V99: 5000 | X99: 1.75 | Y99: =V99*X99 -> 8750 | Z99: 0 | AA99: =Y99+Z99 -> 8750 | AB99: 0.3 | AC99: =Y99*AB99 -> 2625 | AD99: =AC99 -> 2625 | AE99: 46177 | AF99: 033DBFC261542771 | AH99: =AG99 -> 0 | AJ99: =V99-AG99 -> 5000 | AO99: =AG99*AN99 -> 0 | AS99: =AO99+AP99+AQ99+AR99 -> 0 | AV99: PO Issued – Awaiting BL | AZ99: 0 | BA99: =AD99+AZ99 -> 2625 | BB99: 0 | BC99: 0 | BD99: =IF(AK99>0,BA99+BB99+BC99,"0") -> 0 | BE99: =BA99-BD99 -> 2625 | BF99: =BB99-BE99 -> -2625 | BG99: =BE99-BF99 -> 5250 | BH99: =AS99-BD99 -> 0 | BI99: 0 | BO99: =BI99+BL99 -> 0 | BP99: =BH99-BO99 -> 0 | BQ99: =IF(ROUND(BG99,2)>0,"Advance With Supplier",IF(ROUND(BP99,2)>0,"Payable Balance Supplier","Fully Paid")) -> Advance With Supplier | BS99: =IF(AX99<>"","Closed","Open") -> Open | BT99: =IF(BS99="Open",TODAY()-J99,"Closed") -> 89
A100: Aizah Pharma FZCO | B100: 1920.26 | C100: 46185 | D100: Kinshasa | E100: 50000 | F100: 10X10 Tabs | G100: =IF(AG100="","GRN Not Received",AW100/AG100) -> GRN Not Received | H100: =IF(E100="PRF_Details_Not Availbale","PRF Qty Not Available",IF(G100="GRN Not Received","GRN Not Received",--E100*--G100)) -> GRN Not Received | I100: 0139/2026 | J100: 46200 | K100: 50000 | L100: 0.112 | M100: =K100*L100 -> 5600 | N100: 0 | O100: 0 | P100: =M100+O100 -> 5600 | Q100: AM003/2026-27 | R100: 46199 | S100: Ambadnya Life Science Llc | T100: FG04312 | U100: =IFERROR(VLOOKUP(T100,'item master'!B:C,2,0),"") -> ACIDE FOLIC 10X10CES | V100: 50000 | X100: 0.112 | Y100: =V100*X100 -> 5600 | Z100: 0 | AA100: =Y100+Z100 -> 5600 | AB100: 0.3 | AC100: =Y100*AB100 -> 1680 | AD100: =AC100 -> 1680 | AE100: 46216 | AF100: 033DBFC261920137 | AH100: =AG100 -> 0 | AJ100: =V100-AG100 -> 50000 | AO100: =AG100*AN100 -> 0 | AS100: =AO100+AP100+AQ100+AR100 -> 0 | AV100: PO Issued – Awaiting BL | AZ100: 0 | BA100: =AD100+AZ100 -> 1680 | BB100: 0 | BC100: 0 | BD100: =IF(AK100>0,BA100+BB100+BC100,"0") -> 0 | BE100: =BA100-BD100 -> 1680 | BF100: =BB100-BE100 -> -1680 | BG100: =BE100-BF100 -> 3360 | BH100: =AS100-BD100 -> 0 | BI100: 0 | BO100: =BI100+BL100 -> 0 | BP100: =BH100-BO100 -> 0 | BQ100: =IF(ROUND(BG100,2)>0,"Advance With Supplier",IF(ROUND(BP100,2)>0,"Payable Balance Supplier","Fully Paid")) -> Advance With Supplier | BS100: =IF(AX100<>"","Closed","Open") -> Open | BT100: =IF(BS100="Open",TODAY()-J100,"Closed") -> 63
...

Sheet Sheet1
A1: PRF_No | B1: PO_No | C1: PO_Date | D1: PO_Total_Amount | E1: Advance_Amount
A2: 1761.25 | B2: 018/2026 | C2: 46044 | D2: 35200 | E2: 10560 | N2: Values
A3: 1761.25 | B3: 018/2026 | C3: 46044 | D3: 21600 | E3: 6480 | L3: PO_Date | M3: PO_No | N3: Sum of PO_Total_Amount | O3: Sum of Advance_Amount
A4: 1761.25 | B4: 018/2026 | C4: 46044 | D4: 10000 | E4: 3000 | L4: 46044 | M4: 018/2026 | N4: 77800 | O4: 23340
A5: 1772.26 | B5: 018/2026 | C5: 46044 | D5: 11000 | E5: 3300 | M5: 019/2026 | N5: 3240 | O5: 972
A6: 1765.25 | B6: 019/2026 | C6: 46044 | D6: 3240 | E6: 972 | L6: 46174 | M6: 0104/2026 | N6: 154650 | O6: 46395
A7: 1911.26 | B7: 0141/2026 | C7: 46205 | D7: 8300 | E7: 2490 | L7: 46205 | M7: 0141/2026 | N7: 18200 | O7: 5460
A8: 1911.26 | B8: 0141/2026 | C8: 46205 | D8: 4200 | E8: 1260 | L8: Grand Total | N8: 253890 | O8: 76167
A9: 1911.26 | B9: 0141/2026 | C9: 46205 | D9: 5700 | E9: 1710
A10: 1877.26 | B10: 0104/2026 | C10: 46174 | D10: 39600 | E10: 11880
A11: 1877.26 | B11: 0104/2026 | C11: 46174 | D11: 54000 | E11: 16200
A12: 1877.26 | B12: 0104/2026 | C12: 46174 | D12: 3400 | E12: 1020
A13: 1877.26 | B13: 0104/2026 | C13: 46174 | D13: 11000 | E13: 3300
A14: 1877.26 | B14: 0104/2026 | C14: 46174 | D14: 3500 | E14: 1050
A15: 1877.26 | B15: 0104/2026 | C15: 46174 | D15: 10500 | E15: 3150
A16: 1877.26 | B16: 0104/2026 | C16: 46174 | D16: 11500 | E16: 3450
A17: 1877.26 | B17: 0104/2026 | C17: 46174 | D17: 3200 | E17: 960
A18: 1877.26 | B18: 0104/2026 | C18: 46174 | D18: 3500 | E18: 1050 | O18: {=_xlfn.UNIQUE(Data!AV:AV)} -> Shipment_Status
A19: 1877.26 | B19: 0104/2026 | C19: 46174 | D19: 5700 | E19: 1710 | O19: PO Issued – Awaiting BL
A20: 1877.26 | B20: 0104/2026 | C20: 46174 | D20: 8750 | E20: 2625 | O20: Goods Received at Warehouse
O21: Final Invoice Received – Awaiting BL
O22: Transit
O23: 0

Sheet Information
B1: Company | C1: Purchasing Company
B2: PRF_No | C2: PRF get from kinshasa team,but issues old p.o prf details not available
B3: PRF_Date | C3: PRF date from prf,but issues old p.o prf date not available
B4: PRF_Location | C4: PRF location from prf,but issues old p.o prf location not available
B5: PRF_Qty | C5: PRF qty from prf,but issues old p.o prf qty not available
B6: Pack_Size | C6: some items pack size not available but later this details updated
B7: Conversion_Unit | C7: some item purchase qty and selling qty diifrence,that’s why grn created time selling qty will get,so this coloum formula is grn qty /invoice qty
B8: PRF_Qty_Converted | C8: prft qty*Conversion_Unit
B9: PO_No | C9: p.o issued to supplier
B10: PO_Date | C10: p.o date
B11: PO_Qty | C11: p.o qty
B12: PO_Rate | C12: p.o rate
... B71: PO_Age_Days | C71: today-PO_Date

Sheet Units
A1: Pack Size / Presentation
A2: 10 ml x 20 Amps
A3: 125 gm
A4: 75 gm
A5: 100 gm
A6: Per Pack 100 Amp
A7: Per Vial
A8: Pack of 6 Amps
A9: Pack of 10 Amps
A10: Pack of 100 Amps
A11: Pack of 5 Amps
A12: 5 Ml
... A15: Pack of 12 Amp

Sheet PRF Location
A1: Kinshasa
A2: Goma
A3: Lubumbashi

Sheet Company
A1: Company
A2: Aizah Pharma FZCO
A3: Unique Ventures

Sheet item master
A1: Sl No | B1: ITEM_CODE | C1: Kinshasa Name | D1: Supplier_Name | E1: Supplier Country | F1: Brand Name | G1: Status | H1: Dosage Form | I1: Strength / Composition | J1: Pack Size / Presentation | K1: Route of Admin | L1: Indications (Summary) | M1: Posology / Dosage
A2: 1 | B2: =_xlfn.XLOOKUP(C2,[1]IVW8362itmlist!$C:$C,[1]IVW8362itmlist!$B:$B) -> FG02165 | C2: NEUROQUE 500MCG/ML (MECOBALAMIN) INJ. B/5 AMP | F2: Neuroque | G2: Active | H2: Injection | I2: Methylcobalamin 500 mcg/mL | J2: Box of 5 ampoules of 1 mL | K2: IM / IV | L2: Peripheral & diabetic neuropathies, neurotransmitter synthesis, megaloblastic anemia | M2: 1 ampoule (500 mcg) daily, 3 times per week
A3: 2 | B3: =_xlfn.XLOOKUP(C3,[1]IVW8362itmlist!$C:$C,[1]IVW8362itmlist!$B:$B) -> FG02596 | C3: PREGATAS-ME (PREGABALIN+MECOBALAMIN) B/30CAP | F3: Pregatas | G3: Active | H3: Capsule | I3: Pregabalin 75 mg + Methylcobalamin 750 mcg | J3: Box of 30 capsules | K3: Oral | L3: Nerve pain (diabetic neuropathy, shingles, spinal cord injury, fibromyalgia) | M3: As directed by physician
A4: 3 | B4: =_xlfn.XLOOKUP(C4,[1]IVW8362itmlist!$C:$C,[1]IVW8362itmlist!$B:$B) -> FG02595 | C4: PREGATAS-75 (PREGABALIN) B/30 CAPSULE | F4: Pregatas | G4: Active | H4: Capsule | I4: Pregabalin 75 mg | J4: Box of 30 capsules | K4: Oral | L4: Nerve pain (diabetic neuropathy, shingles, spinal cord injury, fibromyalgia) | M4: As directed by physician
A5: 4 | B5: =_xlfn.XLOOKUP(C5,[1]IVW8362itmlist!$C:$C,[1]IVW8362itmlist!$B:$B) -> FG04282 | C5: CYPROPLEX (CYPROHEPTADINE) SIROP 200ML | F5: Cyproplex | G5: Active | H5: Oral Suspension | I5: Cyproheptadine 2 mg / 5 mL | J5: Box of 200 mL | K5: Oral | L5: Allergy symptoms (watery eyes, runny nose, hives, itching) | M5: As directed by physician
A6: 5 | B6: =_xlfn.XLOOKUP(C6,[1]IVW8362itmlist!$C:$C,[1]IVW8362itmlist!$B:$B) -> FG04621 | C6: CYPROPLEX-4 (CYPROHEPTADINE) B/ 10 X 10 CES | F6: Cyproplex | G6: Active | H6: Tablet | I6: Cyproheptadine 4 mg | J6: Box of 2×10 & 10×10 tablets | K6: Oral | L6: Allergy symptoms & appetite stimulation | M6: As directed by physician
A7: 6 | B7: =_xlfn.XLOOKUP(C7,[1]IVW8362itmlist!$C:$C,[1]IVW8362itmlist!$B:$B) -> FG01016 | C7: DESLORA 2.5MG/5ML (DESLORATADINE) SIROP 60ML | F7: Deslora | G7: Active | H7: Syrup | I7: Desloratadine 2.5 mg / 5 mL | J7: Box of 60 mL (Pineapple flavour) | K7: Oral | L7: Allergies (sneezing, watery eyes, itching), chronic skin hives | M7: <1yr: 2mL; 1-3yr: 2.5mL; 3-6yr: 5mL once daily
A8: 7 | B8: =_xlfn.XLOOKUP(C8,[1]IVW8362itmlist!$C:$C,[1]IVW8362itmlist!$B:$B) -> FG01017 | C8: DESLORA-5MG (DESLORATADINE) B/10CES | F8: Deslora | G8: Active | H8: Tablet | I8: Desloratadine 5 mg | J8: Box of 10 tablets | K8: Oral | L8: Allergies (sneezing, watery eyes, itching), chronic skin hives | M8: 1 tablet daily
A9: 8 | B9: =_xlfn.XLOOKUP(C9,[1]IVW8362itmlist!$C:$C,[1]IVW8362itmlist!$B:$B) -> FG01829 | C9: LORANIQE 10MG (LORATADINE) B/10 CES | F9: Loranique | G9: Active | H9: Tablet | I9: Loratadine 10 mg | J9: Box of 10 tablets | K9: Oral | L9: Hay fever, allergies (sneezing, runny nose, itchy eyes), hives | M9: 1 tablet daily
A10: 9 | B10: =_xlfn.XLOOKUP(C10,[1]IVW8362itmlist!$C:$C,[1]IVW8362itmlist!$B:$B) -> FG03625 | C10: BROMOVAN (BROMHEXINE) 4MG /5ML SIRUP 100ML | F10: Bromovan | G10: Active | H10: Syrup | I10: Bromhexine 4 mg / 5 mL | J10: 100 mL bottle | K10: Oral | L10: Respiratory disorders with excessive mucus (bronchitis, bronchiectasis, pneumoconiosis) | M10: Adults/12+: 10mL TID; 6-12y: 5mL TID; 2-5y: 2.5mL TID
A11: 10 | B11: =_xlfn.XLOOKUP(C11,[1]IVW8362itmlist!$C:$C,[1]IVW8362itmlist!$B:$B) -> FG01041 | C11: DEXOL (CONTRE LA GRIPPE) SUSP.FL/ 100ML | F11: Dexol | G11: Active | H11: Syrup (per 5mL) | I11: Paracetamol 250mg + Dextromethorphan 10mg + Chlorphenamine 2mg + Phenylephrine 5mg | J11: 100 mL bottle | K11: Oral | L11: Cold/flu symptoms (fever, cough, stuffy nose, body aches) | M11: 1–2 teaspoon (5–10mL) three times daily
A12: 11 | B12: =_xlfn.XLOOKUP(C12,[1]IVW8362itmlist!$C:$C,[1]IVW8362itmlist!$B:$B) -> FG01040 | C12: DEXOL (ANTIGRIPPALES) B/10 CAPSULES | F12: Dexol | G12: Active | H12: Capsule | I12: Paracetamol 500mg + Dextromethorphan 15mg + Chlorphenamine 2mg + Phenylephrine 10mg | J12: Box of 10 capsules | K12: Oral | L12: Cold/flu, sinusitis, bronchitis (cough, fever, stuffy nose) | M12: 1 capsule twice daily (adults & children ≥12y)
A13: 12 | B13: =_xlfn.XLOOKUP(C13,[1]IVW8362itmlist!$C:$C,[1]IVW8362itmlist!$B:$B) -> FG02669 | C13: QLINDA GEL (CLINDAMYCINE) T/30G | F13: Qlinda | G13: Active | H13: Gel (Topical) | I13: Clindamycin 1% w/w | J13: Tube of 30g & 60g | K13: Cutaneous | L13: Acne treatment | M13: Apply to clean, dry skin twice daily
... A22: 21 | B22: =_xlfn.XLOOKUP(C22,[1]IVW8362itmlist!$C:$C,[1]IVW8362itmlist!$B:$B) -> FG04828 | C22: LE BOXEUR (ANTI-MOSQUITO) LIQUID 3.5ML | F22: Boxer | G22: Active | H22: Liquid | I22: Natural extracts (camphor, mint, etc.) | J22: 3.5 mL bottle | K22: Oral / External | L22: Antipruritic, analgesic, mosquito repellent, colds, headache, muscle aches | M22: As directed by physician
A23: 22 | B23: =_xlfn.XLOOKUP(C23,[1]IVW8362itmlist!$C:$C,[1]IVW8362itmlist!$B:$B) -> FG04589 | C23: BENZOATE DE BENZYLE (BENZOSOL) 25% 100ML | F23: Benzosol | G23: Active | H23: Topical Solution | I23: Benzyl Benzoate 25% w/v | J23: Bottle of 100 mL | K23: Topical | L23: Scabies (Sarcoptes scabiei), trombidiosis (chiggers)
A24: 23 | B24: =_xlfn.XLOOKUP(C24,[1]IVW8362itmlist!$C:$C,[1]IVW8362itmlist!$B:$B) -> FG01000 | C24: DERMACIDAL (ANTISEPSIE) SOLUTION 125ML | F24: Dermacidal | G24: Active | H24: Solution (Skin) | I24: Benzalkonium chloride 0.5g + Chlorhexidine digluconate 0.2g per 100ml | J24: Bottle of 125ml | K24: Topical (Skin) | L24: Antiseptic for external skin infections; cleansing of cutaneous/mucous affections | M24: Apply minimum twice daily
A25: 24 | B25: =_xlfn.XLOOKUP(C25,[1]IVW8362itmlist!$C:$C,[1]IVW8362itmlist!$B:$B) -> FG04728 | C25: GERMITTOL 50ML LIQUID | F25: Germittol | G25: Active | H25: Solution | I25: Chloroxylenol 4.8% + Terpineol 9.0% + Alcohol 13.1% | J25: Bottles of 50ml & 100ml | K25: Topical (External) | L25: Antiseptic for external skin infections | M25: Apply minimum twice daily
A26: 25 | B26: =_xlfn.XLOOKUP(C26,[1]IVW8362itmlist!$C:$C,[1]IVW8362itmlist!$B:$B) -> FG03425 | C26: V-LAVAGE (ACIDE LACTIQUE) LIQUIDE DE LAVAGE 100ML | F26: V-Lavage | G26: Active | H26: Vaginal Wash Solution | I26: Lactic acid 1.2% + Sea buckthorn oil + Tea tree oil (pH 3.5) | J26: Bottle of 100ml | K26: Vaginal | L26: Antiseptic solution for vaginal care | M26: Apply minimum twice daily
A27: 26 | B27: =_xlfn.XLOOKUP(C27,[1]IVW8362itmlist!$C:$C,[1]IVW8362itmlist!$B:$B) -> FG01403 | C27: FOREDERM ( BETAMETHASONE DIPROPIONATE) CREME 15G | F27: Forederm | G27: Active | H27: Cream (Topical) | I27: Betamethasone dipropionate 0.05% | J27: Tubes of 15g & 30g | K27: Topical | L27: Eczema, dermatitis, allergies, rash (reduces swelling, itching, redness) | M27: Apply minimum twice daily
A28: 27 | B28: =_xlfn.XLOOKUP(C28,[1]IVW8362itmlist!$C:$C,[1]IVW8362itmlist!$B:$B) -> FG03410 | C28: UNIDINE-M (POVIDONE IODE+ METRO) POMMDE 30G | F28: Unidine | G28: Active | H28: Ointment | I28: Povidone Iodized 5% + Metronidazole 1% | J28: Box of 30g ointment | K28: Topical | L28: Broad-spectrum for wounds, traumatic tears, ulcers, cellulitis, bedsores | M28: Apply minimum twice daily
A29: 28 | B29: =_xlfn.XLOOKUP(C29,[1]IVW8362itmlist!$C:$C,[1]IVW8362itmlist!$B:$B) -> FG03408 | C29: UNIDINE (POVIDONE IODEE) 10% SOLUTION 125 ML | F29: Unidine | G29: Active | H29: Solution | I29: Povidone Iodized 10% | J29: Bottle of 125ml | K29: Topical | L29: Skin antisepsis, operative field, wounds, burns, vaginitis | M29: Apply minimum twice daily
A30: 29 | B30: =_xlfn.XLOOKUP(C30,[1]IVW8362itmlist!$C:$C,[1]IVW8362itmlist!$B:$B) -> FG03409 | C30: UNIDINE (POVIDONE-IODEE) 5% POMMADE 20G | F30: Unidine | G30: Active | H30: Ointment | I30: Povidone Iodized 5% | J30: Tube of 20g | K30: Topical | L30: Antiseptic for skin disinfection, minor wounds | M30: Apply minimum twice daily
A31: 30 | B31: =_xlfn.XLOOKUP(C31,[1]IVW8362itmlist!$C:$C,[1]IVW8362itmlist!$B:$B) -> FG00551 | C31: CALMIN (CALAMINE) LOTION 100ML | F31: Calmin Lotion | G31: Active | H31: Lotion | I31: Calamine 8% + Aloe Vera 10% + Light Liquid Paraffin 10% | J31: Bottle of 100ml | K31: Topical | L31: Mild itchiness (sunburn, insect bites, poison ivy, mild skin conditions) | M31: Apply minimum twice daily
A32: 31 | B32: =_xlfn.XLOOKUP(C32,[1]IVW8362itmlist!$C:$C,[1]IVW8362itmlist!$B:$B) -> FG04836 | C32: CLOTRISAN V6 (CLOTRIMAZOLE) B/6 OVULE+APPLOCATOR | F32: Clotrisan | G32: Active | H32: Vaginal Insert / Ovule | I32: Clotrimazole 1% w/w | J32: Box of 6 ovules | K32: Vaginal | L32: Vaginal candidiasis, trichomoniasis, mixed vaginal infections, bacterial vaginitis | M32: 1 insert deeply into vagina each evening for 6 consecutive nights
A33: 32 | B33: =_xlfn.XLOOKUP(C33,[1]IVW8362itmlist!$C:$C,[1]IVW8362itmlist!$B:$B) -> FG04615 | C33: CLOTRISAN (CLOTRIMAZOLE) POUDRE 50G | F33: Clotrisan | G33: Active | H33: Topical Powder | I33: Clotrimazole 1% + Zinc Oxide 1.75% + Dimeticone 2.5% + Talc | J33: Bottle of 50g | K33: Topical | L33: Antifungal for skin infections / rashes | M33: As directed by physician
A34: 33 | B34: =_xlfn.XLOOKUP(C34,[1]IVW8362itmlist!$C:$C,[1]IVW8362itmlist!$B:$B) -> FG00865 | C34: CONVEX PRESERVATIF LISSE B/3PCS | F34: Convex | G34: Active | H34: Condom (Medical Device) | I34: N/A | J34: Box of 3 condoms | K34: Barrier / External | L34: Reduces probability of pregnancy or sexually transmitted infections (STIs) | M34: Single use during intercourse; use as directed
A35: 34 | B35: =_xlfn.XLOOKUP(C35,[1]IVW8362itmlist!$C:$C,[1]IVW8362itmlist!$B:$B) -> FG04792 | C35: TADANIQUE 20MG (TADALAFIL) B/4CES | F35: Tadanique | G35: Active | H35: Tablet | I35: Tadalafil 20 mg | J35: Box of 4 tablets | K35: Oral | L35: Erectile dysfunction (ED), Benign prostatic hyperplasia (BPH), Pulmonary arterial hypertension | M35: 1 tablet once daily, 45 mins to 1 hour before relation
A36: 35 | B36: =_xlfn.XLOOKUP(C36,[1]IVW8362itmlist!$C:$C,[1]IVW8362itmlist!$B:$B) -> FG04089 | C36: SILDEQUE-100MG (SILDENAFIL) B/4CES | F36: Sildeque | G36: Active | H36: Tablet | I36: Sildenafil 100 mg | J36: Box of 4 tablets | K36: Oral | L36: Erectile dysfunction, Pulmonary arterial hypertension | M36: 1 tablet once daily, 45 mins to 1 hour before relation
A37: 36 | B37: =_xlfn.XLOOKUP(C37,[1]IVW8362itmlist!$C:$C,[1]IVW8362itmlist!$B:$B) -> FG04090 | C37: SILDEQUE-50 MG (SILDENAFIL) B/4 CES | F37: Sildeque | G37: Active | H37: Tablet | I37: Sildenafil 50 mg | J37: Box of 4 tablets | K37: Oral | L37: Erectile dysfunction, Pulmonary arterial hypertension
A38: 37 | B38: =_xlfn.XLOOKUP(C38,[1]IVW8362itmlist!$C:$C,[1]IVW8362itmlist!$B:$B) -> FG03412 | C38: UNISPA 10MG (BUSCOPAN) B/ 6 SUPPO | F38: Unispa | G38: Active | H38: Suppository | I38: Hyoscine Butylbromide 10 mg | J38: Box of 6 suppositories | K38: Rectal | L38: Crampy abdominal pain, esophageal spasms, renal colic, bladder spasms | M38: As directed by physician
A39: 38 | B39: =_xlfn.XLOOKUP(C39,[1]IVW8362itmlist!$C:$C,[1]IVW8362itmlist!$B:$B) -> FG03070 | C39: SPARET (MEFENAMIQUE + DICYCLOVIRINE) B/10CES | F39: Sparet | G39: Active | H39: Tablet | I39: Mefenamic Acid 500 mg + Paracetamol 325 mg | J39: Box of 10 tablets | K39: Oral | L39: Joint and muscle pains (adults) | M39: 1 tablet once or twice daily
A40: 39 | B40: =_xlfn.XLOOKUP(C40,[1]IVW8362itmlist!$C:$C,[1]IVW8362itmlist!$B:$B) -> FG03069 | C40: SPARET (DICYCLOVERINE+SIMETICONE) GOUTTES 15ML | F40: Sparet | G40: Active | H40: Oral Drops | I40: Simeticone 40 mg + Dicycloverine 10 mg (per drop) | J40: 15 mL oral drops bottle | K40: Oral | L40: Colicky pain in children | M40: 1 drop/kg/dose, 2–3 times daily
A41: 40 | B41: =_xlfn.XLOOKUP(C41,[1]IVW8362itmlist!$C:$C,[1]IVW8362itmlist!$B:$B) -> FG03071 | C41: SPARET FORTE (MEFENAMIQUE+PARACETAMOL) B/10CES | F41: Sparet | G41: Active | H41: Tablet | I41: Mefenamic Acid 250 mg + Dicyclomine HCl 10 mg | J41: Box of 10 tablets | K41: Oral | L41: Menstrual pain, intestinal/biliary/ureteric colic | M41: 1 tablet twice daily
A42: 41 | B42: =_xlfn.XLOOKUP(C42,[1]IVW8362itmlist!$C:$C,[1]IVW8362itmlist!$B:$B) -> FG03603 | C42: 3 PLUS FORTE (VIT.B1+B6+B12) SIROP 100ML | F42: Trois Plus Forte Suspension | G42: Active | H42: Syrup | I42: Thiamine (B1) 20mg + Pyridoxine (B6) 10mg + Cyanocobalamin (B12) 2mcg per 5mL | J42: Bottle of 100 mL | K42: Oral | L42: Adjunctive therapy for functional asthenia | M42: As directed by physician
A43: 42 | B43: =_xlfn.XLOOKUP(C43,[1]IVW8362itmlist!$C:$C,[1]IVW8362itmlist!$B:$B) -> FG04561 | C43: 3 PLUS FORTE (VIT.B1+B6+B12) B/30CES | F43: Trois Plus Forte Tablet | G43: Active | H43: Tablet | I43: Thiamine (B1) 50mg + Pyridoxine (B6) 50mg + Cyanocobalamin (B12) 500mcg | J43: Box of 3×10 tablets | K43: Oral | L43: Adjunctive therapy for functional asthenia | M43: As directed by physician
A44: 43 | B44: =_xlfn.XLOOKUP(C44,[1]IVW8362itmlist!$C:$C,[1]IVW8362itmlist!$B:$B) -> FG03602 | C44: 3 PLUS FORTE (VIT.B1+B6+B12) INJ. B/10AMP | F44: Trois Plus Forte Injectable | G44: Active | H44: Injection | I44: Thiamine (B1) 100mg + Pyridoxine (B6) 100mg + Cyanocobalamin (B12) 1000mcg per 3mL | J44: Box of 10 ampoules of 3 mL | K44: IM / IV | L44: Adjunctive therapy for functional asthenia | M44: As directed by physician
A45: 44 | B45: =_xlfn.XLOOKUP(C45,[1]IVW8362itmlist!$C:$C,[1]IVW8362itmlist!$B:$B) -> FG00918 | C45: CYPROVITAL (CYPROHEPTADINE+VITAMINES) SIROP 100ML | F45: Cyprovital | G45: Active | H45: Syrup | I45: Cyproheptadine 2mg + Vit B1, B2, B6, Nicotinamide per 5mL | J45: Bottle of 100 mL | K45: Oral | L45: Fortifying and food supplement | M45: As directed by physician
A46: 45 | B46: =_xlfn.XLOOKUP(C46,[1]IVW8362itmlist!$C:$C,[1]IVW8362itmlist!$B:$B) -> FG07115 | C46: CYPROPLEX PLUS (CYPROHEPTADINE+MULTIVITAMINE +LYSINE) SIROP DE 200ML | F46: Cyproplex Plus | G46: Active | H46: Oral Suspension | I46: Cyproheptadine HCl 2 mg per 5 mL | J46: Bottle of 200 mL | K46: Oral | L46: Fortifying and food supplement | M46: As directed by physician
A47: 46 | B47: =_xlfn.XLOOKUP(C47,[1]IVW8362itmlist!$C:$C,[1]IVW8362itmlist!$B:$B) -> FG04095 | C47: U CEE 500MG (VITAMINE C) B/10 X 10 CES | F47: U-Cee 500 | G47: Active | H47: Sucking Tablet | I47: Ascorbic Acid (Vitamin C) 500 mg | J47: Box of 10×10 sucking tablets | K47: Oral (Sublingual/Chew) | L47: Antioxidant; maintains skin, cartilage, teeth, bone, blood vessels | M47: 3 tablets daily
A48: 47 | B48: =_xlfn.XLOOKUP(C48,[1]IVW8362itmlist!$C:$C,[1]IVW8362itmlist!$B:$B) -> FG03566 | C48: ZINQUE (GLUCONATE DE ZINC) SIROP 60ML | F48: Zinque | G48: Active | H48: Syrup | I48: Zinc Gluconate 20 mg per 5 mL | J48: 60 mL bottle | K48: Oral | L48: Zinc deficiency, stunted growth, acute diarrhea, wound healing | M48: <6m: 1/2 dose 10–14d; >6m: 1 dose 14d (or as directed)
A49: 48 | B49: =_xlfn.XLOOKUP(C49,[1]IVW8362itmlist!$C:$C,[1]IVW8362itmlist!$B:$B) -> FG03567 | C49: ZINQUE - DT 20MG (SULFATE DE ZINC ) B/10 CES | F49: Zinque | G49: Active | H49: Tablet | I49: Zinc Sulfate 20 mg | J49: Box of 10 tablets | K49: Oral | L49: Zinc deficiency, stunted growth, acute diarrhea, wound healing | M49: <6m: 1/2 tab 10–14d; >6m: 1 tab 14d (or as directed)
... A83: 82 | B83: =_xlfn.XLOOKUP(C83,[1]IVW8362itmlist!$C:$C,[1]IVW8362itmlist!$B:$B) -> FG02642 | C83: PROTOQ 40MG (PANTOPRAZOLE) INJ. B/1VIAL+ NACL 10ML | F83: Protoq Injectable | G83: Active | H83: Powder for Injection | I83: Pantoprazole 40 mg (lyophilized powder) + NaCl diluent | J83: Vial + Sodium Chloride ampoule | K83: IV | L83: GERD, severe esophagitis, duodenal/gastric ulcer, H. pylori eradication, Zollinger-Ellison, stress ulcer, upper GI bleeding | M83: 1 vial (40 mg) per day
A84: 83 | B84: =_xlfn.XLOOKUP(C84,[1]IVW8362itmlist!$C:$C,[1]IVW8362itmlist!$B:$B) -> FG01281 | C84: ESOQUE 20MG (ESOMEPRAZOLE) INJ. B/1 VIAL+NACL | F84: Esoque Injectable | G84: Active | H84: Powder for Injection | I84: Esomeprazole 20 mg + NaCl diluent | J84: Vial + Sodium Chloride ampoule | K84: IV | L84: GERD, severe esophagitis, duodenal/gastric ulcer, H. pylori, Zollinger-Ellison, stress ulcer, NSAID-induced peptic ulcer
A85: 84 | B85: =_xlfn.XLOOKUP(C85,[1]IVW8362itmlist!$C:$C,[1]IVW8362itmlist!$B:$B) -> FG02694 | C85: RABEQUE 20MG (RABEPRAZOLE) B/ 10 CES | F85: Rabeque | G85: Active | H85: Tablet | I85: Rabeprazole 20 mg | J85: Box of 10 tablets | K85: Oral | L85: Short-term treatment of gastric & duodenal ulcers, GERD | M85: 1 tablet once daily in the morning for 4 weeks
A86: 85 | B86: =_xlfn.XLOOKUP(C86,[1]IVW8362itmlist!$C:$C,[1]IVW8362itmlist!$B:$B) -> FG02695 | C86: RABEQUE 20MG (RABEPRAZOLE) INJ. B/1 VIAL+EAU | F86: Rabeque | G86: Active | H86: Powder for Injection | I86: Rabeprazole 20 mg per vial | J86: Box of 1 vial | K86: IV | L86: Gastric & duodenal ulcers, GERD (alternative to oral PPI) | M86: 1 vial (20 mg) IV once daily
A87: 86 | B87: =_xlfn.XLOOKUP(C87,[1]IVW8362itmlist!$C:$C,[1]IVW8362itmlist!$B:$B) -> FG02696 | C87: RABEQUE-D (RABEPRAZOLE+DOMPERI.) B/ 10 GELULES | F87: Rabeque | G87: Active | H87: Capsule | I87: Rabeprazole 10 mg (modified release) + Domperidone 10 mg | J87: Box of 10 capsules | K87: Oral | L87: Gastric & duodenal ulcers, GERD | M87: 1 capsule once daily in the morning for 4 weeks
A88: 87 | B88: =_xlfn.XLOOKUP(C88,[1]IVW8362itmlist!$C:$C,[1]IVW8362itmlist!$B:$B) -> FG04892 | C88: H -LOC (RANITIDINE) INJ B/5AMP | F88: H Loc | G88: Active | H88: Injectable Solution | I88: Ranitidine 50 mg / 2 mL ampoule | J88: Box of 5 ampoules (2 mL) | K88: IM / IV | L88: Peptic ulcer disease, GERD, Zollinger–Ellison syndrome | M88: As directed by physician
A89: 88 | B89: =_xlfn.XLOOKUP(C89,[1]IVW8362itmlist!$C:$C,[1]IVW8362itmlist!$B:$B) -> FG04758 | C89: MISOPTOL (MISOPROSTOL) 200UG B/4CES | F89: Misoptol | G89: Active | H89: Tablet | I89: Misoprostol 200 mcg | J89: Box of 4 tablets | K89: Oral | L89: Prevention & treatment of stomach ulcers | M89: As directed by physician (Contraindicated in pregnancy)
A90: 89 | B90: =_xlfn.XLOOKUP(C90,[1]IVW8362itmlist!$C:$C,[1]IVW8362itmlist!$B:$B) -> FG04557 | C90: ZOCID 20MG (OMEPRAZOLE) B/10X10 GELULE | F90: Zocid | G90: Active | H90: Capsule | I90: Omeprazole 20 mg | J90: Box of 10×10 capsules | K90: Oral | L90: GERD, peptic ulcer disease, Zollinger–Ellison syndrome | M90: Starting: 60 mg daily (1 tab TID); Max: 360 mg daily
A91: 90 | B91: =_xlfn.XLOOKUP(C91,[1]IVW8362itmlist!$C:$C,[1]IVW8362itmlist!$B:$B) -> FG08683 | C91: NOCI KIT – H. PYLORI (7 KITS DE COMBI) | F91: Noci Kit | G91: Active | H91: Kit (Capsules + Tablets) | I91: Lansoprazole 30mg + Clarithromycin 500mg + Tinidazole 500mg (per kit) | J91: Box of 7 kits | K91: Oral | L91: Against Helicobacter pylori infection | M91: ½ kit twice daily for minimum 7 days
A92: 91 | B92: =_xlfn.XLOOKUP(C92,[1]IVW8362itmlist!$C:$C,[1]IVW8362itmlist!$B:$B) -> FG04098 | C92: UNIGEL (ANTI-ACIDE) B/10X10 CES | F92: Unigel Tablet | G92: Active | H92: Chewable Tablet | I92: Aluminium Hydroxide 500 mg | J92: Box of 10×10 chewable tablets | K92: Oral | L92: Gastric hyperacidity, gastritis, stomach pains, GERD | M92: Adults: 1 chewable tablet four times daily
A93: 92 | B93: =_xlfn.XLOOKUP(C93,[1]IVW8362itmlist!$C:$C,[1]IVW8362itmlist!$B:$B) -> FG02195 | C93: NOCIGEL (ANTIACIDE + ANTIFLATULENT) SUSP. 200ML | F93: Nocigel Syrup | G93: Active | H93: Syrup | I93: Aluminium Hydroxide 225mg + Magnesium Hydroxide 200mg + Algenic Acid 200mg + Mg Trisilicate 250mg + Simethicone 50mg (per 5mL) | J93: Bottle of 200 mL | K93: Oral | L93: Gastric hyperacidity, gastritis, stomach pains, GERD | M93: 5 mL (1 tsp), 2–3 times daily (or as directed)
A94: 93 | B94: =_xlfn.XLOOKUP(C94,[1]IVW8362itmlist!$C:$C,[1]IVW8362itmlist!$B:$B) -> FG04082 | C94: SECOURS (PAIN RELIEF) B/10CES | F94: Secours | G94: Active | H94: Tablet | I94: Diclofenac 50mg + Paracetamol 325mg + Chlorphenamine 4mg + Magnesium Trisilicate 100mg | J94: Box of 10 tablets | K94: Oral | L94: Headache, body pain, fever, toothache, gout pain | M94: Adults & children >14y: 1 tablet twice daily (with/after meals)
A95: 94 | B95: =_xlfn.XLOOKUP(C95,[1]IVW8362itmlist!$C:$C,[1]IVW8362itmlist!$B:$B) -> FG03391 | C95: ULTRA DOZEM (PARA+TRAMADOL) B \10 CES | F95: Ultradozem | G95: Active | H95: Tablet | I95: Tramadol 37.5 mg + Paracetamol 325 mg | J95: Box of 10 tablets | K95: Oral | L95: Moderate to severe pain
A96: 95 | B96: =_xlfn.XLOOKUP(C96,[1]IVW8362itmlist!$C:$C,[1]IVW8362itmlist!$B:$B) -> FG01320 | C96: FELOXAM 20MG (PIROXICAM) B/3X5 SUPPO. | F96: Feloxam Suppositories | G96: Active | H96: Suppository | I96: Piroxicam 20 mg | J96: Box of 15 suppositories | K96: Rectal | L96: Rheumatoid arthritis, osteoarthritis, ankylosing spondylitis | M96: 1 suppository daily (at bedtime)
A97: 96 | B97: =_xlfn.XLOOKUP(C97,[1]IVW8362itmlist!$C:$C,[1]IVW8362itmlist!$B:$B) -> FG01319 | C97: FELOXAM 20MG (PIROXICAM) B/10 CAPSULES | F97: Feloxam Capsule | G97: Active | H97: Capsule | I97: Piroxicam 20 mg | J97: Box of 10 capsules | K97: Oral | L97: Rheumatoid arthritis, osteoarthritis, ankylosing spondylitis | M97: 1 capsule once daily
A98: 97 | B98: =_xlfn.XLOOKUP(C98,[1]IVW8362itmlist!$C:$C,[1]IVW8362itmlist!$B:$B) -> FG06906 | C98: IBUNIQUE FORTE (PARA+IBU+CAF) B/10X10 CAPS | F98: Ibunique Forte | G98: Active | H98: Capsule | I98: Ibuprofen 400 mg + Paracetamol 325 mg + Caffeine 40 mg | J98: Box of 10×10 capsules | K98: Oral | L98: Pain relief, analgesic, antipyretic, anti-inflammatory (cold/flu) | M98: 1 capsule three times daily
A99: 98 | B99: =_xlfn.XLOOKUP(C99,[1]IVW8362itmlist!$C:$C,[1]IVW8362itmlist!$B:$B) -> FG04040 | C99: IBUNIQUE (PARA+IBU+CAF) B/10X10 CAPS | F99: Ibunique Capsules | G99: Active | H99: Capsule | I99: Ibuprofen 200 mg + Paracetamol 325 mg + Caffeine 40 mg | J99: Box of 10×10 capsules | K99: Oral | L99: Pain relief, analgesic, antipyretic, anti-inflammatory (cold/flu) | M99: 1 capsule three times daily
A100: 99 | B100: =_xlfn.XLOOKUP(C100,[1]IVW8362itmlist!$C:$C,[1]IVW8362itmlist!$B:$B) -> FG04096 | C100: UFLAM (PARA+IBU) B/10 X10 CES | F100: Uflam Tablets | G100: Active | H100: Tablet | I100: Ibuprofen 400 mg + Paracetamol 325 mg | J100: Box of 10×10 tablets | K100: Oral | L100: Pain relief, analgesic, antipyretic, anti-inflammatory | M100: 1 tablet three times daily
A101: 100 | B101: =_xlfn.XLOOKUP(C101,[1]IVW8362itmlist!$C:$C,[1]IVW8362itmlist!$B:$B) -> FG06495 | C101: UFLAM (PARACETAMOL+IBUPROFEN) SIROP 60ML | F101: Uflam Oral Suspension | G101: Active | H101: Oral Suspension | I101: Ibuprofen 50 mg + Paracetamol 125 mg per 5 mL | J101: Bottle of 60 mL | K101: Oral | L101: Pain relief, analgesic, antipyretic, anti-inflammatory | M101: 5–10 mL three times daily (as directed)
A102: 101 | B102: =_xlfn.XLOOKUP(C102,[1]IVW8362itmlist!$C:$C,[1]IVW8362itmlist!$B:$B) -> FG00409 | C102: BANAFEN 100MG (IBUPROFEN) SUSPENSION FL/100ML | F102: Banafen | G102: Active | H102: Syrup | I102: Ibuprofen 100 mg per 5 mL | J102: Bottle of 100 mL | K102: Oral | L102: Fever and minor aches/pain due to common cold/flu (children) | M102: 5 mL three times daily (usual)
A103: 102 | B103: =_xlfn.XLOOKUP(C103,[1]IVW8362itmlist!$C:$C,[1]IVW8362itmlist!$B:$B) -> FG04902 | C103: IPRO - 400 ((IBUPROFENE) MG BT/10X10CES | F103: Ipro-400 | G103: Active | H103: Tablet | I103: Ibuprofen 400 mg | J103: Box of 10×10 tablets | K103: Oral | L103: Headache, dental pain, menstrual cramps, muscle aches, arthritis | M103: 1 tablet two or three times daily
A104: 103 | B104: =_xlfn.XLOOKUP(C104,[1]IVW8362itmlist!$C:$C,[1]IVW8362itmlist!$B:$B) -> FG01039 | C104: DEXIBU (DEXIBUPROFEN ) SUSPENSION 60ML | F104: Dexibu | G104: Active | H104: Syrup | I104: Dexibuprofen 12 mg per mL | J104: Bottle of 60 mL | K104: Oral | L104: Pain and inflammation in infants | M104: At least 5 mL, 2–3 times daily (as directed)
A105: 104 | B105: =_xlfn.XLOOKUP(C105,[1]IVW8362itmlist!$C:$C,[1]IVW8362itmlist!$B:$B) -> FG04626 | C105: DICLIQUE SPORT GEL T/30G | F105: Diclique Sport Gel | G105: Active | H105: Gel (Topical) | I105: Diclofenac diethylamine 1.16% + Linseed oil 3% + Methyl salicylate 10% + Menthol 5% | J105: Tube of 30 g | K105: Topical | L105: Gout, back pain, osteoarthritis, rheumatoid arthritis, joint/muscle pain | M105: Apply as directed by physician
A106: 105 | B106: =_xlfn.XLOOKUP(C106,[1]IVW8362itmlist!$C:$C,[1]IVW8362itmlist!$B:$B) -> FG03868 | C106: DICLIQUE (DICLO.+PARA.) B/10X10CES | F106: Diclique Suppositories | G106: Active | H106: Suppository | I106: Diclofenac sodium 100 mg | J106: Box of 10 suppositories | K106: Rectal | L106: Acute/chronic inflammatory rheumatism, arthritis, low back pain, radicalgia | M106: 1 suppository per day
A107: 106 | B107: =_xlfn.XLOOKUP(C107,[1]IVW8362itmlist!$C:$C,[1]IVW8362itmlist!$B:$B) -> FG04842 | C107: DICLIQUE PLUS (DICLO+PARA+CHLORZ) B/10X10 CES | F107: Diclique Plus | G107: Active | H107: Tablet | I107: Diclofenac 50 mg + Paracetamol 325 mg + Chlorzoxazone 250 mg | J107: Box of 10×10 tablets | K107: Oral | L107: Gout, back pain, osteoarthritis, rheumatoid arthritis, toothache, muscle ache | M107: As directed by physician (contains 325mg Paracetamol/tab)
... A121: 120 | B121: =_xlfn.XLOOKUP(C121,[1]IVW8362itmlist!$C:$C,[1]IVW8362itmlist!$B:$B) -> FG02488 | C121: PERFAC 100MG (PARACETAMOL) B/10 SUPPOS | F121: Perfac | G121: Active | H121: Suppository | I121: Paracetamol 100 mg | J121: Box of 10 suppositories | K121: Rectal | L121: Moderate pain, fever (when oral route not possible) | M121: Children 6 months – 1 year: as directed
A122: 121 | B122: =_xlfn.XLOOKUP(C122,[1]IVW8362itmlist!$C:$C,[1]IVW8362itmlist!$B:$B) -> FG04070 | C122: PERFAC 750MG (PARACETAMOL) I.M/I.V INJ. B/5AMP | F122: Perfac | G122: Active | H122: Injectable Solution | I122: Paracetamol 750 mg per 5 mL ampoule | J122: Box of 5 ampoules | K122: IM / IV | L122: Post-operative moderate pain, fever (urgent/IV route needed)
A123: 122 | B123: =_xlfn.XLOOKUP(C123,[1]IVW8362itmlist!$C:$C,[1]IVW8362itmlist!$B:$B) -> FG01590 | C123: HIFER-Z (ANTI-ANEMIC) SIROP 200ML | F123: Hifer-Z Syrup | G123: Active | H123: Syrup | I123: Protein hydrolysate 1g + Iron 32mg + Zinc 44mg + Folic acid 1mg + B6 1.5mg + B12 7.5mcg + Lysine 50mg + Niacinamide 45mg + D-panthenol 5mg (per 15mL) | J123: Bottle of 200 mL | K123: Oral | L123: Food vitaminic supplement | M123: 1-6y: 2.5mL BID; 6-12y: 5mL BID; >12y: 10mL BID
A124: 123 | B124: =_xlfn.XLOOKUP(C124,[1]IVW8362itmlist!$C:$C,[1]IVW8362itmlist!$B:$B) -> FG01589 | C124: HIFER 20MG/ML (SACCHAROSE FER) INJ. 5ML B/1 AMP | F124: Hifer Injectable | G124: Active | H124: Injectable Solution | I124: Iron sucrose 20 mg per mL | J124: Box of 1 ampoule (5 mL) | K124: IV | L124: Iron deficiency anemia in kidney disease | M124: As directed by physician
A125: 124 | B125: =_xlfn.XLOOKUP(C125,[1]IVW8362itmlist!$C:$C,[1]IVW8362itmlist!$B:$B) -> FG01587 | C125: HIFER (FER+ACIDE FOLIC) B/ 3X10 CES | F125: Hifer Tablet | G125: Active | H125: Chewable Tablet | I125: Iron 100 mg + Folic Acid 1000 mcg | J125: Box of 3×10 tablets | K125: Oral | L125: Prevention of iron/folic acid deficiency (pregnancy); iron deficiency anemia | M125: 1 tablet once daily (from 3rd month of pregnancy)
A126: 125 | B126: =_xlfn.XLOOKUP(C126,[1]IVW8362itmlist!$C:$C,[1]IVW8362itmlist!$B:$B) -> FG01253 | C126: EPOFIT 4000IU (ERYTHROPOIETINE) B/1 SER.PREREMPLIE | F126: Epofit | G126: Active | H126: Pre-filled Syringe | I126: Erythropoietin 4000 IU per 1.0 mL syringe | J126: Box of 1 pre-filled syringe (1 mL) | K126: SC / IV | L126: Anemia in chronic renal failure, chemotherapy-induced anemia, major surgery, HIV-related anemia | M126: Correction: 50 IU/kg 3x/week; adjust by 25 IU/kg; Maintenance: 75–300 IU/kg/week
A127: 126 | B127: =_xlfn.XLOOKUP(C127,[1]IVW8362itmlist!$C:$C,[1]IVW8362itmlist!$B:$B) -> FG06923 | C127: ZOLETRIX 4MG (ACIDE ZOLEDRONIQUE) INJECTABLE B/1 VIAL | F127: Zoletrix | G127: Active | H127: IV Infusion | I127: Zoledronic acid 4 mg per vial | J127: Box of 1 vial (100 mL) | K127: IV | L127: Skeletal-related events (pathological fractures, spinal compression) in malignancies; tumor-induced hypercalcaemia | M127: As directed by physician
A128: 127 | B128: =_xlfn.XLOOKUP(C128,[1]IVW8362itmlist!$C:$C,[1]IVW8362itmlist!$B:$B) -> FG06917 | C128: PACLITRIX 300MG / 50ML (PACLITAXEL) INJECTABLE B/1 VIAL | F128: Paclitrix | G128: Active | H128: Injectable Solution | I128: Paclitaxel 300 mg per vial | J128: Box of 1 vial | K128: IV | L128: Ovarian, breast, lung, Kaposi sarcoma, cervical, pancreatic cancer | M128: As directed by physician
A129: 128 | B129: =_xlfn.XLOOKUP(C129,[1]IVW8362itmlist!$C:$C,[1]IVW8362itmlist!$B:$B) -> FG06924 | C129: PACLITRIX‐100MG (PACLITAXEL) INJECTABLE B/1 VIAL | F129: Paclitrix | G129: Active | H129: Injectable Solution | I129: Paclitaxel 100 mg per vial | J129: Box of 1 vial | K129: IV | L129: Ovarian, breast, lung, Kaposi sarcoma, cervical, pancreatic cancer | M129: As directed by physician
A130: 129 | B130: =_xlfn.XLOOKUP(C130,[1]IVW8362itmlist!$C:$C,[1]IVW8362itmlist!$B:$B) -> FG06915 | C130: CYTOCIS 50MG / 5ML (CISPLATIN) INJECTABLE B/1 VIAL | F130: Cytocis 50 | G130: Active | H130: Powder for Injection | I130: Cisplatin 50 mg per vial | J130: Box of 1 vial | K130: IV | L130: Testicular, ovarian, bladder, head/neck, non-small cell & small cell lung, cervical carcinoma | M130: As directed by physician
A131: 130 | B131: =_xlfn.XLOOKUP(C131,[1]IVW8362itmlist!$C:$C,[1]IVW8362itmlist!$B:$B) -> FG06914 | C131: CYTOCIS 10MG / 20ML (CISPLATIN) INJECTABLE B/1 VIAL | F131: Cytocis 10 | G131: Active | H131: Powder for Injection | I131: Cisplatin 10 mg per vial | J131: Box of 1 vial | K131: IV | L131: Testicular, ovarian, bladder, head/neck, non-small cell & small cell lung, cervical carcinoma | M131: As directed by physician
A132: 131 | B132: =_xlfn.XLOOKUP(C132,[1]IVW8362itmlist!$C:$C,[1]IVW8362itmlist!$B:$B) -> FG07147 | C132: CYTODOX 50MG (DOXORUBICIN) INJECTABLE B/1 VIAL | F132: Cytodox 50 | G132: Active | H132: Injectable Solution | I132: Doxorubicin 2 mg/mL (50 mg per 25 mL vial) | J132: Box of 1 vial (25 mL) | K132: IV | L132: Acute leukaemia, lymphomas, sarcomas, paediatric malignancies, breast & lung carcinomas | M132: As directed by physician
A133: 132 | B133: =_xlfn.XLOOKUP(C133,[1]IVW8362itmlist!$C:$C,[1]IVW8362itmlist!$B:$B) -> FG06910 | C133: CYTODOX 10MG (DOXORUBICIN) INJECTABLE B/1 VIAL | F133: Cytodox 10 | G133: Active | H133: Injectable Solution | I133: Doxorubicin 2 mg/mL (10 mg per 5 mL vial) | J133: Box of 1 vial (5 mL) | K133: IV | L133: Acute leukaemia, lymphomas, sarcomas, paediatric malignancies, breast & lung carcinomas | M133: As directed by physician
A134: 133 | B134: =_xlfn.XLOOKUP(C134,[1]IVW8362itmlist!$C:$C,[1]IVW8362itmlist!$B:$B) -> FG07140 | C134: BLEOTRIX (BLECOMYCIN SULFATE INJ.) B/1VIAL | F134: Bleotrix | G134: Active | H134: Powder for Injection | I134: Bleomycin 15 IU per vial | J134: Box of 1 vial | K134: IV / IM | L134: Skin, oral cavity, head/neck cancer; lymphomas; testicular cancer; fluid accumulation in chest | M134: As directed by physician
... A136: 135 | B136: =_xlfn.XLOOKUP(C136,[1]IVW8362itmlist!$C:$C,[1]IVW8362itmlist!$B:$B) -> FG03396 | C136: UNICAINE 2% GEL (LIDOCAINE) T/30G | F136: Unicaine | G136: Active | H136: Topical Cream | I136: Lidocaine 2% w/v | J136: Tube of 30 g | K136: Topical (Cutaneous/Mucosal) | L136: Oral/gastric pain; local anesthesia before stomatological, laryngoscopic, esophageal procedures | M136: Apply as needed (2 applications recommended)
A137: 136 | B137: =_xlfn.XLOOKUP(C137,[1]IVW8362itmlist!$C:$C,[1]IVW8362itmlist!$B:$B) -> FG04930 | C137: UNICAINE PLUS (LIDOCAINE+ADRENALINE) INJ. FL/20ML | F137: Unicaine | G137: Active | H137: Injectable Solution | I137: Lidocaine 20 mg + Adrenaline 0.0125 mg per mL | J137: Vial of 20 mL | K137: Injection (Infiltration) | L137: Local, regional, intra-articular, periarticular, sympathetic infiltration anesthesia
A138: 137 | B138: =_xlfn.XLOOKUP(C138,[1]IVW8362itmlist!$C:$C,[1]IVW8362itmlist!$B:$B) -> FG04097 | C138: UNICAINE 2% (LIDOCAIN) INJ. FL/20ML | F138: Unicaine | G138: Active | H138: Injectable Solution | I138: Lidocaine 2 mg per mL | J138: Vial of 20 mL | K138: Injection (Local-regional) | L138: Local-regional anesthesia (adults & children >1 year) | M138: As directed by anesthetist
A139: 138 | B139: =_xlfn.XLOOKUP(C139,[1]IVW8362itmlist!$C:$C,[1]IVW8362itmlist!$B:$B) -> FG02922 | C139: SEVOFLURANE (SOJOURN) ANESTHESIQUE A INHALER 250ML | F139: Sojourn | G139: Active | H139: Inhalation Vapour | I139: Sevoflurane 100% v/v | J139: Bottle of 250 mL | K139: Inhalation | L139: Induction & maintenance of general anesthesia (adults & children) | M139: As directed by anesthetist
A140: 139 | B140: =_xlfn.XLOOKUP(C140,[1]IVW8362itmlist!$C:$C,[1]IVW8362itmlist!$B:$B) -> FG01658 | C140: ISOFLURANE (ISORANE) ANESTHESIQUE A INHALER 250ML | F140: Isorane | G140: Active | H140: Inhalation Vapour | I140: Isoflurane 100% v/v | J140: Bottle of 250 mL | K140: Inhalation | L140: Induction & maintenance of general anesthesia | M140: As directed by anesthetist
A141: 140 | B141: =_xlfn.XLOOKUP(C141,[1]IVW8362itmlist!$C:$C,[1]IVW8362itmlist!$B:$B) -> FG01553 | C141: HALOTHANE (FLUOTHANE) ANESTHESIQUE A INHALER 250ML | F141: Fluothane | G141: Active | H141: Inhalation Vapour | I141: Halothane 100% v/v | J141: Bottle of 250 mL | K141: Inhalation | L141: Induction & maintenance of general anesthesia | M141: As directed by anesthetist
A142: 141 | B142: =_xlfn.XLOOKUP(C142,[1]IVW8362itmlist!$C:$C,[1]IVW8362itmlist!$B:$B) -> FG02332 | C142: OTOBIOTIC GOUTTES OTIQUES 5ML | F142: Otobiotic | G142: Active | H142: Ear Drops | I142: Chloramphenicol 5% + Beclomethasone 0.025% + Lignocaine 2% + Clotrimazole 1% (per 5 mL) | J142: Bottle of 5 mL | K142: Otic | L142: External & media otitis, acute otitis externa | M142: 2–3 drops, 2–3 times daily
A143: 142 | B143: =_xlfn.XLOOKUP(C143,[1]IVW8362itmlist!$C:$C,[1]IVW8362itmlist!$B:$B) -> FG02246 | C143: OCUTIM 0.50% (TIMOLOL) COLLYRE 10ML | F143: OCUTIM | G143: Active | H143: Eye Drops | I143: Timolol 0.5% w/v | J143: Bottle of 10 mL | K143: Ophthalmic | L143: Ocular hypertension, chronic open-angle glaucoma, secondary glaucoma | M143: 1 drop (0.5%) in affected eye twice daily
A144: 143 | B144: =_xlfn.XLOOKUP(C144,[1]IVW8362itmlist!$C:$C,[1]IVW8362itmlist!$B:$B) -> FG00740 | C144: CIPROQUE (CIPROFLOXIN) COLLYRE 10ML | F144: CIPROQUE | G144: Active | H144: Eye Drops | I144: Ciprofloxacin 0.3% w/v (as HCl) | J144: Bottle of 10 mL | K144: Ophthalmic | L144: Conjunctivitis (pinkeye), corneal ulcers (bacterial infections) | M144: 1 drop as directed (tilt head, look upward, close eyes 1–2 min)
A145: 144 | B145: =_xlfn.XLOOKUP(C145,[1]IVW8362itmlist!$C:$C,[1]IVW8362itmlist!$B:$B) -> FG01639 | C145: INDONIQUE 0.1% (INDOMETHACINE) COLLYRE 10ML | F145: Indonique | G145: Active | H145: Eye Drops | I145: Indomethacin 0.1% w/v | J145: Bottle of 10 mL | K145: Ophthalmic | L145: Prevention of per-operative miosis during cataract surgery; post-surgical inflammation | M145: Pre-op: 1 drop every 30 min (2 hrs before); Post-op: 1 drop 4–6 times daily for 1 month
A146: 145 | B146: =_xlfn.XLOOKUP(C146,[1]IVW8362itmlist!$C:$C,[1]IVW8362itmlist!$B:$B) -> FG02256 | C146: OFLOQUE 200MG (OFLOXACINE) B/10 CES | F146: Ofloque 200 | G146: Active | H146: Tablet | I146: Ofloxacin 200 mg | J146: Box of 10 tablets | K146: Oral | L146: Pyelonephritis, complicated UTIs, prostatitis, pelvic inflammatory disease, sepsis | M146: Up to 400 mg once daily (or divided if >400 mg)
A147: 146 | B147: =_xlfn.XLOOKUP(C147,[1]IVW8362itmlist!$C:$C,[1]IVW8362itmlist!$B:$B) -> FG03518 | C147: WAXORT (BICARBONATE) 5% GOUTTE OTIQUE 10ML | F147: Waxort | G147: Active | H147: Ear Drops | I147: Sodium Bicarbonate 5% w/v | J147: Bottle of 10 mL | K147: Otic | L147: Soften dry or hardened earwax | M147: 3–4 drops twice daily for up to 7 days
A148: 147 | B148: =_xlfn.XLOOKUP(C148,[1]IVW8362itmlist!$C:$C,[1]IVW8362itmlist!$B:$B) -> FG02607 | C148: PRETGESTAN 200MG (PROGESTERONE) B/15 CAP ORALE | F148: Pretgestan 200 | G148: Active | H148: Capsule | I148: Progesterone 200 mg | J148: Box of 15 capsules | K148: Oral / Vaginal | L148: Progesterone deficiency (menstrual disorders, premenstrual disorders, menopause, IVF, recurrent abortion) | M148: 200 mg at bedtime Day 15–26 OR 100 mg Day 1–25
A149: 148 | B149: =_xlfn.XLOOKUP(C149,[1]IVW8362itmlist!$C:$C,[1]IVW8362itmlist!$B:$B) -> FG02606 | C149: PRETGESTAN 100MG (PROGESTERONE) B/30 CAP ORALE | F149: Pretgestan 100 | G149: Active | H149: Capsule | I149: Progesterone 100 mg | J149: Box of 30 capsules | K149: Oral / Vaginal | L149: Progesterone deficiency (menstrual disorders, premenstrual disorders, menopause, IVF, recurrent abortion) | M149: 200 mg at bedtime Day 15–26 OR 100 mg Day 1–25
... A161: 160 | B161: =_xlfn.XLOOKUP(C161,[1]IVW8362itmlist!$C:$C,[1]IVW8362itmlist!$B:$B) -> FG02794 | C161: ROVAS 10MG (ROSUVASTATIN) B/30 CES | F161: Rovas | G161: Active | H161: Tablet | I161: Rosuvastatin 10 mg | J161: Box of 30 tablets | K161: Oral | L161: Hypercholesterolaemia, hypertriglyceridemia, mixed dyslipidemia, CV event prevention | M161: 5–20 mg once daily (start dose 5–10 mg)
A162: 161 | B162: =_xlfn.XLOOKUP(C162,[1]IVW8362itmlist!$C:$C,[1]IVW8362itmlist!$B:$B) -> FG02796 | C162: ROVAS 5MG (ROSUVASTATIN) B/30CES | F162: Rovas | G162: Active | H162: Tablet | I162: Rosuvastatin 5 mg | J162: Box of 30 tablets | K162: Oral | L162: Hypercholesterolaemia, hypertriglyceridemia, mixed dyslipidemia, CV event prevention
A163: 162 | B163: =_xlfn.XLOOKUP(C163,[1]IVW8362itmlist!$C:$C,[1]IVW8362itmlist!$B:$B) -> FG00582 | C163: CARCA 6.25MG (CARVEDILOL) B/30CES | F163: Carca | G163: Active | H163: Tablet | I163: Carvedilol 6.25 mg | J163: Box of 30 tablets | K163: Oral | L163: Essential hypertension, chronic stable angina, moderate-severe chronic heart failure | M163: Once daily; max single dose 25 mg, max daily 50 mg
A164: 163 | B164: =_xlfn.XLOOKUP(C164,[1]IVW8362itmlist!$C:$C,[1]IVW8362itmlist!$B:$B) -> FG00581 | C164: CARCA 3.125MG (CARVEDILOL) B/30CES | F164: Carca | G164: Active | H164: Tablet | I164: Carvedilol 3.125 mg | J164: Box of 30 tablets | K164: Oral | L164: Essential hypertension, chronic stable angina, moderate-severe chronic heart failure | M164: Once daily; max single dose 25 mg, max daily 50 mg
